Workbook

Sheet Questions
A1: ref | B1: status | C1: chapter | D1: difficulty | E1: title | F1: fact1_label | G1: fact1_value | H1: fact2_label | I1: fact2_value | J1: fact3_label | K1: fact3_value | L1: fact4_label | M1: fact4_value | N1: question | O1: option_A | P1: option_B | Q1: option_C | R1: option_D | S1: answer | T1: explanation | U1: why_not_A | V1: why_not_B | W1: why_not_C | X1: why_not_D | Y1: quote_1_source | Z1: quote_1 | AA1: quote_2_source | AB1: quote_2 | AC1: citation | AD1: verify | AE1: as_of | AF1: reviewer_notes | AG1: check
A2: ONB/ELG/101 | B2: live | C2: II | D2: 1 | E2: Home regulator outside IOSCO | F2: Applicant | G2: Halden Value Fund, a regulated fund | H2: Home regulator | I2: Not an IOSCO MMoU (Appendix A) signatory, and no bilateral MoU with SEBI | J2: Set up in | K2: Its home country, not an IFSC | L2: Requested | M2: Category II | N2: Can the DDP register it? | O2: Yes, as Category II | P2: No. It fails the home-regulator test in Reg 4(d) | Q2: Yes, if its manager is from a FATF member country | R2: Yes, as Category I, because it is regulated | S2: B | T2: Reg 4(d) requires the applicant to be resident in a country whose securities regulator has signed the IOSCO MMoU (Appendix A) or has a bilateral MoU with SEBI. The two exceptions are a government investor from a country approved by the Government of India, and an applicant set up in an IFSC. | U2: Choosing a category doesn't cure eligibility. Reg 4 applies to every category, so Category II is still blocked. | W2: The FATF-manager test only helps an applicant get into Category I under Reg 5. It doesn't override Reg 4(d). | X2: Being regulated affects the category, but the applicant has to pass Reg 4(d) first. | Y2: SEBI (FPI) Regulations, 2019, Regulation 4(d) | Z2: (d) the applicant is a resident of the country whose securities market regulator is a signatory to the International Organization of Securities Commission's Multilateral Memorandum of Understanding (Appendix A Signatories) or a signatory to the bilateral Memorandum of Understanding with the Board: Provided that an applicant being Government or Government related investor shall be considered as eligible for registration, if such applicant is a resident in the country as may be approved by the Government of India; | AC2: FPI Regs 2019, Reg 4(d) and proviso; Op. Guidelines Part A 2(i) | AE2: Oct 2026 | AG2: =IF(A2="","",IF(COUNTA(O2:R2)<4,"Needs 4 options",IF(ISERROR(FIND(UPPER(S2),"ABCD"))+(LEN(S2)<>1),"Answer must be A-D",IF(OR(D2<1,D2>3),"Difficulty must be 1-3",IF(OR(N2="",T2=""),"Missing question or explanation",IF(COUNTBLANK(U2:X2)<>1,"Need 3 why-not texts",IF(INDEX(U2:X2,1,FIND(UPPER(S2),"ABCD"))<>"","Why-not filled for the answer",IF(AND(B2<>"live",B2<>"draft",B2<>"retired"),"Status must be live/draft/retired","OK")))))))) -> OK
A3: ONB/CAT/102 | B3: live | C3: II | D3: 2 | E3: Bank whose central bank isn't in the BIS | F3: Applicant | G3: Commercial bank, licensed by its home banking regulator | H3: Home central bank | I3: Not a member of the Bank for International Settlements | J3: India presence | K3: None | L3: Requested | M3: Category I, as a regulated bank | N3: Where does this applicant land? | O3: Category I, as a bank regulated by its home banking regulator | P3: Category II, which the guidelines allow for such banks | Q3: Not eligible in any category, because of the BIS test | R3: Category I, once RBI approves the application | S3: B | T3: A bank applicant is expected to come from a country whose central bank is a BIS member (Reg 4(e)). The guidelines let a bank regulated at home whose central bank isn't a BIS member seek registration under Category II instead. | U3: Category I for a bank assumes its central bank is a BIS member, which isn't the case here. | W3: Too strict. The guidelines expressly let this bank apply under Category II. | X3: No RBI approval converts this into Category I. RBI is consulted only for banks with an Indian presence. | Y3: SEBI Operational Guidelines for FPIs and DDPs, Part A 3(i) | Z3: In case a bank FPI applicant is regulated by the banking sector regulator in its home jurisdiction, but the central bank of that country is not a member of BIS, the FPI can seek registration under Category II. | AC3: FPI Regs 2019, Reg 4(e); Op. Guidelines Part A 3(i) | AE3: Oct 2026 | AG3: =IF(A3="","",IF(COUNTA(O3:R3)<4,"Needs 4 options",IF(ISERROR(FIND(UPPER(S3),"ABCD"))+(LEN(S3)<>1),"Answer must be A-D",IF(OR(D3<1,D3>3),"Difficulty must be 1-3",IF(OR(N3="",T3=""),"Missing question or explanation",IF(COUNTBLANK(U3:X3)<>1,"Need 3 why-not texts",IF(INDEX(U3:X3,1,FIND(UPPER(S3),"ABCD"))<>"","Why-not filled for the answer",IF(AND(B3<>"live",B3<>"draft",B3<>"retired"),"Status must be live/draft/retired","OK")))))))) -> OK
A4: ONB/BNK/103 | B4: live | C4: II | D4: 2 | E4: Foreign bank with an Indian branch | F4: Applicant | G4: Proprietary investment arm of a European bank | H4: Group in India | I4: The bank has a branch in Mumbai | J4: Requested | K4: Category I | L4: Documents | M4: Complete | N4: What extra step applies before you register it? | O4: None. Process it like any other Category I bank | P4: Send it to SEBI first, which gets RBI's comments | Q4: Ask the applicant to get RBI's approval directly | R4: Register it now, then tell RBI within 7 working days of approval | S4: B | T4: When the applicant or its group entity is a bank with a branch or representative office in India, or is a central bank, the DDP sends the form to SEBI. SEBI asks RBI for comments and passes them to the DDP to consider. This isn't repeated at continuance. | U4: The Indian branch triggers a reference to SEBI and RBI. Skipping it is a process breach. | W4: The DDP routes the form through SEBI. The applicant doesn't go to RBI itself. | X4: RBI's comments come before registration, not after it. | Y4: SEBI Operational Guidelines for FPIs and DDPs, Part A 3(i) | Z4: In case an applicant/ its group entity is (i) bank or its subsidiary and has a bank branch/representative office in India or (ii) a central bank or its subsidiary, the respective DDP shall forward the application form to SEBI. SEBI would in turn request RBI to provide its comments. Based on the comments received from RBI, SEBI would notify the comments of RBI to DDP to consider while processing such applications. | AC4: Op. Guidelines Part A 3(i) | AE4: Oct 2026 | AG4: =IF(A4="","",IF(COUNTA(O4:R4)<4,"Needs 4 options",IF(ISERROR(FIND(UPPER(S4),"ABCD"))+(LEN(S4)<>1),"Answer must be A-D",IF(OR(D4<1,D4>3),"Difficulty must be 1-3",IF(OR(N4="",T4=""),"Missing question or explanation",IF(COUNTBLANK(U4:X4)<>1,"Need 3 why-not texts",IF(INDEX(U4:X4,1,FIND(UPPER(S4),"ABCD"))<>"","Why-not filled for the answer",IF(AND(B4<>"live",B4<>"draft",B4<>"retired"),"Status must be live/draft/retired","OK")))))))) -> OK
A5: ONB/CAT/104 | B5: live | C5: II | D5: 2 | E5: Unregulated Luxembourg partnership | F5: Applicant | G5: Lindqvist Credit SCSp, Luxembourg | H5: Fund status | I5: Unregulated limited partnership | J5: Manager | K5: Luxembourg AIFM, appropriately regulated, registered with SEBI as a Category I FPI | L5: Undertaking | M5: Manager accepts responsibility for the fund's acts and omissions | N5: Which category? | O5: Category I | P5: Category II, because the fund itself is unregulated | Q5: Not eligible | R5: Category II until the fund is regulated | S5: A | T5: Under Reg 5(a)(iv)(II), an unregulated fund from a FATF member country is Category I when its manager is appropriately regulated, is registered as a Category I FPI, and takes responsibility for the fund's acts and omissions. Luxembourg is a FATF member. | V5: Reg 5(a)(iv)(II) lets an unregulated fund from a FATF country take Category I through a regulated Category I manager. | W5: Unregulated funds can register. Reg 5(b)(viii) even lists them under Category II. | X5: Category I is available now, without the fund being regulated. | Y5: SEBI (FPI) Regulations, 2019, Regulation 5(a)(iv) | Z5: (iv) Entities from the Financial Action Task Force member countries , or from any country specified by the Central Government by an order or by way of an agreement or treaty with other sovereign Governments, which are – I. appropriately regulated funds; II. unregulated funds whose investment manager is appropriately regulated and registered as a Category I foreign portfolio investor: Provided that the investment manager undertakes the responsibility of all the acts of commission or omission of such unregulated fund; | AC5: FPI Regs 2019, Reg 5(a)(iv)(II) | AE5: Oct 2026 | AG5: =IF(A5="","",IF(COUNTA(O5:R5)<4,"Needs 4 options",IF(ISERROR(FIND(UPPER(S5),"ABCD"))+(LEN(S5)<>1),"Answer must be A-D",IF(OR(D5<1,D5>3),"Difficulty must be 1-3",IF(OR(N5="",T5=""),"Missing question or explanation",IF(COUNTBLANK(U5:X5)<>1,"Need 3 why-not texts",IF(INDEX(U5:X5,1,FIND(UPPER(S5),"ABCD"))<>"","Why-not filled for the answer",IF(AND(B5<>"live",B5<>"draft",B5<>"retired"),"Status must be live/draft/retired","OK")))))))) -> OK
A6: ONB/CAT/105 | B6: live | C6: II | D6: 3 | E6: Cayman fund, New York manager | F6: Applicant | G6: Halcyon Opportunities Fund Ltd, Cayman Islands | H6: Fund status | I6: Unregulated | J6: Manager | K6: New York adviser, registered with SEBI as a Category I FPI | L6: Undertaking | M6: Manager accepts responsibility for the fund | N6: Which category? | O6: Category II, because Cayman isn't a FATF member | P6: Category I, under Reg 5(a)(v)(A) | Q6: Not eligible | R6: Category I only if Cayman regulates the fund | S6: B | T6: Reg 5(a)(v)(A) looks at the manager, not where the fund sits. An entity whose manager is from a FATF member country and is registered as a Category I FPI qualifies for Category I, provided the manager takes responsibility. Without that registration and undertaking, the fund would fall to Category II. | U6: That would be right under Reg 5(a)(iv), which looks at the fund's country. Reg 5(a)(v)(A) looks at the manager's. | W6: Nothing here fails the Reg 4 eligibility tests, and unregulated funds can register. | X6: The fund doesn't need to be regulated. The manager route gives Category I. | Y6: SEBI (FPI) Regulations, 2019, Regulation 5(a)(v) | Z6: (v) An entity (A) whose investment manager is from the Financial Action Task Force member country and such an investment manager is registered as a Category I foreign portfolio investor; or (B) which is at least seventy-five per cent owned, directly or indirectly by another entity, eligible under sub-clause (ii), (iii) and (iv) of clause (a) of this regulation and such an eligible entity is from a Financial Action Task Force member country: Provided that such an investment manager or eligible entity undertakes the responsibility of all the acts of commission or omission of the applicants seeking registration under this sub-clause. | AC6: FPI Regs 2019, Reg 5(a)(v)(A) and proviso | AE6: Oct 2026 | AG6: =IF(A6="","",IF(COUNTA(O6:R6)<4,"Needs 4 options",IF(ISERROR(FIND(UPPER(S6),"ABCD"))+(LEN(S6)<>1),"Answer must be A-D",IF(OR(D6<1,D6>3),"Difficulty must be 1-3",IF(OR(N6="",T6=""),"Missing question or explanation",IF(COUNTBLANK(U6:X6)<>1,"Need 3 why-not texts",IF(INDEX(U6:X6,1,FIND(UPPER(S6),"ABCD"))<>"","Why-not filled for the answer",IF(AND(B6<>"live",B6<>"draft",B6<>"retired"),"Status must be live/draft/retired","OK")))))))) -> OK
A7: ONB/NRI/106 | B7: live | C7: II | D7: 3 | E7: NRI general partner runs the fund | F7: Applicant | G7: Meridian Growth Fund LP, Delaware | H7: Largest NRI | I7: 20% of the corpus | J7: All NRI/OCI/RI | K7: 45% of the corpus | L7: Control | M7: An NRI is the general partner. The manager isn't registered with SEBI. | N7: Is the applicant eligible? | O7: Yes. Both percentages are inside the limits | P7: No. NRIs can't be in control of the applicant | Q7: Yes, but only if it registers as a Category II FPI instead | R7: No. Total NRI money has to stay under 25% | S7: B | T7: Three tests apply: each NRI, OCI or RI below 25%, all of them together below 50%, and none of them in control. The control test has carve-outs: an offshore fund with a SEBI NOC under the Mutual Fund Regulations, or a manager controlled by NRIs that is regulated at home and registered with SEBI as a non-investing FPI, or set up and registered in India. None applies here. | U7: The percentages pass, but the control test fails. All three tests have to be met. | W7: The control test is an eligibility condition, so changing the category doesn't fix it. | X7: 25% is the cap for a single NRI, OCI or RI. The cap on all of them together is below 50%. | Y7: SEBI Operational Guidelines for FPIs and DDPs, Part A 2(ii) | Z7: Where NRIs or OCI or RIs are constituents of the applicant – a. the contribution of a single NRI or OCI or RI shall be below twenty-five percent of the total contribution in the corpus of the applicant; b. the aggregate contribution of NRIs, OCIs and RIs shall be below fifty percent of the total contribution in the corpus of the applicant. Explanation: The contribution of RI is permitted, if made through the Liberalised Remittance Scheme (LRS) approved by Reserve Bank of India in global funds whose Indian exposure is less than 50%. c. the NRIs, OCIs and RIs shall not be in control of the applicant. | AC7: FPI Regs 2019, Reg 4(c); Op. Guidelines Part A 2(ii)(a)–(d) | AE7: Oct 2026 | AG7: =IF(A7="","",IF(COUNTA(O7:R7)<4,"Needs 4 options",IF(ISERROR(FIND(UPPER(S7),"ABCD"))+(LEN(S7)<>1),"Answer must be A-D",IF(OR(D7<1,D7>3),"Difficulty must be 1-3",IF(OR(N7="",T7=""),"Missing question or explanation",IF(COUNTBLANK(U7:X7)<>1,"Need 3 why-not texts",IF(INDEX(U7:X7,1,FIND(UPPER(S7),"ABCD"))<>"","Why-not filled for the answer",IF(AND(B7<>"live",B7<>"draft",B7<>"retired"),"Status must be live/draft/retired","OK")))))))) -> OK
A8: MON/NRI/107 | B8: live | C8: II | D8: 3 | E8: Redemptions push NRI share over 50% | F8: Holder | G8: Existing Category II FPI | H8: Event | I8: Other investors redeem; NRI/OCI share rises to 53% | J8: Breach date | K8: 1 July 2026 | L8: Status on 15 July | M8: Still 53% | N8: What timeline applies? | O8: Sell all Indian holdings within 5 trading days of the breach | P8: 90 days to fix it, then a purchase block and a 180-day exit | Q8: No action needed, because a passive breach doesn't count | R8: Stop all trading today and report the breach to SEBI | S8: B | T8: A temporary breach of the NRI/OCI/RI limits gives the FPI 90 days to comply again. If it is still in breach after 90 days, it can't make fresh purchases and must sell its positions within the following 180 days. | U8: 5 trading days is the timeline for breaching an investment limit, not for breaching the investor-mix limits. | W8: A temporary breach still counts. The 90-day period exists to fix exactly this. | X8: Nothing is blocked on day one. The FPI gets 90 days to comply first. | Y8: SEBI Operational Guidelines for FPIs and DDPs, Part A 2(ii)(f) | Z8: In case of temporary breach of above investment limits after December 31. 2020, the foreign portfolio investor shall comply with the eligibility conditions within ninety days of its breach. In case the foreign portfolio investor remains non-compliant with the said requirement even after ninety days, then no fresh purchases shall be permitted and such foreign portfolio investor shall liquidate its existing position in Indian securities market within a period of the next one hundred and eighty days. | AC8: Op. Guidelines Part A 2(ii)(f) | AE8: Oct 2026 | AG8: =IF(A8="","",IF(COUNTA(O8:R8)<4,"Needs 4 options",IF(ISERROR(FIND(UPPER(S8),"ABCD"))+(LEN(S8)<>1),"Answer must be A-D",IF(OR(D8<1,D8>3),"Difficulty must be 1-3",IF(OR(N8="",T8=""),"Missing question or explanation",IF(COUNTBLANK(U8:X8)<>1,"Need 3 why-not texts",IF(INDEX(U8:X8,1,FIND(UPPER(S8),"ABCD"))<>"","Why-not filled for the answer",IF(AND(B8<>"live",B8<>"draft",B8<>"retired"),"Status must be live/draft/retired","OK")))))))) -> OK
A9: MON/LIM/108 | B9: live | C9: IV | D9: 1 | E9: Two sister FPIs cross 10% together | F9: FPI A | G9: Holds 6.2% of Company X | H9: FPI B | I9: Holds 3.5% of Company X | J9: Link | K9: Same parent owns 60% of both | L9: Today | M9: FPI B buys another 0.6% | N9: What's the position? | O9: Fine. Each FPI is below 10% on its own, so no breach | P9: Breach. Sell the excess in 5 trading days or it all becomes FDI | Q9: Fine, as long as the aggregate FPI limit still has room | R9: Breach, and the exchange reverses B's new purchase to cure it | S9: B | T9: Common ownership above 50%, or common control, puts FPIs in one investor group, and their holdings count together against the below-10% limit on a fully diluted basis. If the excess isn't sold within 5 trading days of settlement, the group's entire investment in the company is treated as FDI, and it can't make further portfolio investment in that company. | U9: Common ownership above 50% makes them one investor group, so the limit applies to the combined 10.3%. | W9: The aggregate FPI limit is a separate cap at company level. The 10% group limit still applies. | X9: Exchange trades aren't reversed. The fix is to sell down within 5 trading days, or the holding turns into FDI. | Y9: SEBI (FPI) Regulations, 2019, Regulation 20(7) | Z9: (7) The purchase of equity shares of each company by a single foreign portfolio investor including its investor group shall be below ten per cent of the total paid-up equity capital on a fully diluted basis of the company: Provided that where the total investment under these regulations by a foreign portfolio investor including its investor group exceeds the threshold of below ten per cent of the total paid up equity capital in a listed or to be listed company on a fully diluted basis, the foreign portfolio investor shall divest the excess holding within five trading days from the date of settlement of the trades resulting in the breach: Provided further that in case the foreign portfolio investor fails to divest the excess holding, the entire investment in the company by such foreign portfolio investor including its investor group shall be considered as investment under the Foreign Direct Investment, as per the procedure specified by the Board and the foreign portfolio investor and its investor group shall not make further portfolio investment in that company under these regulations, | AC9: FPI Regs 2019, Reg 20(7), Reg 22(3) | AE9: Oct 2026 | AG9: =IF(A9="","",IF(COUNTA(O9:R9)<4,"Needs 4 options",IF(ISERROR(FIND(UPPER(S9),"ABCD"))+(LEN(S9)<>1),"Answer must be A-D",IF(OR(D9<1,D9>3),"Difficulty must be 1-3",IF(OR(N9="",T9=""),"Missing question or explanation",IF(COUNTBLANK(U9:X9)<>1,"Need 3 why-not texts",IF(INDEX(U9:X9,1,FIND(UPPER(S9),"ABCD"))<>"","Why-not filled for the answer",IF(AND(B9<>"live",B9<>"draft",B9<>"retired"),"Status must be live/draft/retired","OK")))))))) -> OK
A10: MON/LIM/109 | B10: live | C10: V | D10: 3 | E10: Two UCITS under one management company | F10: FPI A | G10: Luxembourg UCITS, holds 6% of Company Y | H10: FPI B | I10: Irish UCITS, holds 5% of Company Y | J10: Link | K10: Same management company (common control); no common ownership above 50% | L10: Both | M10: Open to retail investors | N10: Are they combined for the 10% limit? | O10: Yes. Common control makes them one investor group | P10: No. That rule doesn't apply to regulated public retail funds | Q10: Yes, unless SEBI grants these two funds a specific exemption order | R10: No, because they are domiciled in different countries | S10: B | T10: Reg 22(4) switches off the common-control rule where the FPIs are appropriately regulated public retail funds, or retail funds with regulated managers. The relief covers common control only. If they also shared more than 50% ownership, they would still be combined. | U10: Normally yes, but Reg 22(4) switches off the common-control rule for appropriately regulated public retail funds. | W10: The exemption is written into Reg 22(4) itself. No SEBI order is needed. | X10: Country doesn't decide investor groups. Ownership and control do. | Y10: SEBI (FPI) Regulations, 2019, Regulation 22(4) | Z10: (4) Notwithstanding anything contained in sub-regulation (3), the clubbing of investment limit of foreign portfolio investors having common control shall not be applicable where – (a) foreign portfolio investors are appropriately regulated public retail funds; or (b) the foreign portfolio investors are public retail funds where the majority is owned by appropriately regulated public retail fund on look through basis; or (c) foreign portfolio investors are public retail funds and investment managers of such foreign portfolio investors are appropriately regulated. Explanation - Public retail funds means (i) mutual funds or unit trusts which are open for subscription to retail investors and which do not have specific investor type requirements like accredited investors; (ii) insurance companies where segregated portfolio with one to one correlation with a single investor is not maintained; and (iii)pension funds. | AC10: FPI Regs 2019, Reg 22(4) | AE10: Oct 2026 | AG10: =IF(A10="","",IF(COUNTA(O10:R10)<4,"Needs 4 options",IF(ISERROR(FIND(UPPER(S10),"ABCD"))+(LEN(S10)<>1),"Answer must be A-D",IF(OR(D10<1,D10>3),"Difficulty must be 1-3",IF(OR(N10="",T10=""),"Missing question or explanation",IF(COUNTBLANK(U10:X10)<>1,"Need 3 why-not texts",IF(INDEX(U10:X10,1,FIND(UPPER(S10),"ABCD"))<>"","Why-not filled for the answer",IF(AND(B10<>"live",B10<>"draft",B10<>"retired"),"Status must be live/draft/retired","OK")))))))) -> OK
A11: MON/CHG/110 | B11: live | C11: V | D11: 2 | E11: Ownership change reported eight months late | F11: FPI | G11: Category I fund managed by an asset manager | H11: Event | I11: New parent bought 70% of the asset manager on 10 January 2026 | J11: Told DDP | K11: 15 September 2026 | L11: Category impact | M11: Not yet assessed | N11: What does the DDP do? | O11: Update the records. Late reporting has no consequence | P11: Re-assess eligibility and report the delay to SEBI | Q11: Cancel the registration for the late intimation | R11: Block the account permanently for the breach | S11: B | T11: Any direct or indirect change in structure, ownership or control must be reported within 7 working days. The DDP has to re-assess eligibility. Where the FPI was more than six months late, the DDP must report the case to SEBI with the reason. | U11: A delay over six months has to go to SEBI, and the change itself needs an eligibility check. | W11: DDPs don't cancel registrations. That is SEBI's decision under the Intermediaries Regulations. | X11: There's no automatic permanent block. The DDP re-assesses eligibility and escalates the delay. | Y11: SEBI Operational Guidelines for FPIs and DDPs, Part A 15 | Z11: In terms of Regulation 22(1)(c), if there is any change in the material information previously furnished by the FPI to the DDP and/or SEBI, which has a bearing on the certificate granted by the DDP on behalf of the Board or relating to any direct or indirect change in its structure or ownership or control, change in regulatory status, merger, demerger or restructuring, change in category/ sub-category / structure/ jurisdiction/ name of FPI/ beneficial ownership etc, of the FPI, it shall forthwith inform the DDP and/or the Board in writing. The DDP shall examine all such material changes and re-assess the eligibility of the FPI including requiring FPIs to seek fresh registration. However, DDP shall not process any request for change in jurisdiction of the FPI and in such cases, FPI may apply for new FPI registration. Where there is a delay of more than six months in intimation of material change by the FPI to the DDP, the DDP shall, forthwith, inform all such cases to SEBI for appropriate action, if any, along with reason for delay. | AC11: FPI Regs 2019, Reg 22(1)(c), Reg 31(2)(e); Op. Guidelines Part A 15 | AE11: Oct 2026 | AG11: =IF(A11="","",IF(COUNTA(O11:R11)<4,"Needs 4 options",IF(ISERROR(FIND(UPPER(S11),"ABCD"))+(LEN(S11)<>1),"Answer must be A-D",IF(OR(D11<1,D11>3),"Difficulty must be 1-3",IF(OR(N11="",T11=""),"Missing question or explanation",IF(COUNTBLANK(U11:X11)<>1,"Need 3 why-not texts",IF(INDEX(U11:X11,1,FIND(UPPER(S11),"ABCD"))<>"","Why-not filled for the answer",IF(AND(B11<>"live",B11<>"draft",B11<>"retired"),"Status must be live/draft/retired","OK")))))))) -> OK
A12: MON/CHG/111 | B12: live | C12: V | D12: 1 | E12: Fund moves from Dublin to Luxembourg | F12: FPI | G12: Ireland-domiciled fund | H12: Event | I12: Redomiciled to Luxembourg | J12: Request | K12: Change the country on the existing registration | L12: Holdings | M12: Listed Indian equity | N12: Can the DDP make the change? | O12: Yes. Update the registration and its country code | P12: No. It needs a new FPI registration | Q12: Yes, but only with SEBI's prior written approval | R12: Yes, because both countries are FATF members | S12: B | T12: The DDP re-assesses most material changes, but it can't process a change in the FPI's jurisdiction. The FPI has to apply for a new registration. | U12: The guidelines specifically bar DDPs from processing a change of jurisdiction. | W12: There's no SEBI approval route for this. A fresh registration is the only option. | X12: FATF membership is irrelevant here. A change of jurisdiction can't be processed on an existing registration at all. | Y12: SEBI Operational Guidelines for FPIs and DDPs, Part A 15(ii) | Z12: The DDP shall examine all such material changes and re-assess the eligibility of the FPI including requiring FPIs to seek fresh registration. However, DDP shall not process any request for change in jurisdiction of the FPI and in such cases, FPI may apply for new FPI registration. | AC12: Op. Guidelines Part A 15(ii) | AE12: Oct 2026 | AG12: =IF(A12="","",IF(COUNTA(O12:R12)<4,"Needs 4 options",IF(ISERROR(FIND(UPPER(S12),"ABCD"))+(LEN(S12)<>1),"Answer must be A-D",IF(OR(D12<1,D12>3),"Difficulty must be 1-3",IF(OR(N12="",T12=""),"Missing question or explanation",IF(COUNTBLANK(U12:X12)<>1,"Need 3 why-not texts",IF(INDEX(U12:X12,1,FIND(UPPER(S12),"ABCD"))<>"","Why-not filled for the answer",IF(AND(B12<>"live",B12<>"draft",B12<>"retired"),"Status must be live/draft/retired","OK")))))))) -> OK
A13: MON/REN/112 | B13: live | C13: II | D13: 2 | E13: Renewal fee paid seven weeks late | F13: FPI | G13: Category II fund | H13: Fees paid up to | I13: 31 August 2026 | J13: Today | K13: 20 October 2026 | L13: Request | M13: Take the fee now and continue the registration | N13: What do you tell the client? | O13: Fine. Accept the fee with a written reason for the delay | P13: Not possible. Surrender, then file a fresh application | Q13: Allowed, since it's still within 90 days of expiry | R13: Allowed, but only with SEBI's specific permission | S13: B | T13: A registration stops being valid after the date fees were paid up to, and continuance can't be applied for after expiry. The entity must surrender and apply fresh. Fees and updates should reach the DDP at least 15 days before validity ends. | U13: A reason for delay covers renewal papers that arrive late but before expiry. After expiry, continuance isn't possible. | W13: There's no 90-day grace period after expiry. | X13: The guidelines give no SEBI permission route. It has to surrender and reapply. | Y13: SEBI Operational Guidelines for FPIs and DDPs, Part A 5 | Z13: Where the FPI has not paid fees for continuance of its registration, its FPI registration shall cease to be valid after the date, up to which, the last registration fees were duly paid by the FPI. An FPI cannot apply for continuance after expiry of its registration. However, if such entity intends to have FPI registration, it will have to make a fresh application for registration after surrender of its earlier FPI registration. | AC13: Op. Guidelines Part A 5(iii)–(vi); FPI Regs 2019, Reg 9(3) | AE13: Oct 2026 | AG13: =IF(A13="","",IF(COUNTA(O13:R13)<4,"Needs 4 options",IF(ISERROR(FIND(UPPER(S13),"ABCD"))+(LEN(S13)<>1),"Answer must be A-D",IF(OR(D13<1,D13>3),"Difficulty must be 1-3",IF(OR(N13="",T13=""),"Missing question or explanation",IF(COUNTBLANK(U13:X13)<>1,"Need 3 why-not texts",IF(INDEX(U13:X13,1,FIND(UPPER(S13),"ABCD"))<>"","Why-not filled for the answer",IF(AND(B13<>"live",B13<>"draft",B13<>"retired"),"Status must be live/draft/retired","OK")))))))) -> OK
A14: ONB/CLT/113 | B14: live | C14: II | D14: 2 | E14: Broker investing for its clients | F14: Applicant | G14: Singapore-licensed broker-dealer | H14: Registration sought | I14: Category II, to invest client money | J14: Proposed clients | K14: Two individuals, one family office, one trading company | L14: Client KYC | M14: Done to Singapore standards | N14: Can all four clients invest through this registration? | O14: Yes. All four would be eligible as FPIs on their own | P14: No. The trading company can't be a client | Q14: Yes, if the broker also holds a Category I registration | R14: No. Brokers can't invest on behalf of clients at all | S14: B | T14: Regulated entities can invest for clients as Category II FPIs, but those clients must be individuals or family offices, must themselves be eligible as FPIs, and can't act for third parties. Client details go to the DDP every quarter. | U14: Being FPI-eligible is necessary but not enough. The client also has to be an individual or a family office. | W14: A Category I registration covers the broker's own money. It doesn't widen who the client registration can serve. | X14: Regulated entities, brokers included, can invest for clients through a Category II registration. | Y14: SEBI Operational Guidelines for FPIs and DDPs, Part A 3(iv) | Z14: Where such entities are undertaking investments on behalf of their clients, Category II FPI registration shall be granted subject to following conditions: Clients of FPI can only be individuals and family offices. | AC14: FPI Regs 2019, Reg 5(b)(vii); Op. Guidelines Part A 3(iv) | AE14: Oct 2026 | AG14: =IF(A14="","",IF(COUNTA(O14:R14)<4,"Needs 4 options",IF(ISERROR(FIND(UPPER(S14),"ABCD"))+(LEN(S14)<>1),"Answer must be A-D",IF(OR(D14<1,D14>3),"Difficulty must be 1-3",IF(OR(N14="",T14=""),"Missing question or explanation",IF(COUNTBLANK(U14:X14)<>1,"Need 3 why-not texts",IF(INDEX(U14:X14,1,FIND(UPPER(S14),"ABCD"))<>"","Why-not filled for the answer",IF(AND(B14<>"live",B14<>"draft",B14<>"retired"),"Status must be live/draft/retired","OK")))))))) -> OK
A15: MON/AML/114 | B15: live | C15: II | D15: 2 | E15: Major investor added to UN sanctions list | F15: FPI | G15: Category II fund | H15: Event | I15: An investor holding 30% of the corpus is added to the UN Security Council Sanctions List | J15: Pending | K15: A sell order on Indian holdings | L15: Home country | M15: Unchanged, compliant | N15: What do you do? | O15: Block new buys but let the pending sell go through | P15: Block all buying and selling, and notify SEBI | Q15: Allow trading normally until SEBI writes in | R15: Freeze only that investor's share of the fund | S15: B | T15: If the FPI or a material underlying investor comes under UNSC sanctions, the custodian must stop all further buying and selling in the account and notify SEBI immediately. | U15: Allowing sales is the rule when a home country loses compliant status. Sanctions block selling too. | W15: The custodian acts first and then notifies SEBI. It doesn't wait to hear back. | X15: The block covers the whole FPI account, not one investor's share. | Y15: SEBI Operational Guidelines for FPIs and DDPs, Part A 16(i) | Z15: Further, in case the FPI itself or its underlying investors contributing twenty-five percent or more in the corpus of the FPI or identified on the basis of control, come under the Sanctions List notified by the United Nations Security Council, custodian shall not allow any further buy/sell in the account of such FPI and shall forthwith notify such instances to SEBI. | AC15: FPI Regs 2019, Reg 4(f); Op. Guidelines Part A 16(i) | AE15: Oct 2026 | AG15: =IF(A15="","",IF(COUNTA(O15:R15)<4,"Needs 4 options",IF(ISERROR(FIND(UPPER(S15),"ABCD"))+(LEN(S15)<>1),"Answer must be A-D",IF(OR(D15<1,D15>3),"Difficulty must be 1-3",IF(OR(N15="",T15=""),"Missing question or explanation",IF(COUNTBLANK(U15:X15)<>1,"Need 3 why-not texts",IF(INDEX(U15:X15,1,FIND(UPPER(S15),"ABCD"))<>"","Why-not filled for the answer",IF(AND(B15<>"live",B15<>"draft",B15<>"retired"),"Status must be live/draft/retired","OK")))))))) -> OK
A16: MON/JUR/115 | B16: live | C16: II | D16: 1 | E16: Home country put on the FATF high-risk list | F16: FPI | G16: Category I fund | H16: Event | I16: Home country listed in FATF's public statement as high-risk | J16: Holdings | K16: Listed equity and G-Secs | L16: Fund itself | M16: No adverse findings | N16: What changes for this FPI? | O16: It must sell everything within 180 days | P16: No fresh purchases; it may hold or sell | Q16: The registration is cancelled by the DDP | R16: Nothing changes until the next renewal | S16: B | T16: When a jurisdiction stops being compliant (it leaves IOSCO, a SEBI MoU or the BIS, or FATF names it high-risk), the custodian blocks fresh purchases. The FPI may keep or sell what it holds, and the DDP reports the affected FPIs to SEBI. | U16: There's no forced sale. The FPI can keep or sell its holdings. | W16: The registration isn't cancelled. Fresh purchases are blocked until the jurisdiction is compliant again. | X16: The custodian acts as soon as the status changes, not at renewal. | Y16: SEBI Operational Guidelines for FPIs and DDPs, Part A 16(i) | Z16: If a jurisdiction, which was a compliant jurisdiction at the time of grant of registration to FPI, becomes non-compliant jurisdiction i.e. ceases to be member of IOSCO/ Bilateral Memorandum of Understanding with SEBI/ BIS or the concerned jurisdiction of FPI is listed in FATF public statement as "high risk" and "noncooperative" jurisdiction or the concerned jurisdiction of FPI then concerned Custodian shall not allow such FPIs to make fresh purchases till the time the jurisdiction/FPI is compliant with the Regulations. However, the FPI shall be allowed to sell the securities or continue to hold the securities already purchased by it. The concerned DDP shall inform to SEBI details of such FPIs upon such change. | AC16: Op. Guidelines Part A 16(i) | AE16: Oct 2026 | AG16: =IF(A16="","",IF(COUNTA(O16:R16)<4,"Needs 4 options",IF(ISERROR(FIND(UPPER(S16),"ABCD"))+(LEN(S16)<>1),"Answer must be A-D",IF(OR(D16<1,D16>3),"Difficulty must be 1-3",IF(OR(N16="",T16=""),"Missing question or explanation",IF(COUNTBLANK(U16:X16)<>1,"Need 3 why-not texts",IF(INDEX(U16:X16,1,FIND(UPPER(S16),"ABCD"))<>"","Why-not filled for the answer",IF(AND(B16<>"live",B16<>"draft",B16<>"retired"),"Status must be live/draft/retired","OK")))))))) -> OK
A17: ONB/REJ/116 | B17: live | C17: II | D17: 2 | E17: Rejected for missing papers | F17: Applicant | G17: Category II corporate body | H17: Rejected by | I17: DDP A, for incomplete documents and unpaid fee | J17: Client wants to | K17: Appeal to SEBI | L17: Days since rejection | M17: 12 | N17: What's the right route? | O17: Ask SEBI to reconsider within 30 days | P17: Fix the gaps and reapply, with any DDP | Q17: Wait six months before reapplying anywhere | R17: Reapply only through DDP A, which rejected it | S17: B | T17: An applicant can ask SEBI to reconsider within 30 days, but not when the rejection was technical: missing information or documents, or unpaid fees. Another DDP can take the application once it has checked why it was rejected and confirmed the gaps are fixed. | U17: The 30-day reconsideration route exists, but Reg 8(3) excludes technical rejections like missing documents or fees. | W17: There's no waiting period. It can reapply as soon as the gaps are fixed. | X17: Any DDP can take it, after checking the rejection reason in the depositories' shared database. | Y17: SEBI (FPI) Regulations, 2019, Regulation 8(3) | Z17: (3) The applicant, who is aggrieved by the decision of the designated depository participant under sub-regulation (1) may, within a period of thirty days from the date of receipt of communication under sub-regulation (2), apply to the Board for reconsideration of the decision of the designated depository participant: Provided that such application for reconsideration shall not be considered by the Board where the rejection was on account of technical reasons such as non-submission of complete information, documents, including non-payment of specified fees. | AC17: FPI Regs 2019, Reg 8(3); Op. Guidelines Part A 7 | AE17: Oct 2026 | AG17: =IF(A17="","",IF(COUNTA(O17:R17)<4,"Needs 4 options",IF(ISERROR(FIND(UPPER(S17),"ABCD"))+(LEN(S17)<>1),"Answer must be A-D",IF(OR(D17<1,D17>3),"Difficulty must be 1-3",IF(OR(N17="",T17=""),"Missing question or explanation",IF(COUNTBLANK(U17:X17)<>1,"Need 3 why-not texts",IF(INDEX(U17:X17,1,FIND(UPPER(S17),"ABCD"))<>"","Why-not filled for the answer",IF(AND(B17<>"live",B17<>"draft",B17<>"retired"),"Status must be live/draft/retired","OK")))))))) -> OK
... A21: MON/INV/120 | B21: live | C21: IV | D21: 1 | E21: FPI wants shares in an unlisted company | F21: FPI | G21: Category I UK pension fund | H21: Target | I21: Unlisted Indian fintech | J21: Deal | K21: Buy 4% from existing shareholders | L21: Request | M21: Book it through the FPI account | N21: Can this go through the FPI route? | O21: Yes, because it's well under the 10% limit | P21: No. Buying unlisted equity is FDI | Q21: Yes, but only with SEBI's prior approval | R21: Yes, if it's booked as an off-market transfer | S21: B | T21: The FPI route covers shares of companies that are listed, or about to be listed, on an Indian exchange. Buying shares in an unlisted company is foreign direct investment under FEMA. | U21: The 10% limit only matters for securities an FPI is allowed to buy, and unlisted equity isn't one of them. | W21: No SEBI approval brings unlisted equity into the FPI route. | X21: Off-market sales of unlisted shares are allowed for getting out, at FEMA pricing, not for buying in. | Y21: SEBI (FPI) Regulations, 2019, Regulation 20(1)(a) | Z21: 20. (1) A foreign portfolio investor shall invest only in the following securities, namely (a) shares, debentures and warrants issued by a body corporate; listed or to be listed on a recognized stock exchange in India; | AC21: FPI Regs 2019, Reg 20(1)(a); Op. Guidelines Part C 4 | AE21: Oct 2026 | AG21: =IF(A21="","",IF(COUNTA(O21:R21)<4,"Needs 4 options",IF(ISERROR(FIND(UPPER(S21),"ABCD"))+(LEN(S21)<>1),"Answer must be A-D",IF(OR(D21<1,D21>3),"Difficulty must be 1-3",IF(OR(N21="",T21=""),"Missing question or explanation",IF(COUNTBLANK(U21:X21)<>1,"Need 3 why-not texts",IF(INDEX(U21:X21,1,FIND(UPPER(S21),"ABCD"))<>"","Why-not filled for the answer",IF(AND(B21<>"live",B21<>"draft",B21<>"retired"),"Status must be live/draft/retired","OK")))))))) -> OK
A22: SWG/ELG/201 | B22: live | C22: SW | D22: 1 | E22: Luxembourg UCITS applies for SWAGAT | F22: Applicant | G22: Aurelia Global Equity, a Luxembourg SICAV authorised by the CSSF | H22: Investors | I22: Retail; no accredited-investor condition | J22: Portfolio | K22: Common pool, diversified | L22: Manager | M22: Independent management company | N22: Can it be tagged SWAGAT-FI? | O22: Yes, as a public retail fund | P22: No. Only government investors can qualify | Q22: Only after three years as a regular FPI | R22: No. UCITS have to stay in Category II | S22: A | T22: A retail fund qualifies if it is open to retail investors, runs as a blind pool with diversified investors and investments, has contributors without day-to-day control and an independent manager, and comes from a jurisdiction named in the SOP. Luxembourg UCITS are on the list. | V22: Four types qualify: government investors, retail mutual funds, insurers and pension funds. | W22: There's no waiting period. Eligible applicants can opt in when they first register. | X22: UCITS are often Category I anyway, and the SWAGAT letter is open to Category I and II FPIs alike. | Y22: SEBI circular, 16 Jan 2026 (SWAGAT-FI), para 3.2 (vi)(I) | Z22: I. The following shall be eligible for registration as SWAGAT-FI FPI a. Government or Government related investor as provided under Regulation 5(a)(i) of the FPI Regulations, 2019; b. Appropriately regulated mutual fund or unit trust open for subscription to retail investors without any specific investor type requirements like accredited investors and complying with the following conditions: i. The applicant operates as a blind pool (i.e. common portfolio) with diversified investors and investments. ii. The contributors to the applicant do not have control over day-to-day operations of the applicant and the investment manager of the applicant is independent from such contributors; | AA22: SEBI circular, 16 Jan 2026 (SWAGAT-FI), para 3.2 (vi)(II) | AB22: II. The applicant being a public retail fund is setup in identified jurisdiction and regulated by the identified statutory authority / regulatory body in such identified jurisdiction. The list of identified jurisdictions and identified statutory authority / regulatory body shall be spelt out in the Standard Operating Procedure framed and adopted by Custodians and Designated Depository Participants Standards Setting Forum (CDSSF) in consultation with SEBI. | AC22: SEBI circular 16 Jan 2026, para 3.2 (vi)(I)–(II); SWAGAT SOP 27 May 2026, Annex B | AE22: Oct 2026 | AG22: =IF(A22="","",IF(COUNTA(O22:R22)<4,"Needs 4 options",IF(ISERROR(FIND(UPPER(S22),"ABCD"))+(LEN(S22)<>1),"Answer must be A-D",IF(OR(D22<1,D22>3),"Difficulty must be 1-3",IF(OR(N22="",T22=""),"Missing question or explanation",IF(COUNTBLANK(U22:X22)<>1,"Need 3 why-not texts",IF(INDEX(U22:X22,1,FIND(UPPER(S22),"ABCD"))<>"","Why-not filled for the answer",IF(AND(B22<>"live",B22<>"draft",B22<>"retired"),"Status must be live/draft/retired","OK")))))))) -> OK
A23: SWG/ELG/202 | B23: live | C23: SW | D23: 2 | E23: Irish AIF sold only to qualified investors | F23: Applicant | G23: Irish AIF authorised by the Central Bank of Ireland | H23: Marketing | I23: Qualified investors only, as noted on the Central Bank register | J23: Portfolio | K23: Diversified | L23: Current status | M23: Category I FPI | N23: Does it qualify for SWAGAT-FI? | O23: Yes. It's regulated and based in a FATF member country | P23: No. A qualified-investor fund isn't a public retail fund | Q23: Yes, as long as it gives a signed declaration to the DDP | R23: Yes, because it's already registered with SEBI as a Category I FPI | S23: B | T23: The SOP says an Irish AIF marketed to qualified investors, as shown on the Central Bank of Ireland register, is not a public retail fund. It stays a regular FPI. | U23: Being regulated in a FATF country earns Category I. SWAGAT also needs the fund to be open to retail investors. | W23: The DDP can't rely on a declaration, and here the regulator's register says the opposite. | X23: Category I status doesn't make it a public retail fund. | Y23: CDSSF SOP for SWAGAT-FI, 27 May 2026, Annex B (Ireland) | Z23: In case an AIF is marketed to qualified investors, the same is reflected on the Central Bank of Ireland website in the notes section. (such notification is available at umbrella fund level and not sub fund level) Sample case provided below. Such cases shall not be considered PRFs. Other AIFs are retail and considered as RAIF. | AC23: SWAGAT SOP 27 May 2026, Annex B (Ireland) | AE23: Oct 2026 | AG23: =IF(A23="","",IF(COUNTA(O23:R23)<4,"Needs 4 options",IF(ISERROR(FIND(UPPER(S23),"ABCD"))+(LEN(S23)<>1),"Answer must be A-D",IF(OR(D23<1,D23>3),"Difficulty must be 1-3",IF(OR(N23="",T23=""),"Missing question or explanation",IF(COUNTBLANK(U23:X23)<>1,"Need 3 why-not texts",IF(INDEX(U23:X23,1,FIND(UPPER(S23),"ABCD"))<>"","Why-not filled for the answer",IF(AND(B23<>"live",B23<>"draft",B23<>"retired"),"Status must be live/draft/retired","OK")))))))) -> OK
A24: SWG/ELG/203 | B24: live | C24: SW | D24: 2 | E24: Insurer with unit-linked sleeves | F24: Applicant | G24: Regulated life insurer | H24: India money | I24: Own funds, plus unit-linked portfolios each tied to a single policyholder | J24: Home regulator | K24: Insurance supervisor in a permitted jurisdiction | L24: Requested | M24: SWAGAT-FI | N24: Is it eligible? | O24: Yes. Regulated insurers always qualify | P24: No. The segregated portfolios rule it out | Q24: Yes, by applying as a pension fund instead | R24: Yes, if unit-linked money is under 50% | S24: B | T24: The insurance route covers an appropriately regulated insurer investing its own funds without segregated portfolios, and the insurer has to show evidence of that. Portfolios each tied to one policyholder fail the test. | U24: Only insurers investing their own funds, with no segregated portfolios, qualify. | W24: An insurer isn't a pension fund, and a different label doesn't remove the segregated portfolios. | X24: There's no percentage threshold. Any segregated portfolio fails the test. | Y24: SEBI circular, 16 Jan 2026 (SWAGAT-FI), para 3.2 (vi)(I)(c) | Z24: c. Appropriately regulated insurance company investing its own funds and does not have segregated portfolios; | AC24: SEBI circular 16 Jan 2026, para 3.2 (vi)(I)(c); SWAGAT SOP, section 8 | AE24: Oct 2026 | AG24: =IF(A24="","",IF(COUNTA(O24:R24)<4,"Needs 4 options",IF(ISERROR(FIND(UPPER(S24),"ABCD"))+(LEN(S24)<>1),"Answer must be A-D",IF(OR(D24<1,D24>3),"Difficulty must be 1-3",IF(OR(N24="",T24=""),"Missing question or explanation",IF(COUNTBLANK(U24:X24)<>1,"Need 3 why-not texts",IF(INDEX(U24:X24,1,FIND(UPPER(S24),"ABCD"))<>"","Why-not filled for the answer",IF(AND(B24<>"live",B24<>"draft",B24<>"retired"),"Status must be live/draft/retired","OK")))))))) -> OK
A25: SWG/ELG/204 | B25: live | C25: SW | D25: 3 | E25: Manager's own seed money in the fund | F25: Applicant | G25: Singapore authorised collective investment scheme, retail | H25: Manager stake | I25: 4%, seeded as skin in the game | J25: Manager | K25: Same group as the fund's sponsor | L25: Other investors | M25: Diversified retail | N25: Does either fact block SWAGAT-FI? | O25: Yes. The manager is a contributor, so the manager isn't independent | P25: No. Skin-in-the-game money and a same-group manager are both allowed | Q25: Yes. The manager must come from outside the sponsor's group to be independent | R25: Only if the stake exceeds 2% | S25: B | T25: The SOP clarifies that the test of contributors not controlling the fund ignores a manager's skin-in-the-game money. And the independence test doesn't stop a manager from the FPI's own group from managing or controlling the fund. | U25: The SOP leaves skin-in-the-game money out of the control and independence tests. | W25: The SOP says a manager from the same group doesn't breach independence. | X25: The SOP sets no percentage threshold for skin in the game. | Y25: CDSSF SOP for SWAGAT-FI, 27 May 2026, Section 3 B.1(b)–(c) | Z25: b. The requirement that the contributors to the applicant should not have control over day-to-day operations of the applicant shall not apply in respect of contributions made by the Investment Manager to the fund solely for the purpose of “skin in the game.” requirements, if any. c. The requirement that the applicant's Investment Manager being independent of the contributors to the applicant shall not be construed to prohibit an Investment Manager belonging to the same group as the FPI from managing and/ or controlling the fund. | AC25: SWAGAT SOP 27 May 2026, section 3 B.1(b)–(c) | AE25: Oct 2026 | AG25: =IF(A25="","",IF(COUNTA(O25:R25)<4,"Needs 4 options",IF(ISERROR(FIND(UPPER(S25),"ABCD"))+(LEN(S25)<>1),"Answer must be A-D",IF(OR(D25<1,D25>3),"Difficulty must be 1-3",IF(OR(N25="",T25=""),"Missing question or explanation",IF(COUNTBLANK(U25:X25)<>1,"Need 3 why-not texts",IF(INDEX(U25:X25,1,FIND(UPPER(S25),"ABCD"))<>"","Why-not filled for the answer",IF(AND(B25<>"live",B25<>"draft",B25<>"retired"),"Status must be live/draft/retired","OK")))))))) -> OK
A26: SWG/CNV/205 | B26: live | C26: SW | D26: 2 | E26: Sovereign fund converts to SWAGAT | F26: FPI | G26: Category I sovereign wealth fund, registered under Reg 5(a)(i) in 2021 | H26: Next renewal | I26: March 2027 | J26: Request | K26: Convert to SWAGAT-FI | L26: Changes | M26: None | N26: What does it need to submit and pay? | O26: A fresh KYC pack for the DDP, plus the US$2,500 SWAGAT fee | P26: A declaration of intent only, with no fee now | Q26: A full re-registration with the DDP | R26: A one-time conversion fee of US$250 | S26: B | T26: An FPI already registered as a government or government-related investor only declares its intent, using the SWAGAT requisition letter, with no further documents. No fee is due on transition. SEBI fees fall due at the next renewal after a 10-year block. | U26: A government investor that's already registered needs no further documents, and no fee is due at transition. | W26: Converting is an application to the existing DDP, not a new registration. | X26: There's no conversion fee. US$250 is the regular Category II registration fee. | Y26: CDSSF SOP for SWAGAT-FI, 27 May 2026, Section 3 B.6(a) | Z26: a. Where existing FPIs transitions to SWAGAT-FI, the FPI is not required to pay any fees at the time of transition. The applicable SEBI fees will be paid at the next renewal date after a block of 10 years. | AC26: SWAGAT SOP, section 3 A.2 and B.6(a), section 8 row 1 | AE26: Oct 2026 | AG26: =IF(A26="","",IF(COUNTA(O26:R26)<4,"Needs 4 options",IF(ISERROR(FIND(UPPER(S26),"ABCD"))+(LEN(S26)<>1),"Answer must be A-D",IF(OR(D26<1,D26>3),"Difficulty must be 1-3",IF(OR(N26="",T26=""),"Missing question or explanation",IF(COUNTBLANK(U26:X26)<>1,"Need 3 why-not texts",IF(INDEX(U26:X26,1,FIND(UPPER(S26),"ABCD"))<>"","Why-not filled for the answer",IF(AND(B26<>"live",B26<>"draft",B26<>"retired"),"Status must be live/draft/retired","OK")))))))) -> OK
A27: SWG/FEE/206 | B27: live | C27: SW | D27: 3 | E27: New applicant wants FPI and FVCI | F27: Applicant | G27: Regulated pension fund, new to India | H27: Wants | I27: SWAGAT-FI FPI and SWAGAT-FI FVCI | J27: PAN | K27: One PAN for the entity | L27: Question | M27: Upfront SEBI fee | N27: What is the fresh registration fee? | O27: US$2,500 for 3 years | P27: US$5,000, covering 10 years | Q27: US$2,600, covering 10 years | R27: US$2,500 every year | S27: B | T27: A SWAGAT-FI pays for 10 years in advance: US$2,500 for FPI only, US$2,500 for FVCI only, or US$5,000 for both, plus taxes. Renewal is US$2,500, US$100 or US$2,600. | U27: US$2,500 per 3 years is the regular Category I fee. SWAGAT fees cover 10 years, and this applicant wants both registrations. | W27: US$2,600 is the renewal fee for both, not the fresh fee. | X27: SWAGAT fees are paid once for the 10-year block, not every year. | Y27: CDSSF SOP for SWAGAT-FI, 27 May 2026, Section 3 B.5 (fee table, reformatted) | Z27: SWAGAT-FI will pay only for 10 years in advance, along with applicable taxes (amounts in USD). Registration fees (fresh): Only FPI 2500 · Only FVCI 2500 · FPI and FVCI 5000. Renewal: Only FPI 2500 · Only FVCI 100 · FPI and FVCI 2600. *For the same entity there will be one PAN, and fees would apply only once. | AC27: SWAGAT SOP 27 May 2026, section 3 B.5 | AE27: Oct 2026 | AG27: =IF(A27="","",IF(COUNTA(O27:R27)<4,"Needs 4 options",IF(ISERROR(FIND(UPPER(S27),"ABCD"))+(LEN(S27)<>1),"Answer must be A-D",IF(OR(D27<1,D27>3),"Difficulty must be 1-3",IF(OR(N27="",T27=""),"Missing question or explanation",IF(COUNTBLANK(U27:X27)<>1,"Need 3 why-not texts",IF(INDEX(U27:X27,1,FIND(UPPER(S27),"ABCD"))<>"","Why-not filled for the answer",IF(AND(B27<>"live",B27<>"draft",B27<>"retired"),"Status must be live/draft/retired","OK")))))))) -> OK
A28: SWG/KYC/207 | B28: live | C28: SW | D28: 1 | E28: Custodian diary shows a 2029 KYC review | F28: FPI | G28: SWAGAT-FI pension fund, registered June 2026 | H28: Custodian diary | I28: KYC review: June 2029 | J28: Risk rating | K28: Low | L28: Custodian policy | M28: No special rule | N28: Is the 2029 date right? | O28: Yes. KYC review is every 3 years for every FPI | P28: No. The default for SWAGAT-FIs is every 10 years | Q28: No. Once tagged SWAGAT-FI, it never needs a KYC review again | R28: Yes, but only because it's a pension fund | S28: B | T28: For SWAGAT-FIs, both continuance and KYC review move to a 10-year cycle. The SOP leaves room for a different period set by RBI, for RBI-regulated entities, or by the DDP's own risk policy. | U28: Three years is the usual cycle for regular, lower-risk FPIs. SWAGAT-FIs move to 10 years. | W28: The review still happens, every 10 years by default. | X28: The 10-year cycle applies to every type of SWAGAT-FI, pension funds included. | Y28: SEBI circular, 16 Jan 2026 (SWAGAT-FI), para 3.4 | Z28: In case of SWAGAT-FI FPI, periodicity of KYC review by custodians shall be 10 years. | AC28: Circular 16 Jan 2026, paras 3.3–3.4; SWAGAT SOP, section 3 B.2 | AE28: Oct 2026 | AG28: =IF(A28="","",IF(COUNTA(O28:R28)<4,"Needs 4 options",IF(ISERROR(FIND(UPPER(S28),"ABCD"))+(LEN(S28)<>1),"Answer must be A-D",IF(OR(D28<1,D28>3),"Difficulty must be 1-3",IF(OR(N28="",T28=""),"Missing question or explanation",IF(COUNTBLANK(U28:X28)<>1,"Need 3 why-not texts",IF(INDEX(U28:X28,1,FIND(UPPER(S28),"ABCD"))<>"","Why-not filled for the answer",IF(AND(B28<>"live",B28<>"draft",B28<>"retired"),"Status must be live/draft/retired","OK")))))))) -> OK
A29: SWG/NRI/208 | B29: live | C29: SW | D29: 3 | E29: Resident Indian money in a SWAGAT fund | F29: FPI | G29: SWAGAT-FI retail fund | H29: Largest NRI | I29: 30% of the corpus | J29: Resident Indians | K29: Individuals investing through LRS | L29: Fund's India exposure | M29: 65% | N29: Where's the problem? | O29: The NRI at 30%, which breaks the 25% single-investor cap | P29: The resident Indian money, given 65% India exposure | Q29: Nothing. SWAGAT-FIs are exempt from all contributor rules | R29: Both the NRI stake and the resident Indian money | S29: B | T29: The per-investor and combined NRI/OCI/RI caps don't apply to SWAGAT-FIs. But one condition stays: resident Indian individuals can only invest through LRS, and only in global funds whose India exposure is below 50%. At 65%, this fund fails. | U29: The per-investor and combined caps are switched off for SWAGAT-FIs. | W29: The LRS condition for resident Indians still applies. | X29: Only the resident Indian money fails. The NRI stake is fine. | Y29: SEBI circular, 16 Jan 2026 (SWAGAT-FI), para 3.1 | Z29: db. The provision mentioned at (b) above shall not apply to SWAGAT-FI FPI. However, it shall be subject to the provision that contribution of resident Indian individuals shall be made through the LRS notified by RBI and shall be in global funds whose Indian exposure is less than 50%. | AC29: Circular 16 Jan 2026, para 3.1 (Master Circular Part A para 1(ii)(db)) | AE29: Oct 2026 | AG29: =IF(A29="","",IF(COUNTA(O29:R29)<4,"Needs 4 options",IF(ISERROR(FIND(UPPER(S29),"ABCD"))+(LEN(S29)<>1),"Answer must be A-D",IF(OR(D29<1,D29>3),"Difficulty must be 1-3",IF(OR(N29="",T29=""),"Missing question or explanation",IF(COUNTBLANK(U29:X29)<>1,"Need 3 why-not texts",IF(INDEX(U29:X29,1,FIND(UPPER(S29),"ABCD"))<>"","Why-not filled for the answer",IF(AND(B29<>"live",B29<>"draft",B29<>"retired"),"Status must be live/draft/retired","OK")))))))) -> OK
A30: SWG/EVD/209 | B30: live | C30: SW | D30: 2 | E30: US fund ticks every box itself | F30: Applicant | G30: US open-end mutual fund, SEC-registered | H30: Submitted | I30: SWAGAT letter with Yes for all five retail-fund conditions | J30: Prospectus | K30: Not provided | L30: Request | M30: Tag as SWAGAT-FI this week | N30: Can the DDP approve on this? | O30: Yes. The applicant's own declaration is enough | P30: No. The DDP needs evidence such as the prospectus | Q30: Yes, because SEC registration proves retail status | R30: No. US funds can't be SWAGAT-FIs at all | S30: B | T30: Where the home rules don't show a condition, the applicant must provide a certificate from its regulator or its own documents, such as the prospectus, with the relevant clauses marked. The DDP can't rely on a declaration alone. For US funds the SOP marks openness to retail investors as To Be Verified. | U30: The SOP specifically says the DDP can't rely on a mere declaration. | W30: SEC registration doesn't settle retail access. Some registered funds are sold only to accredited investors. | X30: US funds are covered in the SOP's Annex B. They can qualify with evidence. | Y30: CDSSF SOP for SWAGAT-FI, 27 May 2026, Section 3 B.1(a) | Z30: a. Indicative guidelines for qualifying as a SWAGAT-FI, wherever available under the applicable Acts/ Regulations and/ or on regulatory websites in the home jurisdiction of the funds, are provided in annexures to this SOP. Where such conditions are not evidenced in the above material, the FPI / FVCI should provide to their DDP the original or certified/ attested copy of the certificate/ document evidencing that the FPI/ FVCI meets the eligibility requirement, with the respective provisions clearly identified for verification by the DDP. Such certificate/ document shall be issued by the concerned regulator/ authority or shall form a part of constitutive documents of the FPI / FVCI (including the Prospectus / Information Memorandum (IM)/ Offer Document etc.). The DDP shall obtain sufficient supporting documentation in such cases and not rely on mere declaration by the FPI / FVCI, and the certification/ attestation shall be carried out as authorised in the Master Circular. | AC30: SWAGAT SOP 27 May 2026, section 3 B.1(a); Annex B (USA) | AE30: Oct 2026 | AG30: =IF(A30="","",IF(COUNTA(O30:R30)<4,"Needs 4 options",IF(ISERROR(FIND(UPPER(S30),"ABCD"))+(LEN(S30)<>1),"Answer must be A-D",IF(OR(D30<1,D30>3),"Difficulty must be 1-3",IF(OR(N30="",T30=""),"Missing question or explanation",IF(COUNTBLANK(U30:X30)<>1,"Need 3 why-not texts",IF(INDEX(U30:X30,1,FIND(UPPER(S30),"ABCD"))<>"","Why-not filled for the answer",IF(AND(B30<>"live",B30<>"draft",B30<>"retired"),"Status must be live/draft/retired","OK")))))))) -> OK
A31: SWG/ELG/210 | B31: live | C31: SW | D31: 3 | E31: Pension plan governed by statute only | F31: Applicant | G31: Retirement plan for state employees | H31: Licensing | I31: Not directly licensed by a regulator | J31: Oversight | K31: Set up under a statute that imposes supervision and compliance duties | L31: Requested | M31: SWAGAT-FI as a pension fund | N31: Can it qualify? | O31: No. A pension fund must be directly licensed | P31: Yes. Statutory oversight is enough | Q31: Only by registering as a Category II FPI | R31: Only if it's 100% owned by the government | S31: B | T31: The SOP's pension route includes plans governed or recognised by a statutory, regulatory or tax authority. A plan that isn't directly licensed can still qualify if it operates under a law and is subject to that law's oversight and compliance duties. | U31: The SOP expressly covers plans that aren't directly licensed but are overseen under a statute. | W31: The category doesn't decide SWAGAT eligibility, and pension funds are usually Category I anyway. | X31: Government ownership is one way in. A plan governed by statute also qualifies as a pension fund. | Y31: CDSSF SOP for SWAGAT-FI, 27 May 2026, Section 8, row 4(iv) | Z31: Pension funds governed / recognised by a statutory authority / regulatory body / tax authority for overall supervision and regulation of pensions in the jurisdiction / state. Even where a pension fund is not subject to direct licensing or regulation in its home jurisdiction, in case it operates under— and is subject to oversight and compliance obligations imposed by—an applicable Act/statute, it may be considered eligible for purpose for SWAGAT-FI as a pension fund. | AC31: SWAGAT SOP 27 May 2026, section 8, row 4(iv); Annex C | AE31: Oct 2026 | AG31: =IF(A31="","",IF(COUNTA(O31:R31)<4,"Needs 4 options",IF(ISERROR(FIND(UPPER(S31),"ABCD"))+(LEN(S31)<>1),"Answer must be A-D",IF(OR(D31<1,D31>3),"Difficulty must be 1-3",IF(OR(N31="",T31=""),"Missing question or explanation",IF(COUNTBLANK(U31:X31)<>1,"Need 3 why-not texts",IF(INDEX(U31:X31,1,FIND(UPPER(S31),"ABCD"))<>"","Why-not filled for the answer",IF(AND(B31<>"live",B31<>"draft",B31<>"retired"),"Status must be live/draft/retired","OK")))))))) -> OK
A32: SWG/FVC/211 | B32: live | C32: SW | D32: 1 | E32: SWAGAT FPI adds an FVCI licence | F32: FPI | G32: Registered SWAGAT-FI, a government-related investor | H32: Request | I32: Also register as an FVCI | J32: Documents offered | K32: Asks what extra papers are needed | L32: FPI renewal | M32: 2036 | N32: What's needed? | O32: A full FVCI application with fresh KYC | P32: No further documents; renewal dates align | Q32: A separate DDP for the FVCI registration | R32: SEBI's approval under the FVCI Regulations | S32: B | T32: A SWAGAT-FI that holds or is applying for FPI registration can also register as an FVCI without further documentation. The FVCI renewal date lines up with the FPI's. | U32: The SOP says a SWAGAT-FI can add FVCI without further documentation. | W32: The same DDP handles it, and the depositories keep one combined account. | X32: No separate SEBI approval step is described. The DDP handles the registration. | Y32: CDSSF SOP for SWAGAT-FI, 27 May 2026, Section 3 A.3 | Z32: 3. SWAGAT-FI applying or already registered as FPIs shall also have the option to register as FVCIs, without the need for any further documentation. | AC32: SWAGAT SOP, section 3 A.3 and B.6(b) | AE32: Oct 2026 | AG32: =IF(A32="","",IF(COUNTA(O32:R32)<4,"Needs 4 options",IF(ISERROR(FIND(UPPER(S32),"ABCD"))+(LEN(S32)<>1),"Answer must be A-D",IF(OR(D32<1,D32>3),"Difficulty must be 1-3",IF(OR(N32="",T32=""),"Missing question or explanation",IF(COUNTBLANK(U32:X32)<>1,"Need 3 why-not texts",IF(INDEX(U32:X32,1,FIND(UPPER(S32),"ABCD"))<>"","Why-not filled for the answer",IF(AND(B32<>"live",B32<>"draft",B32<>"retired"),"Status must be live/draft/retired","OK")))))))) -> OK
A33: GSF/REN/301 | B33: live | C33: GS | D33: 1 | E33: G-Sec-only fund comes up for renewal | F33: FPI | G33: Invests only in Government Securities | H33: Event | I33: 3-year block ends next month | J33: Changes since last block | K33: None | L33: Client asks | M33: What do we send? | N33: What does it need to continue? | O33: Only the renewal fee | P33: The fee plus a no-change declaration | Q33: A full KYC refresh plus the fee | R33: Nothing. GS-FPI registration is permanent | S33: A | T33: Under the amended Master Circular, FPIs continue by paying fees and reporting any changes. GS-FPIs only pay the fee; the duty to report changes at renewal doesn't apply to them. | V33: The no-change declaration applies to regular FPIs. GS-FPIs don't have to report changes at renewal. | W33: For GS-FPIs, renewal is just the fee. | X33: The fee is still due for every 3-year block. | Y33: SEBI circular, 16 Jan 2026 (SWAGAT-FI), para 3.3 | Z33: i. FPIs who wish to continue with their registration for the subsequent block of three years (10 years in case of SWAGAT-FI), should pay the fees to their DDPs and inform change in information, if any, as submitted earlier. However, GS-FPIs shall only pay the fees to their DDPs. The requirement of informing any change in information shall not be applicable to GS-FPIs. | AC33: Circular 16 Jan 2026, para 3.3 (Master Circular Part A para 4(i)) | AE33: Oct 2026 | AG33: =IF(A33="","",IF(COUNTA(O33:R33)<4,"Needs 4 options",IF(ISERROR(FIND(UPPER(S33),"ABCD"))+(LEN(S33)<>1),"Answer must be A-D",IF(OR(D33<1,D33>3),"Difficulty must be 1-3",IF(OR(N33="",T33=""),"Missing question or explanation",IF(COUNTBLANK(U33:X33)<>1,"Need 3 why-not texts",IF(INDEX(U33:X33,1,FIND(UPPER(S33),"ABCD"))<>"","Why-not filled for the answer",IF(AND(B33<>"live",B33<>"draft",B33<>"retired"),"Status must be live/draft/retired","OK")))))))) -> OK
A34: GSF/ONB/302 | B34: live | C34: GS | D34: 2 | E34: New G-Sec investor and its group details | F34: Applicant | G34: Fund investing only in G-Secs | H34: Route | I34: General route (not FAR) | J34: Date | K34: October 2026 | L34: Question | M34: Do we need investor-group details? | N34: What's the position now? | O34: Full investor-group details are still required | P34: Not required, whatever the route | Q34: Only required for investors using FAR | R34: Required, unless SEBI approves a waiver | S34: B | T34: The September 2025 circular exempted GS-FPIs investing under the Fully Accessible Route from giving investor-group details. Reports say a 7 September 2026 circular extended this to all FPIs investing only in G-Secs, after RBI dropped the general route's concentration limit. Check the circular itself before relying on this. | U34: That was the rule for general-route investors before September 2026. | W34: It's the other way round: FAR investors were exempted first, in 2025. | X34: The exemption comes from the circular itself. There's no case-by-case approval. | AC34: SEBI circulars 10 Sep 2025 and 7 Sep 2026, as reported | AD34: Y | AE34: Oct 2026 | AG34: =IF(A34="","",IF(COUNTA(O34:R34)<4,"Needs 4 options",IF(ISERROR(FIND(UPPER(S34),"ABCD"))+(LEN(S34)<>1),"Answer must be A-D",IF(OR(D34<1,D34>3),"Difficulty must be 1-3",IF(OR(N34="",T34=""),"Missing question or explanation",IF(COUNTBLANK(U34:X34)<>1,"Need 3 why-not texts",IF(INDEX(U34:X34,1,FIND(UPPER(S34),"ABCD"))<>"","Why-not filled for the answer",IF(AND(B34<>"live",B34<>"draft",B34<>"retired"),"Status must be live/draft/retired","OK")))))))) -> OK
A35: GSF/CNV/303 | B35: live | C35: GS | D35: 2 | E35: GS-FPI wants to buy listed equity | F35: FPI | G35: GS-FPI registered under the lighter regime | H35: Plan | I35: Start buying NSE-listed equity next week | J35: On file | K35: No investor-group details | L35: Request | M35: Just enable the equity account | N35: What has to happen first? | O35: Nothing. Just enable equity trading on the account | P35: Move to regular FPI status and file full details first | Q35: Open a second FPI registration just for the new equity book | R35: Get RBI's approval for the change in investments | S35: B | T35: The GS-FPI relaxations depend on the FPI investing only in Government Securities. Before it invests in anything else, it has to meet the regular FPI requirements through its DDP, including the investor-group details needed to monitor the 10% limit. Confirm the exact steps in the September 2025 circular. | U35: Equity needs the investor-group details GS-FPIs never filed, so the 10% limit can be monitored. | W35: The same registration moves to regular status. No second registration is needed. | X35: This sits within SEBI's registration framework. RBI approval isn't the gate. | AC35: SEBI circular 10 Sep 2025, as summarised by secondary sources | AD35: Y | AE35: Oct 2026 | AG35: =IF(A35="","",IF(COUNTA(O35:R35)<4,"Needs 4 options",IF(ISERROR(FIND(UPPER(S35),"ABCD"))+(LEN(S35)<>1),"Answer must be A-D",IF(OR(D35<1,D35>3),"Difficulty must be 1-3",IF(OR(N35="",T35=""),"Missing question or explanation",IF(COUNTBLANK(U35:X35)<>1,"Need 3 why-not texts",IF(INDEX(U35:X35,1,FIND(UPPER(S35),"ABCD"))<>"","Why-not filled for the answer",IF(AND(B35<>"live",B35<>"draft",B35<>"retired"),"Status must be live/draft/retired","OK")))))))) -> OK
A36: GSF/NRI/304 | B36: live | C36: GS | D36: 3 | E36: NRI-heavy fund buying only G-Secs | F36: FPI | G36: GS-FPI | H36: Largest NRI | I36: 35% of the corpus | J36: Resident Indians | K36: Individuals via LRS | L36: Fund's India exposure | M36: 30% | N36: Is there a contributor problem? | O36: Yes. The largest NRI is above the 25% cap | P36: No. Both contributor conditions are met | Q36: Yes. Resident Indians can't invest in FPIs at all | R36: Yes. Both of the contributor conditions fail | S36: B | T36: The SWAGAT circular adds sub-para (db) next to an existing (da) for GS-FPIs, and both follow the same pattern. The NRI/OCI/RI percentage caps don't apply, but resident Indian individuals can only invest through LRS, in global funds with India exposure below 50%. This fund passes. Check the wording of (da) in the September 2025 circular. | U36: The percentage caps are relaxed for GS-FPIs. | W36: Resident Indian individuals can invest through LRS in funds with India exposure below 50%. | X36: Neither condition fails here. | AC36: Master Circular Part A para 1(ii)(da), as referenced in circular 16 Jan 2026 | AD36: Y | AE36: Oct 2026 | AG36: =IF(A36="","",IF(COUNTA(O36:R36)<4,"Needs 4 options",IF(ISERROR(FIND(UPPER(S36),"ABCD"))+(LEN(S36)<>1),"Answer must be A-D",IF(OR(D36<1,D36>3),"Difficulty must be 1-3",IF(OR(N36="",T36=""),"Missing question or explanation",IF(COUNTBLANK(U36:X36)<>1,"Need 3 why-not texts",IF(INDEX(U36:X36,1,FIND(UPPER(S36),"ABCD"))<>"","Why-not filled for the answer",IF(AND(B36<>"live",B36<>"draft",B36<>"retired"),"Status must be live/draft/retired","OK")))))))) -> OK
A37: ONB/IFS/121 | B37: live | C37: II | D37: 3 | E37: GIFT City fund and the residency test | F37: Applicant | G37: Saffron Bridge Fund, a Category III AIF set up in GIFT IFSC and registered with IFSCA | H37: DDP's concern | I37: GIFT City is in India, so the applicant looks resident | J37: Home-regulator check | K37: IOSCO test not run | L37: Requested | M37: FPI registration | N37: How should the DDP treat the residency and home-regulator tests? | O37: Reject it, since an Indian-resident entity can't be an FPI | P37: Skip them, since Reg 4's proviso switches them off for IFSC | Q37: Register it as Category II only, since IFSCA isn't a foreign regulator | R37: Ask SEBI for a one-off relaxation under Reg 43B | S37: B | T37: The proviso to Reg 4 says clauses (a), (d) and (e) don't apply to an applicant incorporated or set up in an IFSC. Those are the resident-Indian bar, the IOSCO or MoU jurisdiction test, and the BIS test for banks. The Explanation to Reg 5 also deems IFSC applicants appropriately regulated. The other tests, such as sanctions and fit and proper, still apply. | U37: The residency bar in Reg 4(a) is one of the clauses the proviso switches off for IFSC applicants. | W37: IFSC applicants are deemed appropriately regulated, so they aren't pushed into Category II for that reason. | X37: No relaxation is needed. The carve-out is already in the regulation. | Y37: SEBI (FPI) Regulations, 2019, proviso to Regulation 4 | Z37: Provided that clause (a), (d) and (e) shall not apply to an applicant incorporated or established in an International Financial Services Centre. | AA37: SEBI (FPI) Regulations, 2019, Explanation to Regulation 5 | AB37: Explanation: An applicant incorporated or established in an International Financial Services Centre shall be deemed to be appropriately regulated. | AC37: FPI Regs 2019, proviso to Reg 4; Explanation to Reg 5 | AE37: Oct 2026 | AG37: =IF(A37="","",IF(COUNTA(O37:R37)<4,"Needs 4 options",IF(ISERROR(FIND(UPPER(S37),"ABCD"))+(LEN(S37)<>1),"Answer must be A-D",IF(OR(D37<1,D37>3),"Difficulty must be 1-3",IF(OR(N37="",T37=""),"Missing question or explanation",IF(COUNTBLANK(U37:X37)<>1,"Need 3 why-not texts",IF(INDEX(U37:X37,1,FIND(UPPER(S37),"ABCD"))<>"","Why-not filled for the answer",IF(AND(B37<>"live",B37<>"draft",B37<>"retired"),"Status must be live/draft/retired","OK")))))))) -> OK
A38: ONB/IFS/122 | B38: live | C38: II | D38: 3 | E38: Indian sponsor's stake in a GIFT City fund | F38: Applicant | G38: Category II AIF in GIFT IFSC, regulated by IFSCA | H38: Corpus | I38: US$40 million | J38: Sponsor | K38: An Indian asset manager (a resident, not an individual) | L38: Sponsor commitment | M38: 3% of the corpus, or US$1.2 million | N38: Is the sponsor's contribution within limits? | O38: Yes. A resident Indian can hold up to 25% | P38: No. The cap is the lower of 2.5% or US$750,000 | Q38: Yes. Sponsors of IFSC funds have no cap | R38: No. Resident non-individuals can never be constituents | S38: B | T38: Reg 4(c) lets a resident Indian non-individual contribute to an IFSC AIF as its sponsor or manager. For a Category I or II AIF the cap is the lower of 2.5% of corpus or US$750,000. For Category III it's the lower of 5% or US$1.5 million. Here 2.5% is US$1 million, so the US$750,000 limit applies, and US$1.2 million breaches it. | U38: 25% is the single-investor cap for NRIs, OCIs and resident Indian individuals, not for an Indian sponsor entity. | W38: There is a cap, set by the second proviso to Reg 4(c). | X38: They can, in two cases: as the eligible fund manager of a Section 9A fund, or as the sponsor or manager of an IFSC AIF within the cap. | Y38: SEBI (FPI) Regulations, 2019, Regulation 4(c), second proviso | Z38: Provided further that resident Indian, other than individuals, may also be constituents of the applicant, subject to the following conditions, namely – the applicant is an Alternative Investment Fund setup in the International Financial Services Centres and regulated by the International Financial Services Centres Authority; such resident Indian, other than individuals, is a Sponsor or Manager of the applicant; and the contribution of such resident Indian, other than individuals, shall be up to (a) 2.5% of the corpus of the applicant or US $ 7,50,000 (whichever is lower), in case the applicant is a Category I or Category II Alternative Investment Fund; or (b) 5% of the corpus of the applicant or US $ 1.5 million (whichever is lower), in case the applicant is a Category III Alternative Investment Fund; | AC38: FPI Regs 2019, Reg 4(c), first and second provisos | AE38: Oct 2026 | AG38: =IF(A38="","",IF(COUNTA(O38:R38)<4,"Needs 4 options",IF(ISERROR(FIND(UPPER(S38),"ABCD"))+(LEN(S38)<>1),"Answer must be A-D",IF(OR(D38<1,D38>3),"Difficulty must be 1-3",IF(OR(N38="",T38=""),"Missing question or explanation",IF(COUNTBLANK(U38:X38)<>1,"Need 3 why-not texts",IF(INDEX(U38:X38,1,FIND(UPPER(S38),"ABCD"))<>"","Why-not filled for the answer",IF(AND(B38<>"live",B38<>"draft",B38<>"retired"),"Status must be live/draft/retired","OK")))))))) -> OK
A39: ONB/CAT/123 | B39: live | C39: II | D39: 1 | E39: Sovereign fund's 80%-owned subsidiary | F39: Applicant | G39: Kestrel Holdings, an investment company | H39: Ownership | I39: 80% sovereign wealth fund, 20% a private bank | J39: Regulated | K39: No | L39: Requested | M39: Category I | N39: Which category fits? | O39: Category I, as a government-related investor | P39: Category II, as an unregulated corporate body | Q39: Category I, but only if 100% government owned | R39: Not eligible, because it's partly private | S39: A | T39: Reg 5(a)(i) covers government and government-related investors. That includes entities they control, or own at least 75% of, directly or indirectly. 80% clears the test. | V39: Corporate bodies usually fall in Category II, but 75%+ government ownership moves this one into Category I. | W39: The test is control or at least 75% ownership, not 100%. | X39: Mixed ownership is fine as long as the 75% or control test is met. | Y39: SEBI (FPI) Regulations, 2019, Regulation 5(a)(i) | Z39: (i) Government and Government related investors such as central banks, sovereign wealth funds, international or multilateral organizations or agencies including entities controlled or at least 75% directly or indirectly owned by such Government and Government related investor(s); | AC39: FPI Regs 2019, Reg 5(a)(i) | AE39: Oct 2026 | AG39: =IF(A39="","",IF(COUNTA(O39:R39)<4,"Needs 4 options",IF(ISERROR(FIND(UPPER(S39),"ABCD"))+(LEN(S39)<>1),"Answer must be A-D",IF(OR(D39<1,D39>3),"Difficulty must be 1-3",IF(OR(N39="",T39=""),"Missing question or explanation",IF(COUNTBLANK(U39:X39)<>1,"Need 3 why-not texts",IF(INDEX(U39:X39,1,FIND(UPPER(S39),"ABCD"))<>"","Why-not filled for the answer",IF(AND(B39<>"live",B39<>"draft",B39<>"retired"),"Status must be live/draft/retired","OK")))))))) -> OK
A40: ONB/TAT/124 | B40: live | C40: II | D40: 1 | E40: How long can the DDP take? | F40: Application received | G40: 2 March | H40: DDP asked for more documents | I40: 10 March | J40: Documents received | K40: 25 March | L40: Client asks | M40: When is the latest we get a decision? | N40: By when must the DDP decide? | O40: 30 days from 2 March | P40: 30 days from 25 March | Q40: 7 working days from 25 March | R40: There is no deadline | S40: B | T40: Under Reg 7(2), the DDP should decide as soon as possible. The latest is 30 days after it receives the application, or after the further information it asked for under Reg 6 arrives, whichever is later. Here that means 30 days from 25 March. | U40: The clock runs from whichever date is later, and the requested documents arrived later. | W40: 7 working days is the FPI's deadline for reporting changes, not the DDP's decision deadline. | X40: Reg 7(2) sets a 30-day outer limit. | Y40: SEBI (FPI) Regulations, 2019, Regulation 7(2) | Z40: (2) The designated depository participant shall endeavour to dispose of the application for grant of certificate of registration as soon as possible but not later than thirty days after receipt of application by the designated depository participant, or after the information called for under regulation 6 has been furnished; whichever is later. | AC40: FPI Regs 2019, Reg 6(1), Reg 7(2) | AE40: Oct 2026 | AG40: =IF(A40="","",IF(COUNTA(O40:R40)<4,"Needs 4 options",IF(ISERROR(FIND(UPPER(S40),"ABCD"))+(LEN(S40)<>1),"Answer must be A-D",IF(OR(D40<1,D40>3),"Difficulty must be 1-3",IF(OR(N40="",T40=""),"Missing question or explanation",IF(COUNTBLANK(U40:X40)<>1,"Need 3 why-not texts",IF(INDEX(U40:X40,1,FIND(UPPER(S40),"ABCD"))<>"","Why-not filled for the answer",IF(AND(B40<>"live",B40<>"draft",B40<>"retired"),"Status must be live/draft/retired","OK")))))))) -> OK
A41: ONB/VAL/125 | B41: live | C41: II | D41: 2 | E41: Does the FPI certificate expire? | F41: FPI | G41: Category I pension fund, registered 2023 | H41: Client says | I41: "Our certificate expires in 2026, so we need a new one" | J41: Fees | K41: Paid for the current 3-year block | L41: Certificate wording | M41: Valid till suspended, cancelled or surrendered | N41: What's correct? | O41: The certificate expires every three years and is reissued | P41: It's permanent, but fees are due for every three-year block | Q41: It expires after 10 years | R41: It's permanent and no further fees are due | S41: B | T41: Reg 9(1) makes registration permanent unless SEBI suspends or cancels it, or the FPI surrenders it. Separately, the Second Schedule makes fees payable for every three-year block, and a registration stops being valid beyond the period fees cover. | U41: There's no reissue. The certificate stands, and the FPI pays continuance fees. | W41: 10-year blocks apply only to SWAGAT-FIs. | X41: Fees are still due every three years to keep the registration valid. | Y41: SEBI (FPI) Regulations, 2019, Regulation 9(1) | Z41: 9. (1) Subject to the compliance with the provisions of the Act, these regulations and the circulars issued thereunder, the registration granted by the designated depository participant on behalf of the Board under these regulations shall be permanent unless suspended or cancelled by the Board or surrendered by the foreign portfolio investor. | AA41: SEBI (FPI) Regulations, 2019, Second Schedule, Part A(2) | AB41: (2) Foreign portfolio investor belonging to Category I and II shall pay registration fees for every block of three years, till the validity of its registration, | AC41: FPI Regs 2019, Reg 9(1); First Schedule; Second Schedule Part A(2) | AE41: Oct 2026 | AG41: =IF(A41="","",IF(COUNTA(O41:R41)<4,"Needs 4 options",IF(ISERROR(FIND(UPPER(S41),"ABCD"))+(LEN(S41)<>1),"Answer must be A-D",IF(OR(D41<1,D41>3),"Difficulty must be 1-3",IF(OR(N41="",T41=""),"Missing question or explanation",IF(COUNTBLANK(U41:X41)<>1,"Need 3 why-not texts",IF(INDEX(U41:X41,1,FIND(UPPER(S41),"ABCD"))<>"","Why-not filled for the answer",IF(AND(B41<>"live",B41<>"draft",B41<>"retired"),"Status must be live/draft/retired","OK")))))))) -> OK
A42: EXT/SUR/126 | B42: live | C42: II | D42: 2 | E42: Fee unpaid, account already empty | F42: FPI | G42: Category II fund that stopped investing | H42: Holdings | I42: No cash, securities or derivatives in India | J42: Renewal fee | K42: Not paid by the due date | L42: Client | M42: Not responding | N42: What happens to the registration? | O42: It stays active indefinitely until the client responds | P42: It's treated as surrendered, subject to SEBI's approval | Q42: The DDP cancels the registration on the due date | R42: SEBI starts enforcement proceedings against it for non-payment | S42: B | T42: Under Reg 9(3), an FPI that doesn't pay continuance fees by the due date and has no cash, securities or derivatives in India is treated as having applied for surrender. The DDP processes the surrender after getting SEBI's approval. | U42: Without the fee the registration stops being valid, and the rule treats it as surrendered. | W42: The DDP doesn't cancel registrations. It processes the surrender, and only with SEBI's approval. | X42: Unpaid fees with nothing held are handled as a surrender, not as a violation. | Y42: SEBI (FPI) Regulations, 2019, Regulation 9(3) | Z42: (3) When the foreign portfolio investor fails to pay the required fees for continuance of registration within the specified due date and such foreign portfolio investor does not have any cash or security or derivative position in India, such foreign portfolio investor shall be deemed to have applied for surrender of its registration and the designated depository participant of such foreign portfolio investor shall process the surrender after obtaining the approval from the Board. | AC42: FPI Regs 2019, Reg 9(3)–(4) | AE42: Oct 2026 | AG42: =IF(A42="","",IF(COUNTA(O42:R42)<4,"Needs 4 options",IF(ISERROR(FIND(UPPER(S42),"ABCD"))+(LEN(S42)<>1),"Answer must be A-D",IF(OR(D42<1,D42>3),"Difficulty must be 1-3",IF(OR(N42="",T42=""),"Missing question or explanation",IF(COUNTBLANK(U42:X42)<>1,"Need 3 why-not texts",IF(INDEX(U42:X42,1,FIND(UPPER(S42),"ABCD"))<>"","Why-not filled for the answer",IF(AND(B42<>"live",B42<>"draft",B42<>"retired"),"Status must be live/draft/retired","OK")))))))) -> OK
A43: ONB/CAT/127 | B43: live | C43: II | D43: 2 | E43: Category II fund now qualifies for Category I | F43: FPI | G43: Category II fund | H43: Change | I43: Its manager is now registered as a Category I FPI and has given an undertaking | J43: Request | K43: Move to Category I | L43: Holdings | M43: Listed equity | N43: How does it move? | O43: Automatically. The DDP switches it over | P43: It applies to its DDP and pays the fee | Q43: It surrenders and registers again from scratch | R43: Only SEBI itself can recategorise an FPI | S43: B | T43: An FPI that wants to move from Category II to Category I applies to its DDP with the required information and documents, and pays the applicable fee. The DDP recategorises the existing registration on SEBI's behalf. | U43: There's no automatic upgrade. The FPI has to request it. | W43: No surrender is needed. The existing registration is recategorised. | X43: The DDP handles recategorisation on SEBI's behalf. | Y43: SEBI Operational Guidelines for FPIs and DDPs, Part A 1 | Z43: After the exercise of deemed re-categorisation as mentioned above, an FPI desirous to be re-categorized from Category II FPI to Category I, can request to DDP along with requisite information, documents and payment of applicable fees. | AC43: Op. Guidelines Part A 1; FPI Regs 2019, Reg 5 | AE43: Oct 2026 | AG43: =IF(A43="","",IF(COUNTA(O43:R43)<4,"Needs 4 options",IF(ISERROR(FIND(UPPER(S43),"ABCD"))+(LEN(S43)<>1),"Answer must be A-D",IF(OR(D43<1,D43>3),"Difficulty must be 1-3",IF(OR(N43="",T43=""),"Missing question or explanation",IF(COUNTBLANK(U43:X43)<>1,"Need 3 why-not texts",IF(INDEX(U43:X43,1,FIND(UPPER(S43),"ABCD"))<>"","Why-not filled for the answer",IF(AND(B43<>"live",B43<>"draft",B43<>"retired"),"Status must be live/draft/retired","OK")))))))) -> OK
A44: MON/CAT/128 | B44: live | C44: II | D44: 3 | E44: Category I fund loses its regulated status | F44: FPI | G44: Category I regulated fund | H44: Event | I44: Its home licence lapses, so it's no longer appropriately regulated | J44: Now fits | K44: Category II | L44: Holdings | M44: Listed equity | N44: What's the process? | O44: Nothing changes until its next renewal | P44: Fresh buys are blocked until extra KYC; sales allowed | Q44: It must sell all its Indian holdings within 5 trading days | R44: The DDP cancels the registration | S44: B | T44: An FPI that stops meeting its category's requirements must promptly tell its DDP so it can be reclassified, and may need to provide extra KYC. The custodian blocks fresh purchases until that's done, but the FPI can keep selling. If it still holds securities 180 days after the block, it's referred to SEBI. | U44: Reclassification is prompt, not deferred to renewal. | W44: There's no forced sale. Selling stays open during the block. | X44: It's reclassified, not cancelled. | Y44: SEBI Operational Guidelines for FPIs and DDPs, Part A 14 | Z44: If an FPI registered under a particular category/sub-category fails to comply with applicable eligibility requirements, it shall promptly notify this change to its DDP to be reclassified under appropriate category/sub-category. FPI may be required to provide to the DDP with additional KYC documents, as applicable. The concerned DDP / Custodian shall not allow (block) such FPI to make fresh purchases till additional KYC requirements (if any) are complied with. However, such FPI shall be allowed to continue to sell the securities already purchased by it. If such FPI continues to hold securities 180 days after blocking, such FPI shall be referred to SEBI for any further action. | AC44: Op. Guidelines Part A 14; FPI Regs 2019, Reg 22(1)(c) | AE44: Oct 2026 | AG44: =IF(A44="","",IF(COUNTA(O44:R44)<4,"Needs 4 options",IF(ISERROR(FIND(UPPER(S44),"ABCD"))+(LEN(S44)<>1),"Answer must be A-D",IF(OR(D44<1,D44>3),"Difficulty must be 1-3",IF(OR(N44="",T44=""),"Missing question or explanation",IF(COUNTBLANK(U44:X44)<>1,"Need 3 why-not texts",IF(INDEX(U44:X44,1,FIND(UPPER(S44),"ABCD"))<>"","Why-not filled for the answer",IF(AND(B44<>"live",B44<>"draft",B44<>"retired"),"Status must be live/draft/retired","OK")))))))) -> OK
A45: DDP/APP/131 | B45: live | C45: III | D45: 3 | E45: Custodian that isn't an AD Category-1 bank | F45: Applicant | G45: Indian custody firm seeking DDP approval | H45: Registered as | I45: Depository participant and custodian with SEBI | J45: Banking status | K45: Not an AD Category-1 bank | L45: Experience | M45: 15 years of custody for foreign clients | N45: Can SEBI approve it as a DDP? | O45: No. Reg 11(1) requires AD Category-1 status, full stop | P45: Possibly, under Reg 11(2), with an AD Category-1 tie-up | Q45: Yes. DP and custodian registration with SEBI is enough on its own | R45: Yes, as long as NSDL recommends the application | S45: B | T45: Reg 11(1) sets the standard tests: registered DP, registered custodian, AD Category-1 bank, multinational presence, anti-money-laundering systems, and fit and proper. Reg 11(2) lets SEBI consider an entity with enough custody experience where approval helps develop the market. The entity must be registered as a participant and custodian and have a tie-up with an AD Category-1 bank. | U45: Reg 11(2) is an express exception to Reg 11(1). | W45: Under Reg 11(1) it would also need AD Category-1 status. Without that, only the Reg 11(2) route is open. | X45: The depository forwards the application with its recommendation, but SEBI decides on the regulation's tests. | Y45: SEBI (FPI) Regulations, 2019, Regulation 11(2) | Z45: (2) Notwithstanding anything contained in sub-regulation (1) of this regulation, the Board may consider an application from an entity, regulated in India or in its home jurisdiction, for grant of approval to act as designated depository participant, upon being satisfied that the applicant has sufficient experience in providing custodial services and that the grant of such approval is in the interest of the development of the securities market: Provided that such entity shall be registered with the Board as a participant and custodian, and shall have a tie up with Authorised Dealer Category-1 bank. | AC45: FPI Regs 2019, Reg 11(1)–(2) | AE45: Oct 2026 | AG45: =IF(A45="","",IF(COUNTA(O45:R45)<4,"Needs 4 options",IF(ISERROR(FIND(UPPER(S45),"ABCD"))+(LEN(S45)<>1),"Answer must be A-D",IF(OR(D45<1,D45>3),"Difficulty must be 1-3",IF(OR(N45="",T45=""),"Missing question or explanation",IF(COUNTBLANK(U45:X45)<>1,"Need 3 why-not texts",IF(INDEX(U45:X45,1,FIND(UPPER(S45),"ABCD"))<>"","Why-not filled for the answer",IF(AND(B45<>"live",B45<>"draft",B45<>"retired"),"Status must be live/draft/retired","OK")))))))) -> OK
A46: DDP/APP/132 | B46: live | C46: III | D46: 2 | E46: Filing a DDP application | F46: Applicant | G46: Bank that is an NSDL participant, a SEBI custodian and an AD Category-1 bank | H46: Wants | I46: Approval as a DDP | J46: Question | K46: Where to file and what to pay up front | L46: Status | M46: Systems ready | N46: What's the right route? | O46: File directly with SEBI and pay ₹5,00,000 | P46: File through NSDL with a ₹10,000 application fee | Q46: File with RBI, which consults SEBI | R46: File through an existing DDP, which sponsors it | S46: B | T46: Under Reg 10(2)–(3), the application goes through the depository the applicant is a participant of, with a ₹10,000 application fee. The depository certifies eligibility and forwards it to SEBI within 30 days with its recommendation. The ₹5,00,000 approval fee is due when SEBI grants approval. | U46: ₹5,00,000 is the approval fee, paid when approval is granted, and the application goes through the depository. | W46: DDP approval sits with SEBI under the FPI Regulations, not RBI. | X46: DDPs register FPIs. They don't sponsor other DDPs. | Y46: SEBI (FPI) Regulations, 2019, Regulation 10(2)–(3) | Z46: (2) An application for approval to act as a designated depository participant shall be made to the Board through a depository with which the applicant has an agreement to act as a participant and shall be accompanied by the application fee specified in Part B of the Second Schedule which shall be paid in the manner specified therein. (3) The depository shall forward the application to the Board, as early as possible, but not later than thirty days from the date of its receipt by the depository, along with its recommendations and after certifying that the participant has complied with the eligibility criteria as provided for in these regulations. | AC46: FPI Regs 2019, Reg 10(2)–(3); Second Schedule Part B | AE46: Oct 2026 | AG46: =IF(A46="","",IF(COUNTA(O46:R46)<4,"Needs 4 options",IF(ISERROR(FIND(UPPER(S46),"ABCD"))+(LEN(S46)<>1),"Answer must be A-D",IF(OR(D46<1,D46>3),"Difficulty must be 1-3",IF(OR(N46="",T46=""),"Missing question or explanation",IF(COUNTBLANK(U46:X46)<>1,"Need 3 why-not texts",IF(INDEX(U46:X46,1,FIND(UPPER(S46),"ABCD"))<>"","Why-not filled for the answer",IF(AND(B46<>"live",B46<>"draft",B46<>"retired"),"Status must be live/draft/retired","OK")))))))) -> OK
A47: DDP/VAL/133 | B47: live | C47: III | D47: 2 | E47: SEBI wants to withdraw a DDP's approval | F47: DDP | G47: Approved in 2020 | H47: Inspection finding | I47: Repeated breaches of FPI circulars | J47: SEBI view | K47: Approval should be withdrawn | L47: DDP argues | M47: Isn't our approval time-limited anyway? | N47: Which is correct? | O47: Approval lapses after five years, so SEBI can simply let it run out | P47: Approval is permanent; SEBI can withdraw it by order after a hearing | Q47: SEBI can withdraw it immediately without a hearing | R47: Only RBI can withdraw a DDP's approval | S47: B | T47: Reg 16 makes DDP approval permanent unless it is suspended, withdrawn or surrendered. Under Reg 17, if a DDP breaches its conditions or the securities laws, SEBI may suspend or withdraw approval by order, after giving the DDP a reasonable opportunity to be heard. | U47: DDP approval has no fixed term under Reg 16. | W47: Reg 17 requires a reasonable opportunity to be heard first. | X47: SEBI grants the approval, and only SEBI withdraws it. | Y47: SEBI (FPI) Regulations, 2019, Regulation 16 | Z47: 16. Subject to the compliance with the provisions of the Act, these regulations and the circulars issued thereunder, the approval granted by the Board under these regulations shall be permanent unless suspended or withdrawn by the Board or surrendered by the designated depository participant. | AA47: SEBI (FPI) Regulations, 2019, Regulation 17 | AB47: the Board may, without prejudice to any action under the securities laws or directions, instructions or circulars issued thereunder, by an order suspend or withdraw such approval after providing the designated depository participant a reasonable opportunity of being heard. | AC47: FPI Regs 2019, Reg 16–18 | AE47: Oct 2026 | AG47: =IF(A47="","",IF(COUNTA(O47:R47)<4,"Needs 4 options",IF(ISERROR(FIND(UPPER(S47),"ABCD"))+(LEN(S47)<>1),"Answer must be A-D",IF(OR(D47<1,D47>3),"Difficulty must be 1-3",IF(OR(N47="",T47=""),"Missing question or explanation",IF(COUNTBLANK(U47:X47)<>1,"Need 3 why-not texts",IF(INDEX(U47:X47,1,FIND(UPPER(S47),"ABCD"))<>"","Why-not filled for the answer",IF(AND(B47<>"live",B47<>"draft",B47<>"retired"),"Status must be live/draft/retired","OK")))))))) -> OK
A48: DDP/REJ/134 | B48: live | C48: III | D48: 1 | E48: DDP applicant is turned down | F48: Applicant | G48: Proposed DDP | H48: SEBI received | I48: Application on 1 April | J48: Outcome | K48: Rejected in writing on 20 April, citing missing systems | L48: Applicant asks | M48: Is there any recourse? | N48: What can it do? | O48: Nothing. SEBI's rejection is final | P48: Ask SEBI to reconsider within 30 days | Q48: Appeal to the depository that forwarded it | R48: Wait one year and then reapply | S48: B | T48: Under Reg 15, SEBI gives reasons for a rejection in writing, and the applicant can ask for reconsideration within 30 days. SEBI decides after a hearing. Before rejecting at all, Reg 14 gives the applicant a reasonable chance to fix deficiencies. Reg 13(2) asks SEBI to decide applications within 30 days. | U48: Reg 15(3) gives a 30-day reconsideration route. | W48: The depository only forwards the application. It has no appeal role. | X48: The regulations set no waiting period. | Y48: SEBI (FPI) Regulations, 2019, Regulation 15(3) | Z48: (3) The applicant, who is aggrieved by the decision of the Board under sub-regulation (1) may, within a period of thirty days from the date of receipt of communication under sub-regulation (2), apply to the Board for reconsideration of its decision. | AC48: FPI Regs 2019, Reg 13(2), 14, 15 | AE48: Oct 2026 | AG48: =IF(A48="","",IF(COUNTA(O48:R48)<4,"Needs 4 options",IF(ISERROR(FIND(UPPER(S48),"ABCD"))+(LEN(S48)<>1),"Answer must be A-D",IF(OR(D48<1,D48>3),"Difficulty must be 1-3",IF(OR(N48="",T48=""),"Missing question or explanation",IF(COUNTBLANK(U48:X48)<>1,"Need 3 why-not texts",IF(INDEX(U48:X48,1,FIND(UPPER(S48),"ABCD"))<>"","Why-not filled for the answer",IF(AND(B48<>"live",B48<>"draft",B48<>"retired"),"Status must be live/draft/retired","OK")))))))) -> OK
A49: INV/DLV/141 | B49: live | C49: IV | D49: 1 | E49: Intraday trading in cash equity | F49: FPI | G49: Category II fund | H49: Plan | I49: Buy and sell the same shares in one day, without delivery | J49: Segment | K49: Cash market | L49: Broker | M49: SEBI-registered | N49: Is this allowed? | O49: Yes, through a registered broker | P49: No. FPIs must take and give delivery | Q49: Yes, for Category I only | R49: Yes, up to 10% of the company | S49: B | T49: Under Reg 20(4)(a), FPIs deal in securities only by taking and giving delivery. The exceptions include exchange-traded derivatives, short selling under SEBI's framework, and market-making arrangements. Selling against purchases that haven't settled isn't allowed either. | U49: A registered broker is required, but that doesn't remove the delivery rule. | W49: The delivery rule applies to both categories. | X49: The 10% limit is about holding size, not delivery. | Y49: SEBI (FPI) Regulations, 2019, Regulation 20(4)(a) | Z49: (a) A foreign portfolio investor shall transact in the securities in India only on the basis of taking and giving delivery of securities purchased or sold; | AC49: FPI Regs 2019, Reg 20(4)(a)–(b); Op. Guidelines Part C 5 | AE49: Oct 2026 | AG49: =IF(A49="","",IF(COUNTA(O49:R49)<4,"Needs 4 options",IF(ISERROR(FIND(UPPER(S49),"ABCD"))+(LEN(S49)<>1),"Answer must be A-D",IF(OR(D49<1,D49>3),"Difficulty must be 1-3",IF(OR(N49="",T49=""),"Missing question or explanation",IF(COUNTBLANK(U49:X49)<>1,"Need 3 why-not texts",IF(INDEX(U49:X49,1,FIND(UPPER(S49),"ABCD"))<>"","Why-not filled for the answer",IF(AND(B49<>"live",B49<>"draft",B49<>"retired"),"Status must be live/draft/retired","OK")))))))) -> OK
A50: INV/BRK/142 | B50: live | C50: IV | D50: 3 | E50: Tendering in a buyback without a broker | F50: FPI | G50: Category I fund | H50: Event | I50: Listed company runs a buyback under the SEBI Buy-back Regulations | J50: Plan | K50: Tender shares directly | L50: Question | M50: Is a SEBI-registered broker required? | N50: Which is right? | O50: Yes. Every FPI deal goes through a registered broker | P50: No. Buyback sales are exempt from the broker rule | Q50: Only Category II FPIs are exempt | R50: Buybacks aren't open to FPIs | S50: B | T50: Reg 20(4)(c) requires FPIs to deal through SEBI-registered brokers, but Reg 20(4)(d) lists exceptions. They include G-Sec deals done as RBI specifies, open offers, delisting offers, buybacks, government disinvestment offers, corporate bonds, and transfers of rights entitlements. | U50: Reg 20(4)(d) lists specific exceptions, and buybacks are one of them. | W50: The exceptions apply to all FPIs. | X50: FPIs can tender. The regulation names buyback sales specifically. | Y50: SEBI (FPI) Regulations, 2019, Regulation 20(4)(c) | Z50: (c) The transaction involving dealing in securities by a foreign portfolio investor shall be only through stock brokers registered with the Board; | AA50: SEBI (FPI) Regulations, 2019, Regulation 20(4)(d)(iv) | AB50: (iv) sale of securities in accordance with the Securities and Exchange Board of India (Buy-back of Securities) Regulations, 2018; | AC50: FPI Regs 2019, Reg 20(4)(c)–(d) | AE50: Oct 2026 | AG50: =IF(A50="","",IF(COUNTA(O50:R50)<4,"Needs 4 options",IF(ISERROR(FIND(UPPER(S50),"ABCD"))+(LEN(S50)<>1),"Answer must be A-D",IF(OR(D50<1,D50>3),"Difficulty must be 1-3",IF(OR(N50="",T50=""),"Missing question or explanation",IF(COUNTBLANK(U50:X50)<>1,"Need 3 why-not texts",IF(INDEX(U50:X50,1,FIND(UPPER(S50),"ABCD"))<>"","Why-not filled for the answer",IF(AND(B50<>"live",B50<>"draft",B50<>"retired"),"Status must be live/draft/retired","OK")))))))) -> OK
A51: INV/BEN/143 | B51: live | C51: IV | D51: 2 | E51: Shares in the global custodian's name | F51: FPI | G51: Category I fund | H51: Global custodian wants | I51: Indian shares registered in its omnibus name | J51: Local custodian | K51: The FPI's DDP | L51: SEBI approval | M51: None | N51: Can the shares be held that way? | O51: Yes. Omnibus holding is routine for global custodians | P51: No. They must be in the FPI's own name | Q51: Yes, if the FPI gives the custodian a power of attorney | R51: Yes, but only for its Government Securities | S51: B | T51: Under Reg 20(6), unless SEBI approves otherwise, securities are registered in the FPI's name as beneficial owner. FPIs also hold securities only in demat form, with narrow exceptions for older physical shares and rights entitlements. | U51: Omnibus holding isn't allowed in India without SEBI approval. | W51: A power of attorney lets the custodian act, but it doesn't change whose name the securities are in. | X51: Reg 20(6) has no G-Sec carve-out. | Y51: SEBI (FPI) Regulations, 2019, Regulation 20(6) | Z51: (6) Unless otherwise approved by the Board, securities shall be registered in the name of the foreign portfolio investor as a beneficial owner as defined in clause (a) of sub-section (1) of section 2 of the Depositories Act, 1996. | AC51: FPI Regs 2019, Reg 20(4)(e), Reg 20(6) | AE51: Oct 2026 | AG51: =IF(A51="","",IF(COUNTA(O51:R51)<4,"Needs 4 options",IF(ISERROR(FIND(UPPER(S51),"ABCD"))+(LEN(S51)<>1),"Answer must be A-D",IF(OR(D51<1,D51>3),"Difficulty must be 1-3",IF(OR(N51="",T51=""),"Missing question or explanation",IF(COUNTBLANK(U51:X51)<>1,"Need 3 why-not texts",IF(INDEX(U51:X51,1,FIND(UPPER(S51),"ABCD"))<>"","Why-not filled for the answer",IF(AND(B51<>"live",B51<>"draft",B51<>"retired"),"Status must be live/draft/retired","OK")))))))) -> OK
A52: INV/CA/144 | B52: live | C52: IV | D52: 2 | E52: Unlisted shares from a merger | F52: FPI | G52: Category II fund holding listed shares of Company A | H52: Event | I52: Merger approved by the tribunal | J52: Result | K52: A's shareholders receive shares of unlisted Company B | L52: FPI asks | M52: Can we keep B's shares? | N52: How are B's shares treated? | O52: Not allowed. The FPI must sell before allotment | P52: It can hold and sell them, but they count as FDI | Q52: They count as FPI investment like listed shares | R52: They must be transferred to a resident Indian buyer at once | S52: B | T52: Reg 20(4)(d)(x) lets FPIs receive, hold and sell unlisted securities they get through involuntary corporate actions, such as an approved merger or demerger. Its proviso treats those unlisted holdings as foreign direct investment. | U52: Receiving shares through an involuntary corporate action is expressly allowed. | W52: The proviso treats unlisted holdings as FDI, not portfolio investment. | X52: There's no forced transfer. The FPI can hold and sell under FDI rules. | Y52: SEBI (FPI) Regulations, 2019, Regulation 20(4)(d)(x) | Z52: (x) transactions to receive, hold and sell unlisted securities as referred at regulation 20(2) and transactions in unlisted securities received through involuntary corporate actions including a scheme of a merger or demerger approved in accordance with the provisions of the Companies Act, 2013 as well as the applicable guidelines issued by the Board or pursuant to implementation of any resolution plan approved under the Insolvency and Bankruptcy Code, 2016 or in accordance with the guidelines issued by the Government of India or the Reserve Bank of India or any other regulator for a scheme of debt resolution: Provided that such unlisted holdings of the foreign portfolio investor shall be treated as Foreign Direct Investment; | AC52: FPI Regs 2019, Reg 20(4)(d)(x) and proviso | AE52: Oct 2026 | AG52: =IF(A52="","",IF(COUNTA(O52:R52)<4,"Needs 4 options",IF(ISERROR(FIND(UPPER(S52),"ABCD"))+(LEN(S52)<>1),"Answer must be A-D",IF(OR(D52<1,D52>3),"Difficulty must be 1-3",IF(OR(N52="",T52=""),"Missing question or explanation",IF(COUNTBLANK(U52:X52)<>1,"Need 3 why-not texts",IF(INDEX(U52:X52,1,FIND(UPPER(S52),"ABCD"))<>"","Why-not filled for the answer",IF(AND(B52<>"live",B52<>"draft",B52<>"retired"),"Status must be live/draft/retired","OK")))))))) -> OK
A53: INV/ODI/145 | B53: live | C53: IV | D53: 2 | E53: ODI holder wants to transfer to an affiliate | F53: ODI issuer | G53: Category I FPI | H53: Holder | I53: Eligible subscriber, transferring to an affiliate | J53: Affiliate | K53: Eligible as Category I; not pre-approved | L53: Issuer | M53: Not yet asked | N53: What's needed? | O53: Nothing. ODIs move freely between eligible persons | P53: The issuer's prior consent | Q53: SEBI's approval of each transfer | R53: The DDP's consent | S53: B | T53: Under Reg 21(2), an ODI can only be transferred to someone who meets the issuance conditions. The issuing FPI's prior consent is also needed, unless it has pre-approved the transferee. Issuers report all transfers, including those during the month, in their monthly ODI reports. | U53: The transferee must be eligible, and the issuer must also consent unless it pre-approved them. | W53: SEBI receives reports. It doesn't approve each transfer. | X53: The DDP has no consent role for ODI transfers. | Y53: SEBI (FPI) Regulations, 2019, Regulation 21(2) | Z53: (2) A foreign portfolio investor shall ensure that any transfer of offshore derivative instruments issued by or on behalf of it, is subject to the following conditions – (a) such offshore derivative instruments are transferred to persons subject to the fulfilment of sub-regulation (1); and (b) prior consent of the foreign portfolio investor is obtained for such transfer, except in cases, where the persons to whom the offshore derivative instruments are to be transferred, are pre-approved by the foreign portfolio investor. | AC53: FPI Regs 2019, Reg 21(2); Op. Guidelines Part D 3(i) | AE53: Oct 2026 | AG53: =IF(A53="","",IF(COUNTA(O53:R53)<4,"Needs 4 options",IF(ISERROR(FIND(UPPER(S53),"ABCD"))+(LEN(S53)<>1),"Answer must be A-D",IF(OR(D53<1,D53>3),"Difficulty must be 1-3",IF(OR(N53="",T53=""),"Missing question or explanation",IF(COUNTBLANK(U53:X53)<>1,"Need 3 why-not texts",IF(INDEX(U53:X53,1,FIND(UPPER(S53),"ABCD"))<>"","Why-not filled for the answer",IF(AND(B53<>"live",B53<>"draft",B53<>"retired"),"Status must be live/draft/retired","OK")))))))) -> OK
A54: OBL/ENC/151 | B54: live | C54: V | D54: 2 | E54: Pledging Indian shares to a prime broker | F54: FPI | G54: Category II hedge fund | H54: Plan | I54: Pledge Indian shares to its offshore prime broker | J54: Purpose | K54: Financing | L54: Regulatory need | M54: None | N54: Is this allowed? | O54: Yes. FPIs can pledge their holdings freely | P54: No. Only regulatory encumbrances are allowed | Q54: Yes, as long as the prime broker is regulated | R54: Yes, up to 10% of its Indian holdings | S54: B | T54: Under Reg 22(1)(k), an FPI must keep its securities free from all encumbrances. Encumbrances created to meet statutory or regulatory requirements, such as margin obligations, don't count. | U54: Reg 22(1)(k) bans encumbrances unless they meet a statutory or regulatory requirement. | W54: The prime broker being regulated doesn't create an exception. | X54: There's no percentage allowance. | Y54: SEBI (FPI) Regulations, 2019, Regulation 22(1)(k) | Z54: (k) ensure that securities held by foreign portfolio investors are free from all encumbrances. Explanation – An encumbrance created to meet any statutory and regulatory requirements shall not be considered under this clause. | AC54: FPI Regs 2019, Reg 22(1)(k) and Explanation | AE54: Oct 2026 | AG54: =IF(A54="","",IF(COUNTA(O54:R54)<4,"Needs 4 options",IF(ISERROR(FIND(UPPER(S54),"ABCD"))+(LEN(S54)<>1),"Answer must be A-D",IF(OR(D54<1,D54>3),"Difficulty must be 1-3",IF(OR(N54="",T54=""),"Missing question or explanation",IF(COUNTBLANK(U54:X54)<>1,"Need 3 why-not texts",IF(INDEX(U54:X54,1,FIND(UPPER(S54),"ABCD"))<>"","Why-not filled for the answer",IF(AND(B54<>"live",B54<>"draft",B54<>"retired"),"Status must be live/draft/retired","OK")))))))) -> OK
A55: OBL/RPT/152 | B55: live | C55: V | D55: 2 | E55: Overseas regulator fines the FPI | F55: FPI | G55: Category I asset manager | H55: Event | I55: Home regulator imposes a penalty on 3 March | J55: Licence | K55: Unaffected | L55: Question | M55: When to tell the DDP and SEBI | N55: What's the deadline? | O55: At the next continuance of registration | P55: Within 7 working days | Q55: Within 30 days of the penalty order | R55: Only if the licence is cancelled | S55: B | T55: Under Reg 22(1)(e), the FPI tells SEBI and its DDP, as soon as possible and within 7 working days, about any penalty, pending litigation or proceedings, or inspection findings by an overseas regulator. The same deadline applies to false or misleading information and material changes. A past action doesn't automatically make the FPI ineligible. | U55: Waiting for continuance breaches the 7-working-day deadline. | W55: The deadline is 7 working days, not 30 days. | X55: Any penalty or proceeding must be reported, not just a cancellation. | Y55: SEBI (FPI) Regulations, 2019, Regulation 22(1)(e) | Z55: (e) as soon as possible but not later than seven working days, inform the Board and the designated depository participant, in case of any penalty, pending litigation or proceedings, findings of inspections or investigations for which action may have been taken or is in the process of being taken by an overseas regulator against it; | AC55: FPI Regs 2019, Reg 22(1)(b), (c), (e); Op. Guidelines Part A 2(vi) | AE55: Oct 2026 | AG55: =IF(A55="","",IF(COUNTA(O55:R55)<4,"Needs 4 options",IF(ISERROR(FIND(UPPER(S55),"ABCD"))+(LEN(S55)<>1),"Answer must be A-D",IF(OR(D55<1,D55>3),"Difficulty must be 1-3",IF(OR(N55="",T55=""),"Missing question or explanation",IF(COUNTBLANK(U55:X55)<>1,"Need 3 why-not texts",IF(INDEX(U55:X55,1,FIND(UPPER(S55),"ABCD"))<>"","Why-not filled for the answer",IF(AND(B55<>"live",B55<>"draft",B55<>"retired"),"Status must be live/draft/retired","OK")))))))) -> OK
A56: OBL/DDP/153 | B56: live | C56: V | D56: 1 | E56: Register with one bank, keep custody at another | F56: Applicant | G56: Category I fund | H56: Wants | I56: Registration through DDP A, custody with Bank B | J56: Reason | K56: Bank B is cheaper | L56: Both banks | M56: Approved DDPs | N56: Can it split them? | O56: Yes. Any custodian bank will do | P56: No. They must be the same entity | Q56: Yes, with SEBI's prior approval | R56: Yes, because both are approved DDPs | S56: B | T56: Under Reg 24, the FPI's DDP and its custodian must be the same entity at all times. Before investing, the FPI or its global custodian signs a custody agreement with that DDP (Reg 25). | U56: Reg 24 requires one entity for both roles. | W56: Reg 24 has no approval route. | X56: Being approved DDPs doesn't let the roles be split between two of them. | Y56: SEBI (FPI) Regulations, 2019, Regulation 24 | Z56: 24. An applicant seeking registration as a foreign portfolio investor shall engage a designated depository participant to avail its services for obtaining a certificate of registration as foreign portfolio investor and at all times the designated depository participant and the custodian of the foreign portfolio investor shall be the same entity. | AC56: FPI Regs 2019, Reg 24–25 | AE56: Oct 2026 | AG56: =IF(A56="","",IF(COUNTA(O56:R56)<4,"Needs 4 options",IF(ISERROR(FIND(UPPER(S56),"ABCD"))+(LEN(S56)<>1),"Answer must be A-D",IF(OR(D56<1,D56>3),"Difficulty must be 1-3",IF(OR(N56="",T56=""),"Missing question or explanation",IF(COUNTBLANK(U56:X56)<>1,"Need 3 why-not texts",IF(INDEX(U56:X56,1,FIND(UPPER(S56),"ABCD"))<>"","Why-not filled for the answer",IF(AND(B56<>"live",B56<>"draft",B56<>"retired"),"Status must be live/draft/retired","OK")))))))) -> OK
A57: OBL/BNK/154 | B57: live | C57: V | D57: 1 | E57: Bank accounts before the first trade | F57: FPI | G57: Newly registered Category II fund | H57: Done | I57: Registration, custody agreement, PAN | J57: Not done | K57: Bank accounts | L57: Plan | M57: Buy shares tomorrow | N57: What's missing? | O57: Nothing. It can start trading tomorrow | P57: Foreign currency and SNRR bank accounts | Q57: A separate RBI licence to invest in Indian securities | R57: A second PAN registered for the bank | S57: B | T57: Under Reg 26, before investing, an FPI appoints a branch of an RBI-authorised bank to open a foreign currency account and a special non-resident rupee (SNRR) account. Reg 22(1)(f) separately requires a PAN. | U57: The bank accounts must exist before any investment. | W57: An FPI doesn't need a separate RBI licence. | X57: One PAN per FPI. The bank uses the same one. | Y57: SEBI (FPI) Regulations, 2019, Regulation 26 | Z57: 26. A foreign portfolio investor shall appoint a branch of a bank authorised by the Reserve Bank of India for opening a foreign currency denominated account and special non-resident rupee account before making any investments in India. | AC57: FPI Regs 2019, Reg 26, Reg 22(1)(f) | AE57: Oct 2026 | AG57: =IF(A57="","",IF(COUNTA(O57:R57)<4,"Needs 4 options",IF(ISERROR(FIND(UPPER(S57),"ABCD"))+(LEN(S57)<>1),"Answer must be A-D",IF(OR(D57<1,D57>3),"Difficulty must be 1-3",IF(OR(N57="",T57=""),"Missing question or explanation",IF(COUNTBLANK(U57:X57)<>1,"Need 3 why-not texts",IF(INDEX(U57:X57,1,FIND(UPPER(S57),"ABCD"))<>"","Why-not filled for the answer",IF(AND(B57<>"live",B57<>"draft",B57<>"retired"),"Status must be live/draft/retired","OK")))))))) -> OK
A58: OBL/MED/155 | B58: live | C58: V | D58: 2 | E58: Portfolio manager recommends a stock on TV | F58: FPI | G58: Category I fund | H58: Event | I58: Its portfolio manager recommends an Indian stock on a business channel | J58: Fund position | K58: Long in that stock | L58: Disclosed on air | M58: Nothing | N58: What went wrong? | O58: Nothing. FPIs may comment on stocks freely | P58: The fund's long position wasn't disclosed | Q58: FPI employees can't appear in the media | R58: Only the stock exchange needed to be told | S58: B | T58: Under Reg 28, an FPI or its employees can't give investment advice about a security in public media without disclosing their interest, including long or short positions, at the time. An employee also discloses the interests of dependent family members and of the employer. | U58: Advice is allowed, but only with disclosure. | W58: Appearing is allowed. The rule is about disclosing interests. | X58: The disclosure goes to the audience at the time of the advice. | Y58: SEBI (FPI) Regulations, 2019, Regulation 28(1) | Z58: 28. (1) A foreign portfolio investor, or any of its employees shall not render directly or indirectly any investment advice about any security in the publicly accessible media, whether real-time or otherwise, unless a disclosure of its interest including long or short position in the said security has been made, while rendering such advice. | AC58: FPI Regs 2019, Reg 28 | AE58: Oct 2026 | AG58: =IF(A58="","",IF(COUNTA(O58:R58)<4,"Needs 4 options",IF(ISERROR(FIND(UPPER(S58),"ABCD"))+(LEN(S58)<>1),"Answer must be A-D",IF(OR(D58<1,D58>3),"Difficulty must be 1-3",IF(OR(N58="",T58=""),"Missing question or explanation",IF(COUNTBLANK(U58:X58)<>1,"Need 3 why-not texts",IF(INDEX(U58:X58,1,FIND(UPPER(S58),"ABCD"))<>"","Why-not filled for the answer",IF(AND(B58<>"live",B58<>"draft",B58<>"retired"),"Status must be live/draft/retired","OK")))))))) -> OK
A59: OBL/REC/156 | B59: live | C59: V | D59: 2 | E59: Keeping records after surrender | F59: FPI | G59: Category II fund | H59: Event | I59: SEBI approved surrender on 1 August 2026 | J59: Records | K59: Contract notes, bank statements, remittance accounts | L59: Question | M59: When can they be destroyed? | N59: What's the minimum retention? | O59: One year after the surrender | P59: Five years from SEBI's approval | Q59: Eight years from the last trade | R59: They can go once surrender is approved | S59: B | T59: Reg 29 lists the records an FPI keeps: remittance accounts, bank statements, contract notes and communications with intermediaries. Reg 30 says to keep them for at least five years from the date SEBI approves the surrender or cancellation. DDPs, by contrast, keep their records at all times (Reg 32(3)). | U59: The minimum is five years, not one. | W59: The clock starts from SEBI's approval of surrender or cancellation, and the period is five years. | X59: Records must be kept for five years after surrender. | Y59: SEBI (FPI) Regulations, 2019, Regulation 30 | Z59: 30. Subject to the provisions of any other law, for the time being in force, every foreign portfolio investor shall preserve the books of accounts, records and documents specified in regulation 29 for a minimum period of five years from the date of approval of the surrender or cancellation of registration by the Board. | AC59: FPI Regs 2019, Reg 29–30, Reg 32(3) | AE59: Oct 2026 | AG59: =IF(A59="","",IF(COUNTA(O59:R59)<4,"Needs 4 options",IF(ISERROR(FIND(UPPER(S59),"ABCD"))+(LEN(S59)<>1),"Answer must be A-D",IF(OR(D59<1,D59>3),"Difficulty must be 1-3",IF(OR(N59="",T59=""),"Missing question or explanation",IF(COUNTBLANK(U59:X59)<>1,"Need 3 why-not texts",IF(INDEX(U59:X59,1,FIND(UPPER(S59),"ABCD"))<>"","Why-not filled for the answer",IF(AND(B59<>"live",B59<>"draft",B59<>"retired"),"Status must be live/draft/retired","OK")))))))) -> OK
A60: OBL/CO/157 | B60: live | C60: V | D60: 1 | E60: Individual FPI with no staff | F60: FPI | G60: Category II individual investor | H60: Staff | I60: None | J60: Question | K60: Do I need to appoint a compliance officer? | L60: DDP | M60: Asks for the officer's name | N60: What's the rule? | O60: Yes. A separate compliance officer is mandatory | P60: No. The individual is responsible | Q60: The DDP acts as its compliance officer | R60: Only Category I FPIs need one | S60: B | T60: Reg 27 requires every FPI to appoint a compliance officer, who reports any non-compliance straight to SEBI and the DDP. For an individual FPI, the individual carries that responsibility. | U60: The proviso to Reg 27(1) makes the individual responsible. | W60: The DDP has its own compliance officer under Reg 33. It doesn't act for the FPI. | X60: Reg 27 applies to every FPI. | Y60: SEBI (FPI) Regulations, 2019, Regulation 27 | Z60: 27. (1) Every foreign portfolio investor shall appoint a compliance officer who shall be responsible for monitoring the compliance of the Act, rules and regulations, notifications, guidelines and instructions issued by the designated depository participant or the Board or the Central Government: Provided that in case of a foreign portfolio investor who is an individual, such individual shall be responsible for monitoring the compliance of the Act, rules and regulations, notifications, guidelines and instructions issued by the designated depository participant or the Board or the Central Government. (2) The compliance officer shall immediately and independently report any non-compliance observed by him to the Board and the designated depository participant. | AC60: FPI Regs 2019, Reg 27 | AE60: Oct 2026 | AG60: =IF(A60="","",IF(COUNTA(O60:R60)<4,"Needs 4 options",IF(ISERROR(FIND(UPPER(S60),"ABCD"))+(LEN(S60)<>1),"Answer must be A-D",IF(OR(D60<1,D60>3),"Difficulty must be 1-3",IF(OR(N60="",T60=""),"Missing question or explanation",IF(COUNTBLANK(U60:X60)<>1,"Need 3 why-not texts",IF(INDEX(U60:X60,1,FIND(UPPER(S60),"ABCD"))<>"","Why-not filled for the answer",IF(AND(B60<>"live",B60<>"draft",B60<>"retired"),"Status must be live/draft/retired","OK")))))))) -> OK
A61: OBL/JNT/158 | B61: live | C61: V | D61: 2 | E61: Two holders, one account | F61: Applicants | G61: Two siblings, foreign nationals (not NRIs or OCIs) | H61: Want | I61: One joint FPI account | J61: Sibling A | K61: Meets FPI eligibility; KYC done | L61: Sibling B | M61: No KYC submitted | N61: What's needed? | O61: Only the first holder has to qualify | P61: Each holder must qualify and do KYC | Q61: Joint FPI accounts aren't allowed | R61: The second holder just signs a declaration | S61: B | T61: Under Reg 22(2), each joint holder must meet the FPI requirements and is treated as holding a depository account as an FPI. Reg 31(1)(f) requires the DDP to do KYC on each joint holder. | U61: Every joint holder must qualify. | W61: Joint accounts are allowed when each holder meets the requirements. | X61: A declaration doesn't replace KYC. | Y61: SEBI (FPI) Regulations, 2019, Regulation 22(2) | Z61: (2) In case of jointly held depository accounts, each of the joint holders shall meet the requirements specified for foreign portfolio investor and each shall be deemed to be holding a depository account as a foreign portfolio investor. | AC61: FPI Regs 2019, Reg 22(2), Reg 31(1)(f) | AE61: Oct 2026 | AG61: =IF(A61="","",IF(COUNTA(O61:R61)<4,"Needs 4 options",IF(ISERROR(FIND(UPPER(S61),"ABCD"))+(LEN(S61)<>1),"Answer must be A-D",IF(OR(D61<1,D61>3),"Difficulty must be 1-3",IF(OR(N61="",T61=""),"Missing question or explanation",IF(COUNTBLANK(U61:X61)<>1,"Need 3 why-not texts",IF(INDEX(U61:X61,1,FIND(UPPER(S61),"ABCD"))<>"","Why-not filled for the answer",IF(AND(B61<>"live",B61<>"draft",B61<>"retired"),"Status must be live/draft/retired","OK")))))))) -> OK
A62: DDO/RPT/161 | B62: live | C62: VI | D62: 2 | E62: RBI fines the DDP itself | F62: DDP | G62: A bank approved as a DDP | H62: Event | I62: RBI imposes a penalty on 12 May | J62: Question | K62: Who must be told, and by when? | L62: Licence | M62: Unaffected | N62: What's the duty? | O62: Tell SEBI only, in its next annual audit report | P62: SEBI, depositories and exchanges, in 2 working days | Q62: Tell RBI only, since RBI imposed the penalty | R62: Write to all its FPI clients within 30 days of the order | S62: B | T62: Under Reg 31(1)(g), a DDP reports any penalty, pending litigation, proceedings or adverse inspection findings by any regulator to SEBI, the depositories and the stock exchanges, as soon as possible and within two working days. Changes to its own information go to SEBI within two working days too. Compare FPIs, who get seven working days. | U62: The annual audit is too late, and the depositories and exchanges must be told as well. | W62: RBI already knows. The duty is to inform SEBI, the depositories and the exchanges. | X62: The regulation names SEBI, the depositories and the exchanges, not clients. | Y62: SEBI (FPI) Regulations, 2019, Regulation 31(1)(g) | Z62: (g) in case of any penalty, pending litigation or proceedings, findings of inspections or investigations for which action may have been taken or is in the process of being taken by any regulator against a designated depository participant, the designated depository participant shall bring such information as soon as possible but not later than two working days, to the attention of the Board, depositories and stock exchanges; | AC62: FPI Regs 2019, Reg 31(1)(b), (c), (g) | AE62: Oct 2026 | AG62: =IF(A62="","",IF(COUNTA(O62:R62)<4,"Needs 4 options",IF(ISERROR(FIND(UPPER(S62),"ABCD"))+(LEN(S62)<>1),"Answer must be A-D",IF(OR(D62<1,D62>3),"Difficulty must be 1-3",IF(OR(N62="",T62=""),"Missing question or explanation",IF(COUNTBLANK(U62:X62)<>1,"Need 3 why-not texts",IF(INDEX(U62:X62,1,FIND(UPPER(S62),"ABCD"))<>"","Why-not filled for the answer",IF(AND(B62<>"live",B62<>"draft",B62<>"retired"),"Status must be live/draft/retired","OK")))))))) -> OK
A63: DDO/ACC/162 | B63: live | C63: VI | D63: 2 | E63: A second NSDL account for a new strategy | F63: FPI | G63: Category I fund with an NSDL account through its DDP | H63: Request | I63: A second NSDL account for a new strategy | J63: Special scheme | K63: Not under the Voluntary Retention Route or any other scheme | L63: Manager | M63: Same as the existing account | N63: Can the DDP open it? | O63: Yes. FPIs can open as many accounts as they need | P63: No. One per depository, unless for VRR-type schemes | Q63: Yes, if it's opened through a different custodian | R63: Yes, once SEBI has been informed in writing beforehand | S63: B | T63: Under Reg 31(2)(c), the DDP checks before opening an account that the applicant holds no other FPI account at that depository. Separate accounts are allowed for the Voluntary Retention Route or other schemes RBI or SEBI specify. An FPI may hold an account at both NSDL and CDSL, but with only one custodian. | U63: The rule is one account per depository. | W63: The DDP and the custodian must be the same entity, and the one-account rule applies anyway. | X63: There's no notification route around Reg 31(2)(c). | Y63: SEBI (FPI) Regulations, 2019, Regulation 31(2)(c) | Z63: (c) carry out necessary due diligence to ensure that no other depository account per depository is held by any of the concerned applicant as a foreign portfolio investor, before opening a depository account Provided that a foreign portfolio investor can open separate depository accounts for holding securities under the Voluntary Retention Route or any other scheme as specified by the Reserve Bank of India or the Board; | AC63: FPI Regs 2019, Reg 31(2)(c); Op. Guidelines Part B 3 | AE63: Oct 2026 | AG63: =IF(A63="","",IF(COUNTA(O63:R63)<4,"Needs 4 options",IF(ISERROR(FIND(UPPER(S63),"ABCD"))+(LEN(S63)<>1),"Answer must be A-D",IF(OR(D63<1,D63>3),"Difficulty must be 1-3",IF(OR(N63="",T63=""),"Missing question or explanation",IF(COUNTBLANK(U63:X63)<>1,"Need 3 why-not texts",IF(INDEX(U63:X63,1,FIND(UPPER(S63),"ABCD"))<>"","Why-not filled for the answer",IF(AND(B63<>"live",B63<>"draft",B63<>"retired"),"Status must be live/draft/retired","OK")))))))) -> OK
A64: DDO/AUD/163 | B64: live | C64: VI | D64: 3 | E64: When the DDP's audit report is due | F64: DDP | G64: Custodian bank approved as a DDP | H64: Report | I64: Internal-control audit for calendar year 2026 | J64: Also due | K64: Action-taken report on the audit | L64: Question | M64: Deadlines | N64: What are the deadlines? | O64: Within 90 days after 2026 ends; action-taken reports quarterly | P64: By 31 December 2026, with the action-taken report filed once a year | Q64: Within 30 days after 2026 ends; no action-taken report needed | R64: Only when SEBI inspects | S64: A | T64: Under Reg 31(5)–(7), the DDP has an independent professional review its systems every year. It sends SEBI the internal-control audit report for a calendar year within 90 days after that year ends, so by about the end of March 2027 for 2026. Any action-taken report on the audit goes in every quarter. | V64: The report covers the full calendar year, so it can't be due before the year ends, and action-taken reports are quarterly. | W64: The window is 90 days, and action-taken reports are required. | X64: Annual reporting is mandatory, not triggered by inspections. | Y64: SEBI (FPI) Regulations, 2019, Regulation 31(6)–(7) | Z64: (6) The designated depository participant shall furnish to the Board annual audit reports on its internal control for a particular calendar year within ninety days of the next calendar year. (7) The designated depository participant shall submit the Action Taken Report, if any, on the audit report on a quarterly basis to the Board. | AC64: FPI Regs 2019, Reg 31(5)–(7) | AE64: Oct 2026 | AG64: =IF(A64="","",IF(COUNTA(O64:R64)<4,"Needs 4 options",IF(ISERROR(FIND(UPPER(S64),"ABCD"))+(LEN(S64)<>1),"Answer must be A-D",IF(OR(D64<1,D64>3),"Difficulty must be 1-3",IF(OR(N64="",T64=""),"Missing question or explanation",IF(COUNTBLANK(U64:X64)<>1,"Need 3 why-not texts",IF(INDEX(U64:X64,1,FIND(UPPER(S64),"ABCD"))<>"","Why-not filled for the answer",IF(AND(B64<>"live",B64<>"draft",B64<>"retired"),"Status must be live/draft/retired","OK")))))))) -> OK
A65: DDO/GRP/164 | B65: live | C65: VI | D65: 1 | E65: Investor-group box left blank | F65: Applicant | G65: New Category II fund | H65: Parent | I65: Owns 55% of two FPIs already registered | J65: Application | K65: Investor-group section left blank | L65: DDP | M65: Ready to approve | N65: What must the DDP do? | O65: Approve it. Investor groups are the depositories' job | P65: Check for an investor group before registering it | Q65: Ask the FPI to report its group within a year | R65: Nothing, unless the group crosses 10% somewhere | S65: B | T65: Under Reg 31(2)(a), the DDP must find out at registration, and whenever it becomes relevant, whether the applicant is part of an investor group. Common ownership above 50% puts this one in a group. The FPI must keep its investor-group details accurate with the DDP (Reg 22(1)(l)), and the custodian reports group holdings to the depositories (Reg 25(2)(d)). | U65: The depositories monitor the group limit using the details the DDP collects at onboarding. | W65: The group is checked at registration, not a year later. | X65: The 10% limit applies to the group from day one, so the group must be known before any purchase. | Y65: SEBI (FPI) Regulations, 2019, Regulation 31(2)(a) | Z65: (a) ascertain at the time of granting registration and whenever applicable, whether the applicant forms part of any investor group; | AC65: FPI Regs 2019, Reg 31(2)(a), Reg 22(1)(l), Reg 25(2)(d) | AE65: Oct 2026 | AG65: =IF(A65="","",IF(COUNTA(O65:R65)<4,"Needs 4 options",IF(ISERROR(FIND(UPPER(S65),"ABCD"))+(LEN(S65)<>1),"Answer must be A-D",IF(OR(D65<1,D65>3),"Difficulty must be 1-3",IF(OR(N65="",T65=""),"Missing question or explanation",IF(COUNTBLANK(U65:X65)<>1,"Need 3 why-not texts",IF(INDEX(U65:X65,1,FIND(UPPER(S65),"ABCD"))<>"","Why-not filled for the answer",IF(AND(B65<>"live",B65<>"draft",B65<>"retired"),"Status must be live/draft/retired","OK")))))))) -> OK
A66: FEE/REG/171 | B66: live | C66: FEE | D66: 1 | E66: First fee for a family office | F66: Applicant | G66: Category II family office | H66: Question | I66: What is SEBI's registration fee, and how often is it paid? | J66: Location | K66: Singapore | L66: Route | M66: Regular FPI | N66: What does it pay? | O66: US$250 for each three-year block | P66: US$2,500 for each three-year block | Q66: US$250 once, for life | R66: US$3,000 every three years | S66: A | T66: Under the Second Schedule Part A, Category I pays US$2,500 and Category II pays US$250, at application and for every three-year block while registered. These amounts replaced US$3,000 and US$300 in November 2022. | V66: US$2,500 is the Category I fee. | W66: The fee is due again for every three-year block. | X66: US$3,000 was the old Category I fee, before November 2022. | Y66: SEBI (FPI) Regulations, 2019, Second Schedule, Part A(1)–(2) | Z66: (1) Foreign portfolio investor belonging to Category I and II shall pay registration fees of US $2500 and US $250, respectively or any other amount specified by the Board from time to time at the time of submission of the Form to the designated depository participant. (2) Foreign portfolio investor belonging to Category I and II shall pay registration fees for every block of three years, till the validity of its registration, | AC66: FPI Regs 2019, Second Schedule Part A(1)–(2) | AE66: Oct 2026 | AG66: =IF(A66="","",IF(COUNTA(O66:R66)<4,"Needs 4 options",IF(ISERROR(FIND(UPPER(S66),"ABCD"))+(LEN(S66)<>1),"Answer must be A-D",IF(OR(D66<1,D66>3),"Difficulty must be 1-3",IF(OR(N66="",T66=""),"Missing question or explanation",IF(COUNTBLANK(U66:X66)<>1,"Need 3 why-not texts",IF(INDEX(U66:X66,1,FIND(UPPER(S66),"ABCD"))<>"","Why-not filled for the answer",IF(AND(B66<>"live",B66<>"draft",B66<>"retired"),"Status must be live/draft/retired","OK")))))))) -> OK
A67: FEE/EXM/172 | B67: live | C67: FEE | D67: 2 | E67: Multilateral development bank applies | F67: Applicant | G67: Multilateral development bank set up outside India to provide aid | H67: Status | I67: Granted privileges and immunities from Indian taxes and duties by the Central Government | J67: Category | K67: I | L67: Question | M67: Registration fee | N67: What does it pay? | O67: US$2,500, like any other Category I FPI | P67: Nothing. It's exempt | Q67: US$250, at a reduced rate for aid bodies | R67: The US$800 regulatory fee instead | S67: B | T67: The Second Schedule Part A(3) exempts international or multilateral agencies, such as the World Bank, from registration fees. They must be set up outside India to provide aid and have privileges and immunities granted by the Central Government. Separately, World Bank Group entities are exempt from combining holdings for the 10% limit. | U67: The Part A(3) exemption overrides the standard Category I fee. | W67: There's no reduced rate. It's a full exemption. | X67: US$800 is the regulatory fee on ODI subscribers. | Y67: SEBI (FPI) Regulations, 2019, Second Schedule, Part A(3) | Z67: (3) International or multilateral agency such as World Bank and other institutions, established outside India for providing aid, which have been granted privileges and immunities from payment of tax and duties by the Central Government shall be exempted from the payment of registration fees. | AC67: FPI Regs 2019, Second Schedule Part A(3); Op. Guidelines Part C 1 | AE67: Oct 2026 | AG67: =IF(A67="","",IF(COUNTA(O67:R67)<4,"Needs 4 options",IF(ISERROR(FIND(UPPER(S67),"ABCD"))+(LEN(S67)<>1),"Answer must be A-D",IF(OR(D67<1,D67>3),"Difficulty must be 1-3",IF(OR(N67="",T67=""),"Missing question or explanation",IF(COUNTBLANK(U67:X67)<>1,"Need 3 why-not texts",IF(INDEX(U67:X67,1,FIND(UPPER(S67),"ABCD"))<>"","Why-not filled for the answer",IF(AND(B67<>"live",B67<>"draft",B67<>"retired"),"Status must be live/draft/retired","OK")))))))) -> OK
A68: FEE/REM/173 | B68: live | C68: FEE | D68: 2 | E68: Passing collected fees on to SEBI | F68: DDP | G68: Collected FPI registration and continuance fees during September 2026 | H68: Question | I68: When must the money reach SEBI? | J68: Format | K68: SEBI's prescribed statement | L68: Fees collected | M68: Mix of Category I and II | N68: What's the deadline? | O68: By the 5th working day of October 2026 | P68: By 31 March 2027, with the annual return | Q68: Within 30 days of receiving each fee | R68: In a single batch at the end of the year | S68: A | T68: Under the Second Schedule Part A(5), every DDP sends SEBI the fees it collected in the previous month by the 5th working day of each month, with details in the prescribed format. DDPs collect continuance fees in advance, once every three years (Part A(4)). | V68: Fees go to SEBI monthly, not yearly. | W68: The rule is monthly, by the 5th working day, not 30 days per receipt. | X68: There's no yearly batch. Remittance is monthly. | Y68: SEBI (FPI) Regulations, 2019, Second Schedule, Part A(5) | Z68: (5) Every designated depository participant shall remit the fees collected from the foreign portfolio investors during the immediate preceding month, to the Board, by 5th working day of every month, along with the details in the format, as may be specified from time to time. | AC68: FPI Regs 2019, Second Schedule Part A(4)–(5); Reg 7(3) | AE68: Oct 2026 | AG68: =IF(A68="","",IF(COUNTA(O68:R68)<4,"Needs 4 options",IF(ISERROR(FIND(UPPER(S68),"ABCD"))+(LEN(S68)<>1),"Answer must be A-D",IF(OR(D68<1,D68>3),"Difficulty must be 1-3",IF(OR(N68="",T68=""),"Missing question or explanation",IF(COUNTBLANK(U68:X68)<>1,"Need 3 why-not texts",IF(INDEX(U68:X68,1,FIND(UPPER(S68),"ABCD"))<>"","Why-not filled for the answer",IF(AND(B68<>"live",B68<>"draft",B68<>"retired"),"Status must be live/draft/retired","OK")))))))) -> OK
A69: FEE/ODI/174 | B69: live | C69: FEE | D69: 3 | E69: Regulatory fee on ODI subscribers | F69: ODI issuer | G69: Category I FPI | H69: Subscribers | I69: 40 eligible subscribers | J69: Question | K69: What SEBI fee applies to each subscriber? | L69: Cycle | M69: Next deposit due | N69: What's the fee? | O69: US$800 per subscriber, once every three years | P69: US$1,000 per subscriber, every year | Q69: US$2,500 per subscriber, once | R69: No fee. Only the issuer pays its FPI fee | S69: A | T69: Under the Second Schedule Part C, the issuing FPI collects a US$800 regulatory fee from every ODI subscriber and deposits it with SEBI, once every three years (counting from 1 April 2017). | V69: US$1,000 was the old amount, replaced by US$800 in November 2022, and it's paid every three years, not yearly. | W69: US$2,500 is the Category I registration fee. | X69: Reg 21(4) requires the issuer to collect a fee from every subscriber. | Y69: SEBI (FPI) Regulations, 2019, Second Schedule, Part C | Z69: (1) A foreign portfolio investor shall collect the regulatory fee of US $ 800 or any other amount, as may be specified by the Board from time to time, from every subscriber of offshore derivative instrument issued by it and deposit the same with the Board by way of electronic transfer in the designated bank account of the Board. (2) The regulatory fee shall be deposited once every three years beginning April 1, 2017. | AC69: FPI Regs 2019, Reg 21(4); Second Schedule Part C | AE69: Oct 2026 | AG69: =IF(A69="","",IF(COUNTA(O69:R69)<4,"Needs 4 options",IF(ISERROR(FIND(UPPER(S69),"ABCD"))+(LEN(S69)<>1),"Answer must be A-D",IF(OR(D69<1,D69>3),"Difficulty must be 1-3",IF(OR(N69="",T69=""),"Missing question or explanation",IF(COUNTBLANK(U69:X69)<>1,"Need 3 why-not texts",IF(INDEX(U69:X69,1,FIND(UPPER(S69),"ABCD"))<>"","Why-not filled for the answer",IF(AND(B69<>"live",B69<>"draft",B69<>"retired"),"Status must be live/draft/retired","OK")))))))) -> OK
A70: ONB/ELG/201 | B70: live | C70: II | D70: 2 | E70: One province in, one province out | F70: Applicant | G70: Pension plan from a country with separate provincial securities regulators | H70: Its province | I70: Regulator has not signed the IOSCO MMoU and has no SEBI MoU | J70: Neighbouring province | K70: Regulator is an IOSCO MMoU signatory | L70: Requested | M70: Category I | N70: Does the country-level IOSCO status carry it through? | O70: Yes. The country has an IOSCO signatory, which is enough | P70: No. Its own province's regulator must qualify | Q70: Yes, if the neighbouring regulator gives a no-objection | R70: No. Federal countries are excluded from FPI registration | S70: B | T70: Where a country has separate securities regulators for different provinces or states, only applicants from provinces whose regulator signs the IOSCO MMoU, or has a bilateral MoU with SEBI, are eligible. | U70: The test runs at province level. One province's signature doesn't cover another. | W70: There is no no-objection route between regulators. | X70: Federal countries aren't excluded. Applicants from qualifying provinces can register. | Y70: SEBI Operational Guidelines for FPIs and DDPs, Part A 2(i) | Z70: With respect to the eligibility of FPI applicants from a country where there are separate securities market regulators for different provinces/ states within that country, applicants from only those provinces / states whose securities market regulator is a signatory to IOSCO MMOUs or has entered into a Bilateral Memorandum of Understanding with SEBI would be eligible for grant of registration as FPI. | AC70: Op. Guidelines Part A 2(i); FPI Regs 2019, Reg 4(d) | AE70: Oct 2026 | AG70: =IF(A70="","",IF(COUNTA(O70:R70)<4,"Needs 4 options",IF(ISERROR(FIND(UPPER(S70),"ABCD"))+(LEN(S70)<>1),"Answer must be A-D",IF(OR(D70<1,D70>3),"Difficulty must be 1-3",IF(OR(N70="",T70=""),"Missing question or explanation",IF(COUNTBLANK(U70:X70)<>1,"Need 3 why-not texts",IF(INDEX(U70:X70,1,FIND(UPPER(S70),"ABCD"))<>"","Why-not filled for the answer",IF(AND(B70<>"live",B70<>"draft",B70<>"retired"),"Status must be live/draft/retired","OK")))))))) -> OK
A71: ONB/ELG/202 | B71: live | C71: II | D71: 3 | E71: What 'from a FATF member country' means | F71: Applicant | G71: Credit fund incorporated in Luxembourg | H71: Primary place of business | I71: Singapore | J71: Regulated by | K71: Monetary Authority of Singapore | L71: Category test | M71: Needs to be 'from a FATF member country' | N71: How does the DDP apply the FATF-country test? | O71: By place of incorporation alone, nothing else | P71: By primary place of business and regulator | Q71: By the nationality of the largest investor | R71: By where the custodian bank is located | S71: B | T71: An entity 'from a FATF member country' means one whose primary place of business is in a FATF member country and, if regulated, is appropriately regulated in a FATF member country. Here both Singapore facts point the same way. | U71: Incorporation sets the country code, but the FATF test looks at the primary place of business and regulator. | W71: Investor nationality isn't part of this definition. | X71: The custodian's location is irrelevant to the applicant's FATF status. | Y71: SEBI Operational Guidelines for FPIs and DDPs, Part A 2(i) | Z71: Any reference in the Regulations and in these Operating Guidelines, an entity 'from a FATF member country' will mean that the entity has its primary place of business in a FATF member country and, if regulated, is appropriately regulated in a FATF member country. | AC71: Op. Guidelines Part A 2(i) | AE71: Oct 2026 | AG71: =IF(A71="","",IF(COUNTA(O71:R71)<4,"Needs 4 options",IF(ISERROR(FIND(UPPER(S71),"ABCD"))+(LEN(S71)<>1),"Answer must be A-D",IF(OR(D71<1,D71>3),"Difficulty must be 1-3",IF(OR(N71="",T71=""),"Missing question or explanation",IF(COUNTBLANK(U71:X71)<>1,"Need 3 why-not texts",IF(INDEX(U71:X71,1,FIND(UPPER(S71),"ABCD"))<>"","Why-not filled for the answer",IF(AND(B71<>"live",B71<>"draft",B71<>"retired"),"Status must be live/draft/retired","OK")))))))) -> OK
A72: ONB/REG/203 | B72: live | C72: II | D72: 2 | E72: Country code in the registration number | F72: Applicant | G72: Fund incorporated in Ireland | H72: Registered address | I72: Dublin | J72: Manager | K72: Based in London | L72: Question | M72: Which country code goes in its FPI registration number? | N72: Which country code is used? | O72: United Kingdom, where the manager is based | P72: Ireland, its registered address | Q72: India, since the registration is Indian | R72: Whichever the applicant prefers | S72: B | T72: The country code in the FPI registration number is the country of the applicant's registered or residence address, established from its incorporation or regulatory documents. | U72: The manager's location doesn't set the applicant's country code. | W72: The code identifies the FPI's own country, not India. | X72: It's fixed by the registered address, not by choice. | Y72: SEBI Operational Guidelines for FPIs and DDPs, Part A 2(i) | Z72: The country code in the FPI registration number shall be the country of its registered/residence address. | AC72: Op. Guidelines Part A 2(i) | AE72: Oct 2026 | AG72: =IF(A72="","",IF(COUNTA(O72:R72)<4,"Needs 4 options",IF(ISERROR(FIND(UPPER(S72),"ABCD"))+(LEN(S72)<>1),"Answer must be A-D",IF(OR(D72<1,D72>3),"Difficulty must be 1-3",IF(OR(N72="",T72=""),"Missing question or explanation",IF(COUNTBLANK(U72:X72)<>1,"Need 3 why-not texts",IF(INDEX(U72:X72,1,FIND(UPPER(S72),"ABCD"))<>"","Why-not filled for the answer",IF(AND(B72<>"live",B72<>"draft",B72<>"retired"),"Status must be live/draft/retired","OK")))))))) -> OK
A73: ONB/FIT/204 | B73: live | C73: II | D73: 2 | E73: Fined by its regulator two years ago | F73: Applicant | G73: Asset manager seeking Category I | H73: History | I73: Home regulator fined it in 2024 for a reporting lapse | J73: Licence | K73: Still valid; never cancelled | L73: DDP view | M73: Considering rejection on this ground | N73: Does the past fine make it ineligible? | O73: Yes. Any past regulatory action is disqualifying | P73: No, unless the registration was cancelled | Q73: Yes, unless SEBI grants a waiver | R73: Only if the fine was over US$1 million in total | S73: B | T73: Past action by an applicant's regulator doesn't necessarily make it ineligible, as long as the action didn't result in cancellation of its registration. The DDP still assesses fit and proper status. | U73: The guidelines say past action doesn't automatically disqualify an applicant. | W73: No SEBI waiver is needed here. | X73: There's no monetary threshold in the guidelines. | Y73: SEBI Operational Guidelines for FPIs and DDPs, Part A 2(vi) | Z73: Any past action taken by FPI applicant's regulator may not necessarily render such an applicant ineligible as long as such action did not result in cancellation of its registration. | AC73: Op. Guidelines Part A 2(vi); FPI Regs 2019, Reg 4(g) | AE73: Oct 2026 | AG73: =IF(A73="","",IF(COUNTA(O73:R73)<4,"Needs 4 options",IF(ISERROR(FIND(UPPER(S73),"ABCD"))+(LEN(S73)<>1),"Answer must be A-D",IF(OR(D73<1,D73>3),"Difficulty must be 1-3",IF(OR(N73="",T73=""),"Missing question or explanation",IF(COUNTBLANK(U73:X73)<>1,"Need 3 why-not texts",IF(INDEX(U73:X73,1,FIND(UPPER(S73),"ABCD"))<>"","Why-not filled for the answer",IF(AND(B73<>"live",B73<>"draft",B73<>"retired"),"Status must be live/draft/retired","OK")))))))) -> OK
A74: ONB/FIT/205 | B74: live | C74: II | D74: 3 | E74: Suspended in one of five countries | F74: Applicant | G74: Broker-dealer group active in five jurisdictions | H74: Event | I74: One foreign regulator suspended its local entity | J74: Effect | K74: No impact on the group's ability to trade elsewhere | L74: Requested | M74: Category I | N74: Can the DDP still consider it? | O74: No. A suspension anywhere is disqualifying | P74: Yes, if trading elsewhere is unaffected | Q74: Only once the suspension has been lifted everywhere | R74: Only with RBI's prior comments | S74: B | T74: If an applicant present in several jurisdictions is suspended by one regulator, and that doesn't affect the entity's or its affiliates' ability to trade elsewhere, the DDP can consider it eligible, subject to the other requirements. | U74: The guidelines expressly allow such applicants to be considered. | W74: There's no requirement to wait for the suspension to end. | X74: RBI comments apply to banks with an Indian presence, not to this case. | Y74: SEBI Operational Guidelines for FPIs and DDPs, Part A 2(vi) | Z74: Further, if an FPI applicant, which is present in multiple jurisdictions, is suspended by one of its foreign regulator and if this suspension does not affect the entity or any of its affiliates' ability to trade in any other country around the world, DDP can consider such an applicant eligible for grant of FPI registration subject to fulfillment of applicable eligibility requirements. | AC74: Op. Guidelines Part A 2(vi) | AE74: Oct 2026 | AG74: =IF(A74="","",IF(COUNTA(O74:R74)<4,"Needs 4 options",IF(ISERROR(FIND(UPPER(S74),"ABCD"))+(LEN(S74)<>1),"Answer must be A-D",IF(OR(D74<1,D74>3),"Difficulty must be 1-3",IF(OR(N74="",T74=""),"Missing question or explanation",IF(COUNTBLANK(U74:X74)<>1,"Need 3 why-not texts",IF(INDEX(U74:X74,1,FIND(UPPER(S74),"ABCD"))<>"","Why-not filled for the answer",IF(AND(B74<>"live",B74<>"draft",B74<>"retired"),"Status must be live/draft/retired","OK")))))))) -> OK
A75: ONB/REG/206 | B75: live | C75: II | D75: 1 | E75: Adding the manager's name | F75: Applicant | G75: Sub-fund of an umbrella fund | H75: Request | I75: Show the umbrella fund and manager names after its own | J75: Purpose | K75: Easier identification | L75: DDP | M75: Unsure if allowed | N75: Is the suffix allowed? | O75: No. The name must match its incorporation documents | P75: Yes. A manager or umbrella suffix is allowed | Q75: Only with SEBI's approval | R75: Only for Category II applicants | S75: B | T75: An applicant may add the name of its investment manager, umbrella fund or trustee as a suffix to its name. | U75: The guidelines specifically allow this suffix. | W75: No SEBI approval is needed. | X75: The option isn't limited to Category II. | Y75: SEBI Operational Guidelines for FPIs and DDPs, Part A 2(viii) | Z75: The applicant may also add the name of its investment manager/ umbrella fund/trustee, etc. as a suffix to its name. | AC75: Op. Guidelines Part A 2(viii) | AE75: Oct 2026 | AG75: =IF(A75="","",IF(COUNTA(O75:R75)<4,"Needs 4 options",IF(ISERROR(FIND(UPPER(S75),"ABCD"))+(LEN(S75)<>1),"Answer must be A-D",IF(OR(D75<1,D75>3),"Difficulty must be 1-3",IF(OR(N75="",T75=""),"Missing question or explanation",IF(COUNTBLANK(U75:X75)<>1,"Need 3 why-not texts",IF(INDEX(U75:X75,1,FIND(UPPER(S75),"ABCD"))<>"","Why-not filled for the answer",IF(AND(B75<>"live",B75<>"draft",B75<>"retired"),"Status must be live/draft/retired","OK")))))))) -> OK
A76: ONB/BNK/207 | B76: live | C76: II | D76: 2 | E76: Bank supervised by a unified regulator | F76: Applicant | G76: Commercial bank | H76: Home supervision | I76: A single unified financial-sector regulator, not a separate banking regulator | J76: Central bank | K76: BIS member | L76: Requested | M76: Category I as a regulated bank | N76: Is it 'appropriately regulated'? | O76: No. It needs a dedicated banking regulator at home | P76: Yes. A unified regulator counts | Q76: Only if the securities regulator also licenses it | R76: Only after RBI confirms | S76: B | T76: A bank applicant (other than a central bank) is deemed appropriately regulated if it's regulated by the unified financial-sector regulator or by a banking regulator in its home jurisdiction. | U76: A unified regulator is expressly accepted. | W76: No separate securities licence is needed for this test. | X76: RBI comments arise only for banks with an Indian presence. | Y76: SEBI Operational Guidelines for FPIs and DDPs, Part A 3(i) | Z76: An FPI applicant under bank category (other than a central bank) would be deemed to be appropriately regulated if it is regulated by the unified financial sector regulator in its home jurisdiction or by a banking sector regulator in its home jurisdiction. | AC76: Op. Guidelines Part A 3(i); FPI Regs 2019, Reg 2(1)(b) | AE76: Oct 2026 | AG76: =IF(A76="","",IF(COUNTA(O76:R76)<4,"Needs 4 options",IF(ISERROR(FIND(UPPER(S76),"ABCD"))+(LEN(S76)<>1),"Answer must be A-D",IF(OR(D76<1,D76>3),"Difficulty must be 1-3",IF(OR(N76="",T76=""),"Missing question or explanation",IF(COUNTBLANK(U76:X76)<>1,"Need 3 why-not texts",IF(INDEX(U76:X76,1,FIND(UPPER(S76),"ABCD"))<>"","Why-not filled for the answer",IF(AND(B76<>"live",B76<>"draft",B76<>"retired"),"Status must be live/draft/retired","OK")))))))) -> OK
A77: ONB/CAT/208 | B77: live | C77: II | D77: 3 | E77: University endowment, university only three years old | F77: Applicant | G77: Endowment of a private university in Australia (FATF member) | H77: University founded | I77: 2023 | J77: Regulated | K77: No | L77: Requested | M77: Category I | N77: Which category fits? | O77: Category I, as a university fund | P77: Category II, as an endowment | Q77: Not eligible until the university is five years old | R77: Category I, with the trustee's written undertaking | S77: B | T77: Category I covers university-related endowments from FATF countries only where the university has existed for more than five years. Otherwise the endowment falls under Category II, which lists endowments and foundations. | U77: The Category I route needs the university to be over five years old. | W77: It isn't ineligible; it qualifies for Category II. | X77: No undertaking substitutes for the five-year condition. | Y77: SEBI (FPI) Regulations, 2019, Regulation 5(a)(iv)(III) | Z77: university related endowments of such universities that have been in existence for more than five years; | AA77: SEBI (FPI) Regulations, 2019, Regulation 5(b)(ii) | AB77: (ii) endowments and foundations; | AC77: FPI Regs 2019, Reg 5(a)(iv)(III), Reg 5(b)(ii) | AE77: Oct 2026 | AG77: =IF(A77="","",IF(COUNTA(O77:R77)<4,"Needs 4 options",IF(ISERROR(FIND(UPPER(S77),"ABCD"))+(LEN(S77)<>1),"Answer must be A-D",IF(OR(D77<1,D77>3),"Difficulty must be 1-3",IF(OR(N77="",T77=""),"Missing question or explanation",IF(COUNTBLANK(U77:X77)<>1,"Need 3 why-not texts",IF(INDEX(U77:X77,1,FIND(UPPER(S77),"ABCD"))<>"","Why-not filled for the answer",IF(AND(B77<>"live",B77<>"draft",B77<>"retired"),"Status must be live/draft/retired","OK")))))))) -> OK
A78: ONB/CAT/209 | B78: live | C78: II | D78: 2 | E78: Unregulated subsidiary of a regulated bank | F78: Applicant | G78: Unregulated investment vehicle | H78: Owner | I78: 80% owned by a regulated German bank | J78: Parent's status | K78: Eligible as Category I; from a FATF country | L78: Undertaking | M78: Parent accepts responsibility for the vehicle | N78: Which category? | O78: Category II, because the vehicle itself is unregulated | P78: Category I, through its 80% owner | Q78: Category I only if the vehicle gets its own licence | R78: Not eligible | S78: B | T78: Reg 5(a)(v)(B) puts in Category I an entity at least 75% owned, directly or indirectly, by an entity eligible under Reg 5(a)(ii)–(iv) from a FATF member country, provided that owner takes responsibility for its acts and omissions. | U78: Ownership by an eligible regulated parent lifts it into Category I. | W78: Its own licence isn't needed on this route. | X78: It's eligible, and in Category I. | Y78: SEBI (FPI) Regulations, 2019, Regulation 5(a)(v) | Z78: (v) An entity (A) whose investment manager is from the Financial Action Task Force member country and such an investment manager is registered as a Category I foreign portfolio investor; or (B) which is at least seventy-five per cent owned, directly or indirectly by another entity, eligible under sub-clause (ii), (iii) and (iv) of clause (a) of this regulation and such an eligible entity is from a Financial Action Task Force member country: Provided that such an investment manager or eligible entity undertakes the responsibility of all the acts of commission or omission of the applicants seeking registration under this sub-clause. | AC78: FPI Regs 2019, Reg 5(a)(v)(B) and proviso | AE78: Oct 2026 | AG78: =IF(A78="","",IF(COUNTA(O78:R78)<4,"Needs 4 options",IF(ISERROR(FIND(UPPER(S78),"ABCD"))+(LEN(S78)<>1),"Answer must be A-D",IF(OR(D78<1,D78>3),"Difficulty must be 1-3",IF(OR(N78="",T78=""),"Missing question or explanation",IF(COUNTBLANK(U78:X78)<>1,"Need 3 why-not texts",IF(INDEX(U78:X78,1,FIND(UPPER(S78),"ABCD"))<>"","Why-not filled for the answer",IF(AND(B78<>"live",B78<>"draft",B78<>"retired"),"Status must be live/draft/retired","OK")))))))) -> OK
A79: ONB/MIM/210 | B79: live | C79: II | D79: 2 | E79: Three managers, three registrations | F79: Applicant | G79: Sovereign pension fund | H79: Structure | I79: Mandates with three external investment managers | J79: Request | K79: Separate FPI registrations, each through a different DDP | L79: PAN | M79: One PAN | N79: Is this allowed? | O79: No. One entity, one registration, one DDP | P79: Yes, with limits clubbed across them | Q79: Yes, and each registration gets its own 10% limit | R79: Only if each manager gets its own PAN | S79: B | T79: An entity with multiple external investment managers can obtain multiple FPI registrations, naming the manager in each. It may use different DDPs. All registrations share one PAN, and investments are clubbed for investment limits. | U79: Multiple-manager structures are expressly allowed. | W79: Investments under these registrations are clubbed for limits. | X79: They share the same PAN. | Y79: SEBI Operational Guidelines for FPIs and DDPs, Part A 4(i) | Z79: Where an entity engages multiple investment managers (MIM) for managing its investments, the entity can obtain multiple FPI registrations mentioning name of Investment Manager for each such registration. There should be external investment managers in case of MIM structures and such applicants can appoint different DDPs for each such registration. Investments made under such multiple registrations shall be clubbed for the purposes of monitoring of investment limits. | AC79: Op. Guidelines Part A 4 | AE79: Oct 2026 | AG79: =IF(A79="","",IF(COUNTA(O79:R79)<4,"Needs 4 options",IF(ISERROR(FIND(UPPER(S79),"ABCD"))+(LEN(S79)<>1),"Answer must be A-D",IF(OR(D79<1,D79>3),"Difficulty must be 1-3",IF(OR(N79="",T79=""),"Missing question or explanation",IF(COUNTBLANK(U79:X79)<>1,"Need 3 why-not texts",IF(INDEX(U79:X79,1,FIND(UPPER(S79),"ABCD"))<>"","Why-not filled for the answer",IF(AND(B79<>"live",B79<>"draft",B79<>"retired"),"Status must be live/draft/retired","OK")))))))) -> OK
A80: ONB/MIM/211 | B80: live | C80: II | D80: 3 | E80: Two in-house teams want separate registrations | F80: Applicant | G80: Insurance company | H80: Request | I80: Separate FPI registrations for its equity team and bond team | J80: Managers | K80: Both teams are internal staff | L80: Reason | M80: Cleaner reporting | N80: Does the multiple-manager route apply? | O80: Yes. Any two teams can register separately | P80: No. It needs external managers | Q80: Yes, if the two teams sit in different countries | R80: Yes, with a separate PAN for each team | S80: B | T80: Multiple-manager structures need external investment managers. Internal teams of the same entity don't qualify for separate registrations on this basis. | U80: The route is for external managers, not internal teams. | W80: Location doesn't change the external-manager requirement. | X80: Multiple-manager registrations share one PAN, and the route still needs external managers. | Y80: SEBI Operational Guidelines for FPIs and DDPs, Part A 4(i) | Z80: Where an entity engages multiple investment managers (MIM) for managing its investments, the entity can obtain multiple FPI registrations mentioning name of Investment Manager for each such registration. There should be external investment managers in case of MIM structures and such applicants can appoint different DDPs for each such registration. Investments made under such multiple registrations shall be clubbed for the purposes of monitoring of investment limits. | AC80: Op. Guidelines Part A 4(i) | AE80: Oct 2026 | AG80: =IF(A80="","",IF(COUNTA(O80:R80)<4,"Needs 4 options",IF(ISERROR(FIND(UPPER(S80),"ABCD"))+(LEN(S80)<>1),"Answer must be A-D",IF(OR(D80<1,D80>3),"Difficulty must be 1-3",IF(OR(N80="",T80=""),"Missing question or explanation",IF(COUNTBLANK(U80:X80)<>1,"Need 3 why-not texts",IF(INDEX(U80:X80,1,FIND(UPPER(S80),"ABCD"))<>"","Why-not filled for the answer",IF(AND(B80<>"live",B80<>"draft",B80<>"retired"),"Status must be live/draft/retired","OK")))))))) -> OK
A81: ONB/NAM/212 | B81: live | C81: II | D81: 2 | E81: FPI changes its name | F81: FPI | G81: Category I fund | H81: Event | I81: Renamed after a rebrand | J81: Evidence | K81: Updated entry on its home regulator's website | L81: Ownership, category, structure | M81: Unchanged | N81: What does the DDP need, and what follows? | O81: A fresh registration application | P81: Proof of the change and an undertaking | Q81: Nothing. Name changes don't need reporting | R81: SEBI's prior approval of the new name before use | S81: B | T81: The FPI submits proof (regulator's website, certified regulator or registrar documents, or a board resolution) and an undertaking that it's a mere name change with no change in beneficial ownership, category or structure. The DDP issues a letter and fresh certificate. The FPI also updates its PAN records. | U81: A name change doesn't need a new registration. | W81: Name changes must be reported with supporting evidence. | X81: The DDP processes it; no SEBI approval is needed. | Y81: SEBI Operational Guidelines for FPIs and DDPs, Part A 10 | Z81: In case the FPI has undergone a change in name, the request for updation/ incorporation of new name should be submitted by the FPI to the DDP accompanied by documents certifying the name change. Such name change can be evidenced by:    Information available on the website of the home regulator; or Certified copy of document(s) from home regulator; or Certified copy of document(s) from Registrar of Company (or equivalent authority) (wherever applicable) issued; or  Where above is not applicable, a Board Resolution or equivalent authorizing the name change An undertaking by the FPI shall be given stating that it is a mere name change and does not involve change in beneficial ownership, category or structure. | AC81: Op. Guidelines Part A 10 | AE81: Oct 2026 | AG81: =IF(A81="","",IF(COUNTA(O81:R81)<4,"Needs 4 options",IF(ISERROR(FIND(UPPER(S81),"ABCD"))+(LEN(S81)<>1),"Answer must be A-D",IF(OR(D81<1,D81>3),"Difficulty must be 1-3",IF(OR(N81="",T81=""),"Missing question or explanation",IF(COUNTBLANK(U81:X81)<>1,"Need 3 why-not texts",IF(INDEX(U81:X81,1,FIND(UPPER(S81),"ABCD"))<>"","Why-not filled for the answer",IF(AND(B81<>"live",B81<>"draft",B81<>"retired"),"Status must be live/draft/retired","OK")))))))) -> OK
A82: ONB/NAM/213 | B82: live | C82: II | D82: 2 | E82: Name change reported nine months late | F82: FPI | G82: Category II fund | H82: Renamed | I82: January 2026 | J82: Told DDP | K82: October 2026 | L82: Ownership | M82: Unchanged | N82: What extra step applies because of the delay? | O82: None, as long as ownership is unchanged | P82: The DDP reports the delay, with reasons | Q82: The FPI pays a late fee to SEBI | R82: The registration is suspended for six months | S82: B | T82: Where an FPI delays reporting a name change beyond six months, the DDP must provide details of all such instances with reasons. | U82: The guidelines specifically call out delays beyond six months. | W82: There's no late fee in the guidelines. | X82: There's no suspension; the delay is reported. | Y82: SEBI Operational Guidelines for FPIs and DDPs, Part A 10(ii) | Z82: Where FPIs has delayed in submitting details of name change beyond 6 months, DDP shall provide details of all such instances with reasons. | AC82: Op. Guidelines Part A 10(ii) | AE82: Oct 2026 | AG82: =IF(A82="","",IF(COUNTA(O82:R82)<4,"Needs 4 options",IF(ISERROR(FIND(UPPER(S82),"ABCD"))+(LEN(S82)<>1),"Answer must be A-D",IF(OR(D82<1,D82>3),"Difficulty must be 1-3",IF(OR(N82="",T82=""),"Missing question or explanation",IF(COUNTBLANK(U82:X82)<>1,"Need 3 why-not texts",IF(INDEX(U82:X82,1,FIND(UPPER(S82),"ABCD"))<>"","Why-not filled for the answer",IF(AND(B82<>"live",B82<>"draft",B82<>"retired"),"Status must be live/draft/retired","OK")))))))) -> OK
A83: ONB/CUS/214 | B83: live | C83: II | D83: 1 | E83: How long to move to the new custodian | F83: FPI | G83: Category I fund | H83: Event | I83: New DDP approved its change of custodian on 1 March | J83: Status | K83: Assets still with the old custodian on 20 March | L83: Question | M83: Deadline | N83: What's the transfer deadline? | O83: 7 working days from the approval | P83: 30 days, plus one 30-day extension | Q83: 90 days from the approval | R83: No deadline applies to transfers | S83: B | T83: Once the change of DDP or custodian is approved, the FPI transfers accounts and assets within 30 days. If that isn't done, it gives reasons and may seek a further 30 days. Both DDPs then confirm completion to SEBI. | U83: 7 working days is the material-change reporting deadline, not the transfer window. | W83: The window is 30 days, plus one 30-day extension. | X83: The guidelines set a 30-day window. | Y83: SEBI Operational Guidelines for FPIs and DDPs, Part A 12(iii) | Z83: Once the change of DDP/Custodian is approved by DDP, the FPI will need to transfer accounts and assets to the new DDP/Custodian within a period of 30 days. In case the transition does not take place within the stipulated time, the FPI shall provide reasons for the same and seek extension from DDP for a further period of 30 days. | AC83: Op. Guidelines Part A 12(iii) | AE83: Oct 2026 | AG83: =IF(A83="","",IF(COUNTA(O83:R83)<4,"Needs 4 options",IF(ISERROR(FIND(UPPER(S83),"ABCD"))+(LEN(S83)<>1),"Answer must be A-D",IF(OR(D83<1,D83>3),"Difficulty must be 1-3",IF(OR(N83="",T83=""),"Missing question or explanation",IF(COUNTBLANK(U83:X83)<>1,"Need 3 why-not texts",IF(INDEX(U83:X83,1,FIND(UPPER(S83),"ABCD"))<>"","Why-not filled for the answer",IF(AND(B83<>"live",B83<>"draft",B83<>"retired"),"Status must be live/draft/retired","OK")))))))) -> OK
A84: ONB/CUS/215 | B84: live | C84: II | D84: 3 | E84: New DDP relying on the old one's checks | F84: FPI | G84: Moving from DDP A to DDP B | H84: DDP B asks | I84: Must we redo all due diligence now? | J84: Next continuance | K84: Eighteen months away | L84: KYC | M84: Complete at DDP A | N84: What does DDP B have to do? | O84: Redo full due diligence before accepting the transfer | P84: Rely on DDP A now; redo checks at continuance | Q84: Nothing, ever. DDP A's checks carry over permanently | R84: Ask SEBI to approve the reliance | S84: B | T84: On a change of DDP, the new DDP may rely on the due diligence carried out by the old DDP. It must carry out adequate due diligence itself when the FPI applies for continuance. | U84: Full re-diligence isn't required at transfer. | W84: Reliance lasts only until continuance. | X84: No SEBI approval is needed for this reliance. | Y84: SEBI Operational Guidelines for FPIs and DDPs, Part A 12(iv) | Z84: With respect to the process of change of local custodian/DDP by an FPI, the new DDP (i.e. transferee) may rely on the due diligence carried out by the old DDP. However, the new DDP is required to carry out adequate due diligence at the time when the FPI applies for continuance of its registration. | AC84: Op. Guidelines Part A 12(iv) | AE84: Oct 2026 | AG84: =IF(A84="","",IF(COUNTA(O84:R84)<4,"Needs 4 options",IF(ISERROR(FIND(UPPER(S84),"ABCD"))+(LEN(S84)<>1),"Answer must be A-D",IF(OR(D84<1,D84>3),"Difficulty must be 1-3",IF(OR(N84="",T84=""),"Missing question or explanation",IF(COUNTBLANK(U84:X84)<>1,"Need 3 why-not texts",IF(INDEX(U84:X84,1,FIND(UPPER(S84),"ABCD"))<>"","Why-not filled for the answer",IF(AND(B84<>"live",B84<>"draft",B84<>"retired"),"Status must be live/draft/retired","OK")))))))) -> OK
A85: ONB/CUS/216 | B85: live | C85: II | D85: 2 | E85: Global custodian moves its clients | F85: Requester | G85: Global custodian acting for 40 underlying FPIs | H85: Request | I85: Move all 40 to a new local custodian | J85: Authorisation | K85: Explicit authority from each client | L85: Question | M85: Who must the new custodian inform? | N85: What applies? | O85: The FPIs must each apply themselves | P85: Allowed; it tells each FPI's compliance officer | Q85: Allowed only with SEBI's prior approval | R85: Not allowed for more than 10 FPIs in one request | S85: B | T85: A global custodian can request the change on behalf of its underlying FPIs if explicitly authorised by them. The transferee custodian then informs the compliance officer of each FPI about the change. | U85: An authorised global custodian can request it for them. | W85: No SEBI approval is needed for the request. | X85: There's no cap on the number of FPIs. | Y85: SEBI Operational Guidelines for FPIs and DDPs, Part A 12(i) | Z85: In case, an FPI or its Global Custodian wishes to change the local custodian/DDP, the request for change shall be forwarded to new local custodian/DDP. In case, the Global Custodian of FPI wishes to change the local custodian/DDP, then the request for change can be sent by the Global Custodian on behalf of its underlying FPI clients provided such Global Custodian has been explicitly authorized to take such steps by the client. | AA85: SEBI Operational Guidelines for FPIs and DDPs, Part A 12(ii) | AB85: In case, the request for change in local custodian/DDP is received from Global Custodian, the transferee local custodian/DDP shall inform Compliance Officer of the concerned FPI(s) regarding the change in their local custodian/DDP. | AC85: Op. Guidelines Part A 12(i)–(ii) | AE85: Oct 2026 | AG85: =IF(A85="","",IF(COUNTA(O85:R85)<4,"Needs 4 options",IF(ISERROR(FIND(UPPER(S85),"ABCD"))+(LEN(S85)<>1),"Answer must be A-D",IF(OR(D85<1,D85>3),"Difficulty must be 1-3",IF(OR(N85="",T85=""),"Missing question or explanation",IF(COUNTBLANK(U85:X85)<>1,"Need 3 why-not texts",IF(INDEX(U85:X85,1,FIND(UPPER(S85),"ABCD"))<>"","Why-not filled for the answer",IF(AND(B85<>"live",B85<>"draft",B85<>"retired"),"Status must be live/draft/retired","OK")))))))) -> OK
A86: ONB/AML/217 | B86: live | C86: II | D86: 1 | E86: Applicant from a FATF call-for-action country | F86: Applicant | G86: Investment company | H86: Residence | I86: Country listed by FATF as subject to counter-measures | J86: Documents | K86: Complete | L86: Requested | M86: Category II | N86: Can it be registered? | O86: Yes, as Category II with enhanced KYC checks | P86: No. It's ineligible under Reg 4(f) | Q86: Yes, if its investors are from other countries | R86: Yes, with SEBI's approval | S86: B | T86: Reg 4(f) bars applicants resident in a country identified by FATF as having strategic AML/CFT deficiencies to which counter-measures apply, or that hasn't made sufficient progress on its action plan. | U86: Enhanced KYC doesn't cure Reg 4(f) ineligibility. | W86: The test looks at the applicant's own residence too. | X86: Reg 4(f) has no SEBI approval route. | Y86: SEBI (FPI) Regulations, 2019, Regulation 4(f) | Z86: (f) the applicant or its underlying investors contributing more than the threshold prescribed under sub-rule (3) of rule 9 of the Prevention of Money-laundering (Maintenance of Records) Rules, 2005 in the corpus of the applicant or identified on the basis of control, shall not be the person(s) mentioned in the Sanctions List notified from time to time by the United Nations Security Council and is not a resident in the country identified in the public statement of Financial Action Task Force as – (i) a jurisdiction having a strategic Anti-Money Laundering or Combating the Financing of Terrorism deficiencies to which counter measures apply; or (ii) a jurisdiction that has not made sufficient progress in addressing the deficiencies or has not committed to an action plan developed with the Financial Action Task Force to address the deficiencies; | AC86: FPI Regs 2019, Reg 4(f) | AE86: Oct 2026 | AG86: =IF(A86="","",IF(COUNTA(O86:R86)<4,"Needs 4 options",IF(ISERROR(FIND(UPPER(S86),"ABCD"))+(LEN(S86)<>1),"Answer must be A-D",IF(OR(D86<1,D86>3),"Difficulty must be 1-3",IF(OR(N86="",T86=""),"Missing question or explanation",IF(COUNTBLANK(U86:X86)<>1,"Need 3 why-not texts",IF(INDEX(U86:X86,1,FIND(UPPER(S86),"ABCD"))<>"","Why-not filled for the answer",IF(AND(B86<>"live",B86<>"draft",B86<>"retired"),"Status must be live/draft/retired","OK")))))))) -> OK
A87: ONB/REN/218 | B87: live | C87: II | D87: 2 | E87: Fee paid, KYC review unfinished | F87: FPI | G87: Category II fund | H87: Fee | I87: Paid before the validity date | J87: KYC review | K87: Incomplete at the validity date, because the FPI didn't send documents | L87: Request | M87: Keep buying | N87: What's the position until the DDP confirms continuance? | O87: Business as usual, since the fee is paid | P87: No purchases until continuance is confirmed | Q87: The registration lapses | R87: Only debt purchases until the review is done | S87: B | T87: If the DDP receives fees before the validity date but due diligence, including KYC review, isn't complete because the FPI hasn't sent information, no further purchases are allowed until the DDP intimates continuance. | U87: Paying the fee alone doesn't unlock purchases here. | W87: It doesn't lapse, because the fee was paid in time. | X87: The block covers all purchases. | Y87: SEBI Operational Guidelines for FPIs and DDPs, Part A 5(iv) | Z87: If DDP is in receipt of registration fees prior to validity date but the due-diligence including KYC review is not complete by the validity date due to non-submission of information by the FPI, no further purchases may be permitted till the intimation of continuance is given by DDP. | AC87: Op. Guidelines Part A 5(iv) | AE87: Oct 2026 | AG87: =IF(A87="","",IF(COUNTA(O87:R87)<4,"Needs 4 options",IF(ISERROR(FIND(UPPER(S87),"ABCD"))+(LEN(S87)<>1),"Answer must be A-D",IF(OR(D87<1,D87>3),"Difficulty must be 1-3",IF(OR(N87="",T87=""),"Missing question or explanation",IF(COUNTBLANK(U87:X87)<>1,"Need 3 why-not texts",IF(INDEX(U87:X87,1,FIND(UPPER(S87),"ABCD"))<>"","Why-not filled for the answer",IF(AND(B87<>"live",B87<>"draft",B87<>"retired"),"Status must be live/draft/retired","OK")))))))) -> OK
A88: KYC/UBO/221 | B88: live | C88: II | D88: 1 | E88: Beneficial owners of a central bank | F88: Applicant | G88: A foreign central bank | H88: Category | I88: I, under Reg 5(a)(i) | J88: DDP asks | K88: Please list your ultimate beneficial owners | L88: Applicant's reply | M88: Not applicable | N88: Is the applicant right? | O88: No. Every FPI must list UBOs | P88: Yes. Reg 5(a)(i) FPIs are exempt | Q88: Only if it also gives a board resolution confirming it | R88: Only for its first registration | S88: B | T88: UBO details aren't required for government and government-related entities. Category I FPIs registered under Reg 5(a)(i) are exempt from providing BO details. | U88: Government-related Category I FPIs are expressly exempt. | W88: The exemption doesn't depend on a board resolution. | X88: It isn't limited to first registration. | Y88: SEBI Operational Guidelines for FPIs and DDPs, Part B 1, Table 4 note 3 | Z88: UBO is not required for Government and Government related entities. | AA88: SEBI Operational Guidelines for FPIs and DDPs, Part B 4(ii) | AB88: Category I FPI registered under Regulation 5(a)(i) are exempt from providing BO details. | AC88: Op. Guidelines Part B 1 (Table 4 note 3), Part B 4(ii) | AE88: Oct 2026 | AG88: =IF(A88="","",IF(COUNTA(O88:R88)<4,"Needs 4 options",IF(ISERROR(FIND(UPPER(S88),"ABCD"))+(LEN(S88)<>1),"Answer must be A-D",IF(OR(D88<1,D88>3),"Difficulty must be 1-3",IF(OR(N88="",T88=""),"Missing question or explanation",IF(COUNTBLANK(U88:X88)<>1,"Need 3 why-not texts",IF(INDEX(U88:X88,1,FIND(UPPER(S88),"ABCD"))<>"","Why-not filled for the answer",IF(AND(B88<>"live",B88<>"draft",B88<>"retired"),"Status must be live/draft/retired","OK")))))))) -> OK
A89: KYC/RSK/222 | B89: live | C89: II | D89: 3 | E89: Category I fund from a high-risk jurisdiction | F89: Applicant | G89: Regulated mutual fund, Category I | H89: Jurisdiction | I89: Rated high risk by the custodian | J89: Government-related | K89: No | L89: KYC pack offered | M89: The standard Category I set | N89: What KYC applies? | O89: The standard Category I set is enough for this fund | P89: Category II-level documents | Q89: No KYC; Category I is exempt | R89: It must re-register as Category II | S89: B | T89: For Category I FPIs from high-risk jurisdictions (other than Reg 5(a)(i) entities), Category II-level KYC documentation applies, and intermediaries may apply a lower 10% materiality threshold to identify beneficial owners. | U89: High-risk jurisdiction triggers heavier documentation. | W89: Only Reg 5(a)(i) entities get BO exemptions, and KYC still applies. | X89: Its category doesn't change; its documentation does. | Y89: SEBI Operational Guidelines for FPIs and DDPs, Part B 1, note (ii) | Z89: For FPI Category - I coming from high-risk jurisdiction (other than those registered under Regulation 5(a)(i)), the KYC documentation equivalent to FPI Category II shall apply. | AA89: SEBI Operational Guidelines for FPIs and DDPs, Part B 4(iv) | AB89: In respect of FPIs (other than Category I FPI registered under Regulation 5(a)(i)) coming from “high risk jurisdictions” as identified by intermediary, the intermediaries may apply lower materiality threshold of 10% for identification of BO. | AC89: Op. Guidelines Part B 1 (note ii), Part B 4(iv) | AE89: Oct 2026 | AG89: =IF(A89="","",IF(COUNTA(O89:R89)<4,"Needs 4 options",IF(ISERROR(FIND(UPPER(S89),"ABCD"))+(LEN(S89)<>1),"Answer must be A-D",IF(OR(D89<1,D89>3),"Difficulty must be 1-3",IF(OR(N89="",T89=""),"Missing question or explanation",IF(COUNTBLANK(U89:X89)<>1,"Need 3 why-not texts",IF(INDEX(U89:X89,1,FIND(UPPER(S89),"ABCD"))<>"","Why-not filled for the answer",IF(AND(B89<>"live",B89<>"draft",B89<>"retired"),"Status must be live/draft/retired","OK")))))))) -> OK
A90: KYC/RSK/223 | B90: live | C90: II | D90: 3 | E90: Category II regulated fund's paperwork | F90: Applicant | G90: Regulated fund from a non-FATF country | H90: Category | I90: II under Reg 5(b)(i) | J90: Question | K90: Which KYC set applies? | L90: BO format | M90: To be confirmed | N90: What documentation applies? | O90: Full Category II documentation, like any Category II FPI | P90: Category I-equivalent, BO in set format | Q90: No KYC; it's regulated | R90: Whatever its home regulator requires | S90: B | T90: Category II FPIs registered under Reg 5(b)(i), appropriately regulated funds not eligible for Category I, provide KYC documentation equivalent to Category I, but BO details must be given in the specified format. | U90: Reg 5(b)(i) funds get the lighter Category I-equivalent set. | W90: Regulated funds still go through KYC. | X90: Indian KYC rules set the documentation, not home rules. | Y90: SEBI Operational Guidelines for FPIs and DDPs, Part B 1, note (iii) | Z90: FPI Category – II registered under Regulation 5(b)(i), shall provide KYC documentation equivalent to FPI Category - I. However, BO details need to be provided in specified format. | AC90: Op. Guidelines Part B 1 (note iii) | AE90: Oct 2026 | AG90: =IF(A90="","",IF(COUNTA(O90:R90)<4,"Needs 4 options",IF(ISERROR(FIND(UPPER(S90),"ABCD"))+(LEN(S90)<>1),"Answer must be A-D",IF(OR(D90<1,D90>3),"Difficulty must be 1-3",IF(OR(N90="",T90=""),"Missing question or explanation",IF(COUNTBLANK(U90:X90)<>1,"Need 3 why-not texts",IF(INDEX(U90:X90,1,FIND(UPPER(S90),"ABCD"))<>"","Why-not filled for the answer",IF(AND(B90<>"live",B90<>"draft",B90<>"retired"),"Status must be live/draft/retired","OK")))))))) -> OK
A91: KYC/DOC/224 | B91: live | C91: II | D91: 2 | E91: No board resolution on file | F91: Applicant | G91: Category I pension fund | H91: Missing | I91: Board resolution and authorised signatory list | J91: Instead | K91: Power of attorney to its global custodian; instructions sent by SWIFT | L91: DDP asks | M91: Can we proceed? | N91: Can the DDP proceed? | O91: No. A board resolution is mandatory | P91: Yes. A power of attorney and SWIFT cover it | Q91: Only if the resolution follows within 30 days | R91: Only for Category II | S91: B | T91: A power of attorney granted to the global or local custodian is accepted in place of a board resolution, and the board resolution and authorised signatory list aren't required if SWIFT is used for instructions. | U91: The guidelines accept substitutes for the resolution. | W91: No later submission is required. | X91: The relief isn't limited to Category II. | Y91: SEBI Operational Guidelines for FPIs and DDPs, Part B 1, Table 4 note 2 | Z91: Power of Attorney granted to Global custodian/ local custodian is accepted in lieu of Board Resolution (BR). BR and the authorized signatory list (ASL) is not required if SWIFT is used as a medium of instruction. | AC91: Op. Guidelines Part B 1 (Table 4 note 2) | AE91: Oct 2026 | AG91: =IF(A91="","",IF(COUNTA(O91:R91)<4,"Needs 4 options",IF(ISERROR(FIND(UPPER(S91),"ABCD"))+(LEN(S91)<>1),"Answer must be A-D",IF(OR(D91<1,D91>3),"Difficulty must be 1-3",IF(OR(N91="",T91=""),"Missing question or explanation",IF(COUNTBLANK(U91:X91)<>1,"Need 3 why-not texts",IF(INDEX(U91:X91,1,FIND(UPPER(S91),"ABCD"))<>"","Why-not filled for the answer",IF(AND(B91<>"live",B91<>"draft",B91<>"retired"),"Status must be live/draft/retired","OK")))))))) -> OK
A92: KYC/REL/225 | B92: live | C92: II | D92: 3 | E92: Relying on the global custodian's KYC | F92: Local custodian | G92: Part of the same banking group as the FPI's global custodian | H92: Global custodian | I92: Regulated in a FATF country; did KYC to home standards | J92: Proposal | K92: Rely on that KYC for non-PAN documents | L92: Undertaking | M92: Offered | N92: What must the local custodian still do? | O92: Nothing more; reliance covers everything | P92: Collect constitution and BO papers; log it on the KRA | Q92: Redo all of the KYC from scratch itself | R92: Get SEBI approval for the reliance | S92: B | T92: For non-PAN KYC documents, a local custodian can rely on KYC by a same-group regulated entity from a FATF country, with an undertaking to produce documents on demand. It must still collect constitution documents and BO declarations, and upload evidence of the reliance to the KRA. | U92: Reliance doesn't cover constitution documents, BO declarations or KRA upload. | W92: Reliance is allowed, so full re-KYC isn't needed. | X92: No SEBI approval is needed. | Y92: SEBI Operational Guidelines for FPIs and DDPs, Part B 1, note (iv) | Z92: For non-PAN related KYC documents (including KYC form), a local custodian can rely on KYC carried out by another entity of the same financial group (like a Global Custodian or Investment Manager) which is regulated and coming from an FATF member country, where KYC is carried out as per their home jurisdiction standards. Where this reliance is placed, such entity/ FPI shall provide an undertaking to the effect that the relevant KYC documents, would be submitted to the DDP/ Local Custodian when required by regulator/law enforcement agency/ government departments/ tax authority, etc. However, the Custodian / local intermediary will be required to collect constitution documents and BO related declarations (wherever applicable) of the FPI and also, upload the evidence of KYC reliance on KRA. | AC92: Op. Guidelines Part B 1 (note iv) | AE92: Oct 2026 | AG92: =IF(A92="","",IF(COUNTA(O92:R92)<4,"Needs 4 options",IF(ISERROR(FIND(UPPER(S92),"ABCD"))+(LEN(S92)<>1),"Answer must be A-D",IF(OR(D92<1,D92>3),"Difficulty must be 1-3",IF(OR(N92="",T92=""),"Missing question or explanation",IF(COUNTBLANK(U92:X92)<>1,"Need 3 why-not texts",IF(INDEX(U92:X92,1,FIND(UPPER(S92),"ABCD"))<>"","Why-not filled for the answer",IF(AND(B92<>"live",B92<>"draft",B92<>"retired"),"Status must be live/draft/retired","OK")))))))) -> OK
A93: KYC/DOC/226 | B93: live | C93: II | D93: 1 | E93: Prospectus instead of a constitution | F93: Applicant | G93: Open-ended fund | H93: Constitutive document | I93: Not available as a separate official document | J93: Offered | K93: Its prospectus | L93: DDP | M93: Unsure | N93: Is the prospectus acceptable? | O93: No. Only official constitutive documents are accepted | P93: Yes. A prospectus is accepted | Q93: Only if notarised in India | R93: Only for Category I | S93: B | T93: A prospectus or information memorandum is acceptable in lieu of an official constitutional document. | U93: The guidelines accept a prospectus as a substitute. | W93: There's no Indian notarisation requirement here. | X93: It isn't limited to Category I. | Y93: SEBI Operational Guidelines for FPIs and DDPs, Part B 1, note (v) | Z93: Prospectus and Information Memorandum are acceptable in lieu of an official constitutional document. | AC93: Op. Guidelines Part B 1 (note v) | AE93: Oct 2026 | AG93: =IF(A93="","",IF(COUNTA(O93:R93)<4,"Needs 4 options",IF(ISERROR(FIND(UPPER(S93),"ABCD"))+(LEN(S93)<>1),"Answer must be A-D",IF(OR(D93<1,D93>3),"Difficulty must be 1-3",IF(OR(N93="",T93=""),"Missing question or explanation",IF(COUNTBLANK(U93:X93)<>1,"Need 3 why-not texts",IF(INDEX(U93:X93,1,FIND(UPPER(S93),"ABCD"))<>"","Why-not filled for the answer",IF(AND(B93<>"live",B93<>"draft",B93<>"retired"),"Status must be live/draft/retired","OK")))))))) -> OK
A94: KYC/PAN/227 | B94: live | C94: II | D94: 2 | E94: PAN for signatories and owners | F94: Applicant | G94: Category II fund | H94: DDP request | I94: PAN cards for every signatory, UBO and senior manager | J94: Applicant | K94: Has a PAN for the fund only | L94: Question | M94: Is the request right? | N94: What's required? | O94: PAN for every listed person | P94: PAN for the FPI only | Q94: No PAN at all for Category II | R94: PAN for each UBO above 25% | S94: B | T94: The FPI needs a PAN, which can be verified online or provided as an e-PAN without certification. PAN isn't mandatory for the FPI's UBOs, senior management or authorised signatories. | U94: The guidelines say PAN isn't mandatory for these individuals. | W94: Every FPI needs its own PAN, Category II included. | X94: There's no UBO PAN requirement at any threshold. | Y94: SEBI Operational Guidelines for FPIs and DDPs, Part B 1, note (vii) | Z94: Intermediary can verify the PAN of FPIs online from website authorized by the Income-Tax department. To clarify no certification of PAN document required from FPI. Alternatively, e-PAN issued by CBDT can also be produced by FPI for KYC compliance without requiring any certifications. In such situations where the broker is relying on KRA, it shall verify the PAN and download the available documents from KRA. PAN is not mandatory for UBO, senior management and authorized signatories of FPI. | AC94: Op. Guidelines Part B 1 (note vii); FPI Regs 2019, Reg 22(1)(f) | AE94: Oct 2026 | AG94: =IF(A94="","",IF(COUNTA(O94:R94)<4,"Needs 4 options",IF(ISERROR(FIND(UPPER(S94),"ABCD"))+(LEN(S94)<>1),"Answer must be A-D",IF(OR(D94<1,D94>3),"Difficulty must be 1-3",IF(OR(N94="",T94=""),"Missing question or explanation",IF(COUNTBLANK(U94:X94)<>1,"Need 3 why-not texts",IF(INDEX(U94:X94,1,FIND(UPPER(S94),"ABCD"))<>"","Why-not filled for the answer",IF(AND(B94<>"live",B94<>"draft",B94<>"retired"),"Status must be live/draft/retired","OK")))))))) -> OK
A95: KYC/BO/228 | B95: live | C95: II | D95: 3 | E95: Intermediate owner is a sovereign fund | F95: Applicant | G95: Category II fund | H95: Owner | I95: 40% held by a holding company | J95: Holding company | K95: Eligible for Category I under Reg 5(a)(i) | L95: DDP plan | M95: Look through the holding company to its natural persons | N95: Does the DDP need to look further through the holding company? | O95: Yes. Always look through to the natural persons | P95: No. That holding company is carved out | Q95: Only if it holds over 50% | R95: Only if the jurisdiction is high risk | S95: B | T95: BO identification uses a look-through basis for material intermediate owners. Where the intermediate owner is eligible as a Category I FPI under Reg 5(a)(i), no further identification of its beneficial owners is needed. | U95: The guidelines carve out Reg 5(a)(i) intermediate owners. | W95: The carve-out doesn't depend on a 50% holding. | X95: Jurisdiction risk doesn't change this carve-out. | Y95: SEBI Operational Guidelines for FPIs and DDPs, Part B 4(v) | Z95: In case the intermediate shareholder/ owner entity is eligible for registration as Category I FPI under Regulation 5(a)(i), there is no need for further identification and verification of beneficial owner of such intermediate shareholder/ owner entity. | AC95: Op. Guidelines Part B 4(v) | AE95: Oct 2026 | AG95: =IF(A95="","",IF(COUNTA(O95:R95)<4,"Needs 4 options",IF(ISERROR(FIND(UPPER(S95),"ABCD"))+(LEN(S95)<>1),"Answer must be A-D",IF(OR(D95<1,D95>3),"Difficulty must be 1-3",IF(OR(N95="",T95=""),"Missing question or explanation",IF(COUNTBLANK(U95:X95)<>1,"Need 3 why-not texts",IF(INDEX(U95:X95,1,FIND(UPPER(S95),"ABCD"))<>"","Why-not filled for the answer",IF(AND(B95<>"live",B95<>"draft",B95<>"retired"),"Status must be live/draft/retired","OK")))))))) -> OK
A96: KYC/BO/229 | B96: live | C96: II | D96: 2 | E96: Shares held by a law firm | F96: Applicant | G96: Company whose shares are registered to a law firm | H96: Law firm role | I96: Holds as nominee for clients | J96: BO list submitted | K96: Names the law firm's partners | L96: DDP | M96: Reviewing | N96: Is the BO list acceptable? | O96: Yes. The registered holders are the beneficial owners | P96: No. The real owners must be named | Q96: Yes, if the law firm is regulated | R96: Only if the partners sign an undertaking | S96: B | T96: Where companies or trusts are represented by service providers such as lawyers or accountants, the FPI must give details of the real owners or effective controllers. A BO can't be a nominee of another person. | U96: Nominees aren't beneficial owners. | W96: Regulation of the law firm doesn't change this. | X96: An undertaking doesn't replace identifying the real owners. | Y96: SEBI Operational Guidelines for FPIs and DDPs, Part B 4(vii) | Z96: In case of companies/ trusts represented by service providers like lawyers/ accountants, FPIs should provide information of the real owners/ effective controllers of those companies / trusts. If the BO exercises controls through means like voting rights, agreements, arrangement etc., that should also be specified. It is clarified that BO should not be a nominee of another person and real BO should be identified. | AC96: Op. Guidelines Part B 4(vii) | AE96: Oct 2026 | AG96: =IF(A96="","",IF(COUNTA(O96:R96)<4,"Needs 4 options",IF(ISERROR(FIND(UPPER(S96),"ABCD"))+(LEN(S96)<>1),"Answer must be A-D",IF(OR(D96<1,D96>3),"Difficulty must be 1-3",IF(OR(N96="",T96=""),"Missing question or explanation",IF(COUNTBLANK(U96:X96)<>1,"Need 3 why-not texts",IF(INDEX(U96:X96,1,FIND(UPPER(S96),"ABCD"))<>"","Why-not filled for the answer",IF(AND(B96<>"live",B96<>"draft",B96<>"retired"),"Status must be live/draft/retired","OK")))))))) -> OK
A97: KYC/BO/230 | B97: live | C97: II | D97: 2 | E97: Beneficial owners of a limited partnership | F97: Applicant | G97: Limited partnership fund | H97: General partner | I97: Controls all decisions; holds 1% | J97: Largest LP | K97: Holds 30% of commitments | L97: DDP | M97: Deciding how to identify BOs | N97: On what basis are BOs identified? | O97: Ownership only, so the general partner is ignored | P97: Both ownership or entitlement and control | Q97: Control only, so only the general partner | R97: Whoever signed the subscription agreement | S97: B | T97: For FPIs with a general partner and limited partnership structure, beneficial owners are identified on both an ownership or entitlement basis and a control basis. | U97: Control matters too, so the general partner can't be ignored. | W97: Ownership matters too, so large LPs count. | X97: Signing the subscription agreement doesn't define BO status. | Y97: SEBI Operational Guidelines for FPIs and DDPs, Part B 4(ii) | Z97: BOs of FPIs having General Partner/Limited Partnership structure shall be identified on ownership or entitlement basis and control basis. | AC97: Op. Guidelines Part B 4(ii) | AE97: Oct 2026 | AG97: =IF(A97="","",IF(COUNTA(O97:R97)<4,"Needs 4 options",IF(ISERROR(FIND(UPPER(S97),"ABCD"))+(LEN(S97)<>1),"Answer must be A-D",IF(OR(D97<1,D97>3),"Difficulty must be 1-3",IF(OR(N97="",T97=""),"Missing question or explanation",IF(COUNTBLANK(U97:X97)<>1,"Need 3 why-not texts",IF(INDEX(U97:X97,1,FIND(UPPER(S97),"ABCD"))<>"","Why-not filled for the answer",IF(AND(B97<>"live",B97<>"draft",B97<>"retired"),"Status must be live/draft/retired","OK")))))))) -> OK
A98: KYC/REV/231 | B98: live | C98: II | D98: 3 | E98: How often to review KYC | F98: FPI | G98: Category II unregulated corporate body | H98: Jurisdiction | I98: Not high risk | J98: Custodian diary | K98: Review every three years at continuance | L98: Question | M98: Is three years right? | N98: What's the review cycle? | O98: Every three years, at continuance | P98: Annually | Q98: Every ten years | R98: Only when something changes | S98: B | T98: Under the guidelines' review table, Category II regulated entities are reviewed at continuance (every three years), while other Category II FPIs are reviewed annually. SWAGAT-FIs and GS-FPIs follow their own later rules. | U98: Three years applies to regulated Category II entities, not this one. | W98: Ten years is the SWAGAT-FI cycle. | X98: Reviews are periodic, not just event-driven. | Y98: SEBI Operational Guidelines for FPIs and DDPs, Part B 5, Table 6 (table reformatted) | Z98: Periodic KYC review (Table 6). FPI Category I, high-risk jurisdiction: registered under Regulation 5(a)(i), during continuance of registration i.e. every 3 years; others, annually. FPI Category I, non-high-risk: during continuance of registration i.e. every 3 years. FPI Category II: regulated entities during continuance of registration i.e. every 3 years; others, annually. | AC98: Op. Guidelines Part B 5 (Table 6) | AE98: Oct 2026 | AG98: =IF(A98="","",IF(COUNTA(O98:R98)<4,"Needs 4 options",IF(ISERROR(FIND(UPPER(S98),"ABCD"))+(LEN(S98)<>1),"Answer must be A-D",IF(OR(D98<1,D98>3),"Difficulty must be 1-3",IF(OR(N98="",T98=""),"Missing question or explanation",IF(COUNTBLANK(U98:X98)<>1,"Need 3 why-not texts",IF(INDEX(U98:X98,1,FIND(UPPER(S98),"ABCD"))<>"","Why-not filled for the answer",IF(AND(B98<>"live",B98<>"draft",B98<>"retired"),"Status must be live/draft/retired","OK")))))))) -> OK
A99: KYC/DOC/232 | B99: live | C99: II | D99: 1 | E99: Certificate in Japanese | F99: Applicant | G99: Japanese pension fund | H99: Proof of identity | I99: Issued in Japanese | J99: DDP asks | K99: Is it acceptable as is? | L99: Other documents | M99: In English | N99: What's needed? | O99: Nothing; any language works | P99: An English translation | Q99: A Hindi translation | R99: A fresh document issued in English by the regulator | S99: B | T99: If any proof of identity or address is in a foreign language, a translation into English is required. | U99: The guidelines require translation for foreign-language documents. | W99: The requirement is English, not Hindi. | X99: A translation suffices; reissue isn't required. | Y99: SEBI Operational Guidelines for FPIs and DDPs, Part B 8(ii) | Z99: If any proof of identity or address is in a foreign language, then translation into English is required. | AC99: Op. Guidelines Part B 8(ii) | AE99: Oct 2026 | AG99: =IF(A99="","",IF(COUNTA(O99:R99)<4,"Needs 4 options",IF(ISERROR(FIND(UPPER(S99),"ABCD"))+(LEN(S99)<>1),"Answer must be A-D",IF(OR(D99<1,D99>3),"Difficulty must be 1-3",IF(OR(N99="",T99=""),"Missing question or explanation",IF(COUNTBLANK(U99:X99)<>1,"Need 3 why-not texts",IF(INDEX(U99:X99,1,FIND(UPPER(S99),"ABCD"))<>"","Why-not filled for the answer",IF(AND(B99<>"live",B99<>"draft",B99<>"retired"),"Status must be live/draft/retired","OK")))))))) -> OK
A100: KYC/DOC/233 | B100: live | C100: II | D100: 2 | E100: How recent must address proof be? | F100: Applicant | G100: Individual Category II investor | H100: Offered | I100: Electricity bill dated three months ago | J100: Alternative | K100: Bank statement dated ten weeks ago | L100: DDP | M100: Checking validity | N100: Which can the DDP accept? | O100: Both of them | P100: The bank statement only | Q100: The utility bill only | R100: Neither of them | S100: B | T100: Utility bills used as address proof must be no more than two months old, and bank statements no more than three months old. Ten weeks is within three months, so the statement works. | U100: The utility bill is over the two-month limit. | W100: It's the other way round. | X100: The bank statement is within its three-month limit. | Y100: SEBI Operational Guidelines for FPIs and DDPs, Part B 9(B) | Z100: Utility bills like Telephone Bill, Electricity bill or Gas bill - Not more than 2 months old. Bank Account Statement/Passbook/letter -- Not more than 3 months old. | AC100: Op. Guidelines Part B 9(B) | AE100: Oct 2026 | AG100: =IF(A100="","",IF(COUNTA(O100:R100)<4,"Needs 4 options",IF(ISERROR(FIND(UPPER(S100),"ABCD"))+(LEN(S100)<>1),"Answer must be A-D",IF(OR(D100<1,D100>3),"Difficulty must be 1-3",IF(OR(N100="",T100=""),"Missing question or explanation",IF(COUNTBLANK(U100:X100)<>1,"Need 3 why-not texts",IF(INDEX(U100:X100,1,FIND(UPPER(S100),"ABCD"))<>"","Why-not filled for the answer",IF(AND(B100<>"live",B100<>"draft",B100<>"retired"),"Status must be live/draft/retired","OK")))))))) -> OK
A101: KYC/DOC/234 | B101: live | C101: II | D101: 2 | E101: Who can attest copies? | F101: Applicant | G101: Category II family office | H101: Originals | I101: Not available for verification | J101: Copies attested by | K101: Its own company secretary | L101: DDP | M101: Checking | N101: Are the copies acceptable? | O101: Yes. Any of its own officers can attest copies | P101: No. Only a notary or authorised bank official | Q101: Yes, if the FPI self-certifies too | R101: Only if apostilled in India | S101: B | T101: Where originals aren't produced, copies must be attested by authorised persons: a notary public, or officials of multinational foreign banks or banks regulated by RBI, with name, designation and seal. | U101: An in-house officer isn't an authorised attester. | W101: Self-certification is no longer required, and doesn't replace attestation. | X101: Indian apostille isn't the stated route. | Y101: SEBI Operational Guidelines for FPIs and DDPs, Part B 8(i) | Z101: Copies of all the documents submitted by the applicant should be accompanied by originals for verification. In case the original of any document is not produced for verification, then the copies should be properly attested by entities authorized for attesting the documents. | AA101: SEBI Operational Guidelines for FPIs and DDPs, Part B 8(viii) | AB101: List of people authorized to attest the documents: Notary Public, officials of Multinational Foreign Banks or any Bank regulated by Reserve Bank of India (Name, Designation & Seal should be affixed on the copy). | AC101: Op. Guidelines Part B 8(i), (viii) | AE101: Oct 2026 | AG101: =IF(A101="","",IF(COUNTA(O101:R101)<4,"Needs 4 options",IF(ISERROR(FIND(UPPER(S101),"ABCD"))+(LEN(S101)<>1),"Answer must be A-D",IF(OR(D101<1,D101>3),"Difficulty must be 1-3",IF(OR(N101="",T101=""),"Missing question or explanation",IF(COUNTBLANK(U101:X101)<>1,"Need 3 why-not texts",IF(INDEX(U101:X101,1,FIND(UPPER(S101),"ABCD"))<>"","Why-not filled for the answer",IF(AND(B101<>"live",B101<>"draft",B101<>"retired"),"Status must be live/draft/retired","OK")))))))) -> OK
A102: KYC/IPV/235 | B102: live | C102: II | D102: 1 | E102: In-person verification for a fund | F102: Applicant | G102: Luxembourg fund | H102: DDP plan | I102: Arrange in-person verification of the fund | J102: Individuals involved | K102: Directors abroad | L102: Question | M102: Is IPV needed? | N102: Does in-person verification apply? | O102: Yes, for every FPI applicant | P102: No. Not for non-individual clients | Q102: Yes, by video for each director | R102: Only if the fund is Category II | S102: B | T102: In-person verification isn't applicable for non-individual clients. For individual clients, it can be done by web camera. | U102: IPV doesn't apply to non-individuals. | W102: Video IPV is for individual clients. | X102: Category doesn't change this. | Y102: SEBI Operational Guidelines for FPIs and DDPs, Part B 8(vi) | Z102: In person verification is not applicable for a non-individual Client. IPV for individual clients through web camera shall be allowed. | AC102: Op. Guidelines Part B 8(vi) | AE102: Oct 2026 | AG102: =IF(A102="","",IF(COUNTA(O102:R102)<4,"Needs 4 options",IF(ISERROR(FIND(UPPER(S102),"ABCD"))+(LEN(S102)<>1),"Answer must be A-D",IF(OR(D102<1,D102>3),"Difficulty must be 1-3",IF(OR(N102="",T102=""),"Missing question or explanation",IF(COUNTBLANK(U102:X102)<>1,"Need 3 why-not texts",IF(INDEX(U102:X102,1,FIND(UPPER(S102),"ABCD"))<>"","Why-not filled for the answer",IF(AND(B102<>"live",B102<>"draft",B102<>"retired"),"Status must be live/draft/retired","OK")))))))) -> OK
A103: KYC/REC/236 | B103: live | C103: II | D103: 2 | E103: Keeping KYC after the client leaves | F103: Custodian | G103: Closing an FPI's account in 2026 | H103: Litigation | I103: A tax case involving the FPI is pending | J103: Question | K103: How long to keep KYC records? | L103: Format | M103: Originals | N103: What's the rule? | O103: One year after the account is closed | P103: Five years from cessation, or until the case ends | Q103: Until the next audit | R103: They can be destroyed at closure | S103: B | T103: The custodian keeps KYC records in original for at least five years from the date transactions with the FPI cease. If litigation is pending, records are kept until proceedings end. | U103: The minimum is five years, not one. | W103: Audits don't set the retention period. | X103: Records must be kept after closure. | Y103: SEBI Operational Guidelines for FPIs and DDPs, Part B 7 | Z103: The Custodian should maintain the KYC records in original for a minimum period of five years from the date of cessation of the transactions with the said FPI. In case any litigation is pending, these records should be maintained till the completion of the proceedings. | AC103: Op. Guidelines Part B 7 | AE103: Oct 2026 | AG103: =IF(A103="","",IF(COUNTA(O103:R103)<4,"Needs 4 options",IF(ISERROR(FIND(UPPER(S103),"ABCD"))+(LEN(S103)<>1),"Answer must be A-D",IF(OR(D103<1,D103>3),"Difficulty must be 1-3",IF(OR(N103="",T103=""),"Missing question or explanation",IF(COUNTBLANK(U103:X103)<>1,"Need 3 why-not texts",IF(INDEX(U103:X103,1,FIND(UPPER(S103),"ABCD"))<>"","Why-not filled for the answer",IF(AND(B103<>"live",B103<>"draft",B103<>"retired"),"Status must be live/draft/retired","OK")))))))) -> OK
...

Sheet How to use
B2: Custody Desk League · Question bank
B3: One row per question on the Questions sheet. Only rows with status = live reach players.
B5: Step | C5: What to do
B6: Edit | C6: Work on the Questions sheet. Yellow columns are yours to fill; the grey Check column fills itself.
B7: Review drafts | C7: New questions arrive as status = draft. Read each one, fix anything, then change status to live.
